Workbook

Sheet Client ID Records_v1
A1: Date Received | B1: Client Name | C1: Assigned Sex At Birth | D1: Client ID Number | F1: Status | G1: Designation | H1: Institution | I1: Department / Laboratory | J1: Telephone Number | K1: Mobile Number | L1: Fax Number | M1: Email Address | N1: Mailing Address
A2: 2019
A3: 43873 | B3: Philippine Genome Center Visayas | D3: CL-2019- | E3: 000 | F3: Ongoing
A4: 2020
A5: 43873 | B5: Nowena S. Solidum | C5: F | D5: CL-2020- | E5: 1 | F5: Completed | G5: Instructor | H5: Capiz State University | I5: Fishery Department | J5: N/A | K5: 9983950535 | L5: N/A | M5: nowena_solidum@yahoo.com | N5: Fishery Department, Capiz State University - Dayao Satellite College, Dayao, Roxas City, Capiz
A6: 43873 | B6: Marissa C. Naorbe | C6: F | D6: CL-2020- | E6: 2 | F6: Completed | G6: Instructor | H6: Capiz State University | I6: Fishery Department | J6: N/A | K6: 9506798777 | L6: N/A | M6: castromarissa99@gmail.com | N6: Fishery Department, Capiz State University - Dayao Satellite College, Dayao, Roxas City, Capiz
A7: 43873 | B7: Shirleen Grace Brillantes | C7: F | D7: CL-2020- | E7: 3 | F7: Completed | G7: Faculty | H7: Samar State University | I7: Marine Biology | J7: N/A | K7: 9177145364 | L7: N/A | M7: sweetbrillantes@gmail.com | N7: Samar State University - Mercedes, Mercedes, Catbalogan City, Samar 6700
A8: 43873 | B8: Irene Jean C. Lagumbay | C8: F | D8: CL-2020- | E8: 4 | F8: Completed | G8: Instructor I | H8: Samar State University | I8: Marine Biology | J8: N/A | K8: 9165866013 | L8: N/A | M8: irenelagumbay95@gmail.com | N8: Talisay, Bontoc, Southern Leyte
A9: 43873 | B9: Rhodmar D. Panis | C9: M | D9: CL-2020- | E9: 5 | F9: Completed | G9: SRS I | H9: Samar State University | I9: OVPRES/ Micro Lab | J9: N/A | K9: 9056728581 | L9: N/A | M9: rhodmar.divino@ssu.up.edu.ph | N9: N/A
A10: 43873 | B10: Jay T. Torrefiel | C10: M | D10: CL-2020- | E10: 6 | F10: Completed | G10: Instructor | H10: UPV Tacloban College | I10: DNSM | J10: N/A | K10: 9058848900 | L10: N/A | M10: jattorrefiel@gmail.com | N10: 779 San Mateo St., Brangay 4, Jaro, Leyte
A11: 43873 | B11: Rhyzz Jane Balinos | C11: F | D11: CL-2020- | E11: 7 | F11: Completed | G11: Laboratory Aide | H11: UP Visayas | I11: CFOS IA (DOST TGMPPEFET) | J11: N/A | K11: 9666553130 | L11: N/A | M11: rhyzz.jane@gmail.com | N11: Bolho, Miagao, Iloilo
A12: 43873 | B12: Mary Antonette F. Atilano | C12: F | D12: CL-2020- | E12: 8 | F12: Completed | G12: University Research Associate I | H12: UP Visayas | I12: CFOS IA (DOST TGMPPEFET) | J12: N/A | K12: 9062227281 | L12: N/A | M12: atilanomaryantonette@gmail.com | N12: N/A
A13: 43874 | B13: Alvin M. Doroteo | C13: M | D13: CL-2020- | E13: 9 | F13: Completed | G13: Instructor I | H13: University of Antique | I13: COFES | J13: N/A | K13: 9272051528 | L13: N/A | M13: doroteoalvin@yahoo.com | N13: N/A
A14: 43902 | B14: Rema C. Sibonga | C14: F | D14: CL-2020- | E14: 10 | F14: Completed | G14: Early Career Researcher | H14: UP Visayas | I14: GlobalSeaweedSTARProejct, CFOS IA | J14: N/A | K14: 09171409960; 09985315320 | L14: N/A | M14: rcsibonga@gmail.com | N14: Institute of Aquaculture, College of Fisheries and Ocean Sciences, University of the Philippines Visayas, Miagao, 5023, Iloilo
A15: 43903 | B15: Karen Claire S. Ebreo | C15: F | D15: CL-2020- | E15: 11 | F15: Completed | G15: Research Assistant | H15: UP Visayas | I15: Taklong Barcoding Initiative, Marine Biodiversity and Evolution Lab, Division of Biological Sciences | J15: (033) 315 8160 | K15: 9174290778 | L15: N/A | M15: ksebreo@up.edu.ph | N15: Room 124, CAS Bldg., Division of Biological Sciences, College of Arts and Sciences, University of the Philippines Visayas, Miagao, Iloilo
A16: 43990 | B16: Kyle R. Castañares | C16: M | D16: CL-2020- | E16: 12 | F16: Completed | G16: University Research Associate I | H16: UP Visayas | I16: CFOS IA (DOST TGMPPEFET) | J16: N/A | K16: 9171669790 | L16: N/A | M16: kyleresmac@gmail.com | N16: IA-Hatchery Complex, University of the Philippines Visayas, Miagao 5023, Iloilo
A17: 43990 | B17: Angel Queenee D. Dequito | C17: F | D17: CL-2020- | E17: 13 | F17: Completed | G17: Assistant Professor/Project Leader | H17: UP Visayas | I17: CFOS IA (DOST TGMPPEFET) | J17: N/A | K17: 9177212519 | L17: N/A | M17: addequito@up.edu.ph | N17: CFOS-IA, UP Visayas, Miagao, Iloilo
A18: 44015 | B18: Nadalene Faith N. Cartago | C18: F | D18: CL-2020- | E18: 14 | F18: Completed | G18: MS Fisheries (Aquaculture) | H18: UP Visayas | I18: CFOS IA | J18: N/A | K18: 9452398275 | L18: N/A | M18: nadelenefaithcartago@yahoo.com | N18: 42 Quezon Street, Miagao, Iloilo
A19: 44015 | B19: Karl Angelo P. Tenizo | C19: M | D19: CL-2020- | E19: 15 | F19: Ongoing | G19: Science Research Assistant | H19: UP Visayas | I19: CFOS IA ("Ice-ice Project" | J19: N/A | K19: 9983085275 | L19: N/A | M19: kptenizo@up.edu.ph | N19: Nonato's Extension, Brgy. Baybay Norte, Miagao, Iloilo
A20: 44034 | B20: Gabrielle Troy A. Cuevas | C20: M | D20: CL-2020- | E20: 16 | F20: Completed | G20: Assistant Professor/Project Leader | H20: UP Visayas | I20: Department of Chemistry | J20: N/A | K20: 9953856717 | L20: N/A | M20: gacuevas@up.edu.ph | N20: Department of Chemistry, College of Arts and Sciences, UP Visayas
A21: 44034 | B21: Wilson F. Medrocillo | C21: M | D21: CL-2020- | E21: 17 | F21: Completed | G21: Research Assistant | H21: UP Visayas | I21: Department of Chemistry | J21: N/A | K21: 936981029 | L21: N/A | M21: wfmedrocillo@up.edu.ph | N21: RA Lounge, CAS Basement, College of Arts and Sciences, UP Visayas
A22: 44035 | B22: Leonilo F. Endoma | C22: M | D22: CL-2020- | E22: 18 | F22: Cancelled | G22: Faculty | H22: UP Visayas | I22: CFOS IFPT Chemistry Lab | J22: N/A | K22: 9152715677 | L22: N/A | M22: lfendoma@up.edu.ph
A23: 44048 | B23: Dominique P. Mediodia | C23: M | D23: CL-2020- | E23: 19 | F23: Completed | G23: Instructor/Project Leader | H23: UP Visayas | J23: N/A | K23: 9267259050 | L23: N/A | M23: dpmediodia@up.edu.ph | N23: UPV Museum of Natural Sciences, UP Visayas, Miagao, Iloilo 5023
A24: 44048 | B24: Ma. Novem Grace Ylayron | C24: F | D24: CL-2020- | E24: 20 | F24: Completed | G24: Research Assistant | H24: UP Visayas | I24: CFOS IMFO/MFPA Project | J24: N/A | K24: 9292671029 | L24: N/A | M24: maylayron@up.edu.ph | N24: UPV CFOS IMFO
A25: 44048 | B25: Carmelo del Castillo | C25: M | D25: CL-2020- | E25: 21 | F25: Ongoing | G25: Assistant Professor | H25: UP Visayas | I25: CFOS IA | J25: N/A | K25: 9177110107 | L25: N/A | M25: csdelcastillo@up.edu.ph | N25: UPV
A26: 44062 | B26: Pretty Lee Silva | C26: F | D26: CL-2020- | E26: 22 | F26: Cancelled | G26: Faculty | H26: UP Visayas | I26: SOTECH/MS Chem Eng (Diliman)
A27: 44131 | B27: Loina Henzel A. Delgado | C27: F | D27: CL-2020- | E27: 023 | F27: Completed | G27: Student Assistant | H27: Samar State University | I27: Taklong Barcoding Initiative, Marine Biodiversity and Evolution Lab, Division of Biological Sciences | J27: (033) 315 8160 | K27: 9300953925 | L27: N/A | M27: ladelgado1@up.edu.ph | N27: Room 124, CAS Bldg., Division of Biological Sciences, College of Arts and Sciences, University of the Philippines Visayas, Miagao, Iloilo
A28: 44168 | B28: Denise V. Miranda | C28: F | D28: CL-2020- | E28: 024 | F28: Ongoing | G28: University Research Associate I | H28: UP Visayas | I28: CFOS IA (DOST Ice-Ice | J28: N/A | K28: 09777305977 | L28: N/A | M28: dvmiranda@up.edu.ph | N28: #49 Tajanlangit St., Brgy. Tacas, Miagao, Iloilo
A29: 2021
A30: 44216 | B30: Alain C. Juayang | C30: M | D30: CL-2021- | E30: 25 | F30: Completed | G30: Section Head | H30: Corazon Locsin Montelibano Memorial Regional Hospital | I30: Molecular Laboratory | J30: N/A | K30: 09226942501 | L30: N/A | M30: alainjuayang@yahoo.com | N30: Molecular Laboratory, Corazon L. Montelibano Memorial Regional Hospital, Burgos-Lacson St., Bacolod City
A31: 44216 | B31: Jezreel Teruel Ywayan | C31: F | D31: CL-2021- | E31: 26 | F31: Completed | G31: Chief Medical Technologist | H31: Bacolod Queen of Mercy Hospital | I31: Molecular Laboratory | J31: N/A | K31: 09231531678 | L31: N/A | M31: jbtywayanmolecular2020@gmail.com | N31: Bacolod Queen of Mercy Hospital Molecular Laboratory, LN Eroreco Drive, Mandalagan, Bacolod City 6100
A32: 44250 | B32: Leni G. Yap-Dejeto | C32: F | D32: CL-2021- | E32: 27 | F32: Completed | G32: Professor 6 | H32: UPV Tacloban College | I32: Division of Natural Science and Mathematics | J32: +6353 3218299 | K32: +639368135357 | L32: 6353 3255108 | M32: lgyapdejeto@up.edu.ph | N32: UPV Tacloban College, Magsaysay Blvd., Tacloban City, Leyte 6500
A33: 44280 | B33: Dianne Frances Penuela | C33: F | D33: CL-2021- | E33: 28 | F33: Completed | G33: Science Research Assistant | H33: UP Visayas | I33: Division of Biological Sciences | J33: 323 2733 | K33: 09052565544 | L33: N/A | M33: dapenuela@up.edu.ph | N33: Brgy. Abangay, Dingle, Iloilo
A34: 44280 | B34: Roxanne Cabebe | C34: F | D34: CL-2021- | E34: 29 | F34: Completed | G34: Science Research Assistant | H34: UP Visayas | I34: Division of Biological Sciences | J34: N/A | K34: 09760511920 | L34: N/A | M34: racabebe@up.edu.ph | N34: Brgy. Mat-y, Miagao, Iloilo
A35: 44302 | B35: Albert C. Noblezada | C35: M | D35: CL-2021- | E35: 30 | F35: Completed | G35: MS Fisheries (Aquaculture) | H35: UP Visayas | I35: CFOS IA | J35: N/A | K35: 09165448358 | L35: N/A | M35: acnoblezada@up.edu.ph | N35: Brgy. Buenavista, Leon, Iloilo
A36: 44334 | B36: Arlene L . Avillanosa | C36: F | D36: CL-2021- | E36: 31 | F36: Ongoing | G36: Project Leader | H36: Western Philippines University | I36: WPU GeM-PHIL Project | J36: N/A | K36: 09278173880 | L36: N/A | M36: arlene.avillanosa@wpu.edu.ph | N36: Room 9, Second Floor (ABBA R&D Center), College of Fisheries and Aquatic Science (CFAS), WPU-Puerto Princesa Campus, Sta. Monica, Puerto Princesa City
A37: 44334 | B37: Reymart S. Dagaraga | C37: M | D37: CL-2021- | E37: 32 | F37: Ongoing | G37: University Research Associate | H37: Western Philippines University | I37: WPU GeM-PHIL Project | J37: N/A | K37: 09678700527 09475042638 09958698243 | L37: N/A | M37: gemphilproject@gmail.com | N37: Room 9, Second Floor (ABBA R&D Center), College of Fisheries and Aquatic Science (CFAS), WPU-Puerto Princesa Campus, Sta. Monica, Puerto Princesa City
A38: 44334 | B38: Jasper D. Pacho | C38: M | D38: CL-2021- | E38: 33 | F38: Ongoing | G38: Science Research Assistant | H38: Western Philippines University | I38: WPU GeM-PHIL Project | J38: N/A | K38: 09507960935 | L38: N/A | M38: jasperpacho181@gmail.com | N38: Room 9, Second Floor (ABBA R&D Center), College of Fisheries and Aquatic Science (CFAS), WPU-Puerto Princesa Campus, Sta. Monica, Puerto Princesa City
A39: 44382 | B39: Kristina Samantha Lacson | C39: F | D39: CL-2021- | E39: 34 | F39: Completed | G39: Research Assistant | H39: UP Visayas | I39: Department of Chemistry | J39: N/A | K39: 09561765997 | L39: N/A | M39: kblacson@up.edu.ph | N39: College of Arts and Sciences (CAS) Buidling, University of the Philippines Visayas, Miagao, Iloilo 5023
A40: 44382 | B40: Concepcion Ponce | C40: F | D40: CL-2021- | E40: 35 | F40: Completed | G40: Project Leader | H40: UP Visayas | I40: Department of Chemistry | J40: N/A | K40: 09951970469 | L40: N/A | M40: cpponce@upv.edu.ph | N40: College of Arts and Sciences (CAS) Buidling, University of the Philippines Visayas, Miagao, Iloilo 5023
A41: 44435 | B41: Carolyn T. Mejares | C41: F | D41: CL-2021- | E41: 36 | F41: Cancelled | G41: Faculty | H41: School of Technology, UP Visayas | I41: N/A | J41: N/A | K41: 09174804428 | L41: N/A | M41: ctmejares@up.edu.ph | N41: School of Technology, University of the Philippines Visayas, Miagao, Iloilo
A42: 2022
A43: 44580 | B43: Rowena E. Cadiz | C43: F | D43: CL-2022- | E43: 37 | F43: Cancelled | G43: University Research Associate II | H43: UP Visayas | I43: CFOS IA | J43: N/A | L43: N/A | M43: recadiz@up.edu.ph | N43: Institute of Aquaculutre, College of Fisheries and Ocean Science, University of the Philippines Visayas, Miagao, Iloilo
A44: 44622 | B44: Eric Zeus C. Rizo | C44: M | D44: CL-2022- | E44: 38 | F44: Ongoing | G44: Project Leader | H44: UP Visayas | I44: Division of Biological Sciences | J44: N/A | K44: 09153101800 | L44: N/A | M44: ecrizo@up.edu.ph | N44: Neki's Bldg., Zulueta Ave., Brgy. Ubos-Ilawod, Miagao, Iloilo
A45: 44622 | B45: Shea Kathleen P. Guinto | C45: F | D45: CL-2022- | E45: 39 | F45: Ongoing | G45: Science Research Assistant | H45: UP Visayas | I45: Ocean Bio Lab | J45: N/A | K45: 09178587562 | L45: N/A | M45: spguinto@up.edu.ph | N45: Neki's Bldg., Zulueta Ave., Brgy. Ubos-Ilawod, Miagao, Iloilo
A46: 44622 | B46: Rother M. Gaudiel | C46: M | D46: CL-2022- | E46: 40 | F46: Completed | G46: MS Fisheries (Aquaculture) | H46: UP Visayas | I46: CFOS IMFO | J46: 333158851 | K46: 09569874648 | L46: N/A | M46: rmgaudiel@up.edu.ph | N46: rmgaudiel@up.edu.ph
A47: 44624 | B47: John Rey F. Rasgo | C47: M | D47: CL-2022- | E47: 41 | F47: Completed | G47: BS Fisheries IV | H47: UP Visayas | I47: CFOS IMFO | J47: N/A | K47: 09612217613 | L47: N/A | M47: jfrasgo@up.edu.ph | N47: Noble Apartment, Hinolan St., Brgy. Baybay Sur, Miagao, Iloilo
A48: 44628 | B48: Luke Dranoel D. Atencio | C48: M | D48: CL-2022- | E48: 42 | F48: Completed | G48: University Researcher I | H48: UP Visayas | I48: OVCRE-RRC | J48: N/A | K48: 09958160186 | L48: N/A | M48: ldatencio@up.edu.ph | N48: Regional Research Center, New Academic Complex, University of the Philippines Visayas, Miagao, Iloilo
A49: 44634 | B49: Whelver N. Surnido | C49: M | D49: CL-2022- | E49: 43 | F49: Completed | G49: Science Research Assistant | H49: UP Visayas | I49: CFOS IA | J49: N/A | K49: 0936618579 | L49: N/A | M49: wnsurnido@up.edu.ph | N49: GN Boarding House, Nonato Ext. Street, Baybay Norte, Miagao, Iloilo
A50: 44644 | B50: Kingsley John de los Santos | C50: M | D50: CL-2022- | E50: 44 | F50: Completed | G50: MS Biology | H50: UP Visayas | I50: Division of Biological Sciences | J50: N/A | K50: 09995569350 | L50: N/A | M50: kdelossantos@up.edu.ph | N50: 117 Queszon St., Mat-y, 5023 Miagao, Iloilo
A51: 44645 | B51: Karl C. Abismo | C51: M | D51: CL-2022- | E51: 45 | F51: Completed | G51: BS Fisheries IV | H51: UP Visayas | I51: CFOS IA | J51: N/A | K51: 09458533418 | L51: N/A | M51: kcabismo@up.edu.ph | N51: 482 Aqunio Nobleza West, Janiuay, Iloilo
A52: 44663 | B52: Stephen G. Sabinay | C52: M | D52: CL-2022- | E52: 46 | F52: Completed | G52: Center Head | H52: West Visayas State University | I52: Center for Biotech and Biomedical Research, College of Medicine | J52: N/A | K52: 09983115444 | L52: N/A | M52: ssabinay@wvsu.edu.ph | N52: 4th Floor, Roxas Hall Annex, College of Medicine, West Visayas State University, La Paz, Iloilo City
A53: 44680 | B53: Benedict Maralit | C53: M | D53: CL-2022- | E53: 47 | F53: Completed
A54: 44680 | B54: Philip Alviola | C54: M | D54: CL-2022- | E54: 48 | F54: Ongoing
A55: 44705 | B55: Isabel Grace Gatpatan | C55: F | D55: CL-2022- | E55: 49 | F55: Completed | G55: Research Assistant | H55: UP Visayas | I55: College of Arts and Sciences | J55: N/A | K55: 09507678137 | L55: N/A | M55: isabelagrasya@gmail.com | N55: N/A
A56: 44718 | B56: Camille Rose T. Mueda | C56: F | D56: CL-2022- | E56: 50 | F56: Completed | G56: MS Molecular Biology and Biotechnology | H56: UP Los Banos | I56: Institute of Biological Sciences | J56: N/A | K56: 09086043843 | L56: N/A | M56: ctmueda@up.edu.ph | N56: Zulueta Ave., Miagao, Iloilo
A57: 44725 | B57: Beverly T. Jaspe | C57: F | D57: CL-2022- | E57: 51 | F57: Completed | G57: Project Leader, Diwal Project | H57: Aklan State University - New Washington Campus | I57: Fisheries and Marine Sciences Department
A58: 44729 | B58: Zeth Rodario Bebit | C58: M | D58: CL-2022- | E58: 52 | F58: Completed | G58: Research Assistant | H58: UP Visayas | I58: Department of Chemistry | J58: N/A | K58: N/A | L58: N/A | M58: N/A | N58: Department of Chemistry, College of Arts and Sciences, UP Visayas, Miagao, Iloilo 5023
A59: 44725 | B59: Kneessa Louie G. Dato-on | C59: F | D59: CL-2022- | E59: 53 | F59: Completed | G59: MS Microbiology Student | H59: UP Los Banos | I59: Institute of Biological Sciences | J59: N/A | K59: 09563167064 | L59: N/A | M59: kgdatoon@up.edu.ph | N59: N/A
A60: 44733 | B60: Leogiver G. Mañosca | C60: M | D60: CL-2022- | E60: 54 | F60: Completed | G60: Faculty | H60: Philippine Science High School - MIMAROPA Region Campus | I60: N/A | J60: N/A | K60: N/A | L60: N/A | M60: N/A | N60: Brgy. Rizal, Odiongan Romblon
A61: 44763 | B61: Rhudith Cabulong | C61: F | D61: CL-2022- | E61: 55 | F61: Completed | G61: Assistant Professor | H61: UP Visayas | I61: College of Arts and Sciences | J61: N/A | K61: N/A | L61: N/A | M61: rbcabulong@up.edu.ph | N61: Microbiology Laboratory, College of Arts and Sciences, University of the Philippines Visayas, 5023 Miagao, Iloilo
A62: 44785 | B62: Viva Princess A. Basa | C62: F | D62: CL-2022- | E62: 56 | F62: Completed | G62: SRA | H62: MIndoro State University | I62: Research and Development Extension | J62: N/A | K62: 9065278053 | L62: N/A | M62: vivaprincessbasa@icloud.com | N62: Pinagsabangan II, Curva Naujan, 5204 , Orien Mindoro
A63: 44785 | B63: Katherine P. Sanchez | C63: F | D63: CL-2022- | E63: 57 | F63: Completed | G63: Associate Proffesor III/ Project Leader - Goby | H63: MIndoro State University | I63: Research and Development Extension | J63: N/A | K63: 9166094464 | L63: N/A | M63: nyctarinia@gmail.com | N63: Macatoc, Victoria, Oriental, Mindoro
A64: 44785 | B64: Jermaine Ritzchelle D. Marquez | C64: F | D64: CL-2022- | E64: 58 | F64: Completed | G64: Instructor I | H64: MIndoro State University | I64: College of Teacher Education | J64: N/A | K64: 9606937846 | L64: N/A | M64: jrmarquez2790@gmail.com | N64: Block 12 Lot 13 Carnation St. Maria Luisa Subd. Suqui, Calapan City, Oriental Mindoro
A65: 44785 | B65: Elsie Y. Guibone | C65: F | D65: CL-2022- | E65: 59 | F65: Completed | G65: R & D Coordinator/ Projet Staff, Goby Project | H65: MIndoro State University | I65: Institute of Fisheries | J65: N/A | K65: 9770898748 | L65: N/A | M65: gebrielle10@gmail.com | N65: MinSu, Bongabong Campus, Brgy. Labasan, Bongabong, Oriental Mindoro
A66: 44868 | B66: Rommel Gestuveo | C66: M | D66: CL-2022- | E66: 60 | F66: Ongoing | G66: Assistant Professor/ Project Leader | H66: UP Visayas | I66: Division of Biological Sciences | J66: 033-3310237 | K66: 9610914560 | L66: N/A | M66: rjgestuveo@up.edu.ph | N66: Division of Biological Sciences, College of Arts and Sciences, Tomas Fonacier Hall, UP Visayas, Miagao, Iloilo 5023
A67: 44869 | B67: Frenche B. Hechanova | C67: F | D67: CL-2022- | E67: 61 | F67: Ongoing | G67: Science Research Assistant | H67: UP Visayas | I67: Division of Biological Sciences | J67: N/A | K67: 9776634482 | L67: N/A | M67: fbhechanova@up.edu.ph | N67: Rizal Ilawod St., Zone 1, Cabatuan, Iloilo 5031
A68: 44859 | B68: Jade G. Pahila | C68: F | D68: CL-2022- | E68: 62 | F68: Ongoing | G68: University Researcher I/Project Leader | H68: UPV Regional Research Center | I68: Food, Feeds, and Functional Nutrition Laboratory | J68: N/A | K68: 9171740515 | L68: N/A | M68: jgpahila@up.edu.ph | N68: Regional Research Center Building, University of the Philippines Visayas Miagao, 5023, Iloilo
A69: 44859 | B69: Cezarie L. Golingay | C69: F | D69: CL-2022- | E69: 63 | F69: Ongoing | G69: DOST CIP Graduate Fellow | H69: UPV Regional Research Center | I69: DOST Dried Microalgal Biomass Project (Food, Feeds, and Functional Nutrition Laboratory) | J69: N/A | K69: N/A | L69: N/A | M69: clgolingay@up.edu.ph | N69: Regional Research Center Building, University of the Philippines Visayas Miagao, 5023, Iloilo
A70: 44859 | B70: Ella Marie E. Villaruz | C70: F | D70: CL-2022- | E70: 64 | F70: Ongoing | G70: Science Research Analyst | H70: UPV Regional Research Center | I70: DOST Dried Microalgal Biomass Project (Food, Feeds, and Functional Nutrition Laboratory) | J70: N/A | K70: N/A | L70: N/A | M70: eevillaruz@up.edu.ph | N70: Regional Research Center Building, University of the Philippines Visayas Miagao, 5023, Iloilo
A71: 44859 | B71: Antoniette Lorain Z. Dimaano | C71: F | D71: CL-2022- | E71: 65 | F71: Ongoing | G71: Laboratory Aide II | H71: UPV Regional Research Center | I71: DOST Dried Microalgal Biomass Project (Food, Feeds, and Functional Nutrition Laboratory) | J71: N/A | K71: N/A | L71: N/A | M71: azdimaano@up.edu.ph | N71: Regional Research Center Building, University of the Philippines Visayas Miagao, 5023, Iloilo
A72: 44902 | B72: Pauline Anne Lamela | C72: F | D72: CL-2022- | E72: 66 | F72: Completed | G72: BS in Biology IV student | H72: UP Visayas | I72: College of Arts and Sciences Division of Biological Sciences | J72: N/A | K72: N/A | L72: N/A | M72: pmlamela@up.edu.ph | N72: College of Arts and Sciences Division of Biological Sciences, University of the Philippines Visayas Miagao, 5023, Iloilo
A73: 44910 | B73: Raymond Cabarles | C73: M | D73: CL-2022- | E73: 67 | F73: Completed | G73: Fish 219 – Advanced Fish Genetics Graduate Student | H73: UP Visayas | I73: CFOS IA | J73: N/A | K73: N/A | L73: N/A | N73: Institute of Aquaculutre, College of Fisheries and Ocean Science, University of the Philippines Visayas, Miagao, Iloilo
A74: 44910 | B74: Emelyn Joy Mameloco | C74: F | D74: CL-2022- | E74: 68 | F74: Completed | G74: Fish 219 – Advanced Fish Genetics Graduate Student | H74: UP Visayas | I74: CFOS IA | J74: N/A | K74: N/A | L74: N/A | N74: Institute of Aquaculutre, College of Fisheries and Ocean Science, University of the Philippines Visayas, Miagao, Iloilo
A75: 44910 | B75: Edcel T. Resano | C75: F | D75: CL-2022- | E75: 69 | F75: Completed | G75: Fish 219 – Advanced Fish Genetics Graduate Student | H75: UP Visayas | I75: CFOS IA | J75: N/A | K75: N/A | L75: N/A | N75: Institute of Aquaculutre, College of Fisheries and Ocean Science, University of the Philippines Visayas, Miagao, Iloilo
A76: 44925 | B76: Yobhel Grace T. Diputado | C76: F | D76: CL-2022- | E76: 075A | F76: Completed | G76: BS in Biology IV student | H76: UP Visayas | I76: College of Arts and Sciences Division of Biological Sciences | J76: N/A | K76: 9756763834 | L76: N/A | M76: ytdiputado@up.edu.ph | N76: College of Arts and Sciences Division of Biological Sciences, University of the Philippines Visayas Miagao, 5023, Iloilo
A77: 2023
A78: 44951 | B78: Persie Persie Mark Sienes | C78: M | D78: CL-2023- | E78: 70 | F78: Ongoing | G78: Faculty | H78: Siliman University
A79: 44964 | B79: Dr. Sitti Zayda Halun | C79: F | D79: CL-2023- | E79: 71 | F79: Ongoing | G79: Program Leader | H79: Mindanao State University in Tawi-Tawi | I79: Seaweed Research and Development Center, | K79: 9985307495 | M79: szhalun@msutawi-tawi.edu.ph | N79: Seaweed Research and Development Center, Mindanao State University in Tawi-Tawi Sanga-Sanga, Bongao, Tawi-Tawi, Philippines
A80: 44972 | B80: Reynaldo P. Peja Jr. | C80: M | D80: CL-2023- | E80: 72 | F80: Completed | G80: Project Leader | H80: Visayas State University - Alangalang
A81: 44985 | B81: June Rey A. Montajes | C81: M | D81: CL-2023- | E81: 73 | F81: Completed | G81: Assistant Professor | H81: Visayas State University Tolosa | I81: Fisheries | J81: (053) 604 | K81: 0992 933 7825 | 0997 069 9927 | M81: junerey.montajes@vsu.edu.ph | N81: ODREIC, 2/F KOICA (New Administration) Building, Maharlika Highway, Tanghas, Tolosa, Leyte
A82: 44985 | B82: Shereen A. Merro | C82: F | D82: CL-2023- | E82: 74 | F82: Completed | G82: Assistant Professor | H82: Visayas State University Tolosa | I82: Fisheries | J82: (053) 601 | K82: 0917 407 6762 | M82: shereen.merro@vsu.edu.ph | N82: ODAA, G/F KOICA (New Administration) Building, Maharlika Highway, Tanghas, Tolosa, Leyte
A83: 44985 | B83: Jay Marie V. Lumantas | C83: F | D83: CL-2023- | E83: 075B | F83: Completed | G83: BS in Biology IV student | H83: UP Visayas | I83: College of Arts and Sciences Division of Biological Sciences | J83: N/A | N83: College of Arts and Sciences Division of Biological Sciences, University of the Philippines Visayas Miagao, 5023, Iloilo
A84: 44985 | B84: Arnel Adrian Rara | C84: M | D84: CL-2023- | E84: 76 | F84: Completed | G84: BS Chemical Engineering | H84: UP Visayas | I84: DOST Dried Microalgal Biomass Project (Food, Feeds, and Functional Nutrition Laboratory) | J84: N/A
A85: 44999 | B85: Claire Samantha Juanico | C85: F | D85: CL-2023- | E85: 77 | F85: Ongoing | G85: Phd Student- Marine Biotech | H85: UP Visayas | I85: CFOS IA | J85: N/A | M85: gebrielle10@gmail.com
A86: 44999 | B86: Elsie Y. Guibone | C86: F | D86: CL-2023- | E86: 78 | F86: Completed
A87: 45007 | B87: Rose Ann Lumapan | C87: F | D87: CL-2023- | E87: 79 | F87: Completed | G87: Undergraduate Student (BS Fisheries IV) | H87: UP Visayas | I87: CFOS IFPT | J87: N/A | K87: 09491129316 | L87: N/A | M87: rvlumapan@up.edu.ph | N87: Balay Madyaas, UPV Dormitory Area
A88: 45020 | B88: Karmelie Jane Monaya | C88: F | D88: CL-2023- | E88: 80 | F88: Completed | G88: URA I | H88: UP Visayas | J88: N/A | K88: 09179155714 | L88: N/A | M88: kmmonaya@up.edu.ph | N88: IFPT Wet LAboratories, UPV Campus, Miagao, Iloilo
A89: 45035 | B89: Beatrice L. Anacita | C89: F | D89: CL-2023- | E89: 81 | F89: Completed | G89: BS Biology IV | H89: UP Visayas | I89: College of Arts and Sciences Division of Biological Sciences | J89: N/A | K89: 9183304418 | L89: N/A | M89: blanacita@up.edu.ph | N89: St. Therese Boarding House, Brgy. Mat-y, Miagao, Iloilo
A90: 45035 | B90: Kyla Julienne P. Talaman | C90: F | D90: CL-2023- | E90: 82 | F90: Completed | G90: BS Biology IV | H90: UP Visayas | I90: College of Arts and Sciences Division of Biological Sciences | J90: 5118523 | K90: 9156252447 | L90: N/A | M90: kptalaman@up.edu.ph | N90: St. Therese Boarding House, Brgy. Mat-y, Miagao, Iloilo
A91: 45036 | B91: Trisha Marie Santos | C91: F | D91: CL-2023- | E91: 83 | F91: Completed | G91: BS Biology IV | H91: UP Visayas | I91: College of Arts and Sciences Division of Biological Sciences | J91: 5118523 | K91: 9500034025 | L91: N/A | M91: tesantos2@up.edu.ph
A92: 45051 | B92: Trisha Catalya | C92: F | D92: CL-2023- | E92: 84 | F92: Completed | G92: BS Fisheries IV | H92: UP Visayas | I92: CFOS IFPT | J92: N/A | K92: 9451027090 | L92: N/A | M92: tccatalya@up.edu.ph | N92: Balay Gumamela, University of the Philippines Visayas, Brgy. Mat-y, Miagao, Iloilo Philippines 5023
A93: 45054 | B93: Josie Mar G. Cabalo | C93: F | D93: CL-2023- | E93: 85 | F93: Ongoing | G93: Project Technical Assistant II | H93: UP Visayas | I93: CFOS IA | J93: 3319762 | K93: 9150466811 | L93: N/A | M93: jgcabalo1@up.edu.ph | N93: Brgy. Camangahan, Guimbal, Iloilo 5022
A94: 45062 | B94: Carlo S. Gregorio | C94: M | D94: CL-2023- | E94: 86 | F94: Completed | G94: MS Ocean Sciences | H94: UP Visayas | I94: CFOS IMFO | J94: N/A | K94: 9381797811 | L94: N/A | M94: csgregorio@up.edu.ph | N94: Sitio Macaebang Norte, Ginictan, Altavas, Aklan
A95: 45062 | B95: Elize Margareth C. Sibulan | C95: F | D95: CL-2023- | E95: 87 | F95: Completed | G95: MS Ocean Sciences | H95: UP Visayas | I95: CFOS IMFO | J95: N/A | K95: 9611424133 | L95: N/A | M95: ecsibulan@up.edu.ph | N95: Unidos, Nabas, Aklan
A96: 45083 | B96: Abigail F. Padua | C96: F | D96: CL-2023- | E96: 88 | F96: Completed | G96: BS Biology (Biotech) | H96: West Visayas State University | I96: WVSU Biotechnology & Biomedical Research Labroatory | J96: N/A | K96: 9510585545 | L96: N/A | M96: abigail.padua@wvsu.edu.ph
A97: 45083 | B97: Rachel A. Casio | C97: F | D97: CL-2023- | E97: 89 | F97: Completed | G97: Draftsman I | H97: Department of Environmental and Natural Resources | I97: Conservation and Development Division | J97: (033) 328 1813 | K97: 9948480119 | L97: N/A | M97: oisaacra@gmail.com; denrcddr6.2018@gmail.com | N97: DENR Regional Office 6, Pepita Aquino St., Port Area, Iloilo City
A98: 45083 | B98: Jojie P. Gereza | C98: F | D98: CL-2023- | E98: 90 | F98: Completed | G98: Forester I | H98: Department of Environmental and Natural Resources | J98: N/A | K98: 9062648390 | L98: N/A | M98: cenroiloilo@denr.gov.ph | N98: DENR CENRO Guimbal, Brgy. Guibongan, Miagao, Iloilo
A99: 45085 | B99: Ella Marie Kristine Baldove | C99: F | D99: CL-2023- | E99: 91 | F99: Completed | G99: Research and Development Specialist | H99: Feedmix Specialist Inc. II | I99: Microalgae Department
A100: 45091 | B100: Ma Jowina Galarion | C100: F | D100: CL-2023- | E100: 92 | F100: Completed | G100: PhD Student | H100: University of Glasgow | I100: Medical Research Council | J100: N/A | K100: 9955359003 | L100: N/A | M100: m.galarion.1@research.gla.ac.uk | N100: 22A Yen St., Villa Arca II, Brgy. Baesa, Quezon City, Philippines
...

Sheet PLEASE READ ME
A1: Column 1 | B1: INSTRUCTION FOR USE OF CLIENT RECORDS | C1: INSTRUCTION FOR USE OF PROJECT RECORDS | D1: INSTRUCTION FOR USE OF CHARGE SLIP/BILLING
A2: 1. The search bar is programmed for quick search of a client and the project(s) where he/she belongs to | B2: 1. The client records sheet serves as the masterlist of information of all transacting clients. | C2: 1. The Project records sheet contains the project that a client(s) belongs to. Some client may not belong to a certain project depending on the nature of their engagement. | D2: 1. The charge slip/billing sheet serves as a summary of all charge slip released to transacting clients.
A3: 2. Type the client's name under the 'SEARCH CLIENT NAME' cell to search for the information | B3: 2. Before the service starts, all new transacting client must be given the following forms to process their information in the client records sheet: - Client Information Sheet (CIS): VSF-LF-CIS-v003 - Client Conforme (CC) | C3: 2. Choose/type the client's name from the drop down under the 'Client Name' column. If client name is not found, it means that the client is missing in the client records sheet. Input information of the client first before accomplishing the project records sheet. | D3: 2. A charge slip is released once the service has been rendered or the client has requested it in advance.
A4: 3. Information includes project/s attached to the client and charging/billing paid | B4: 3. All information in the client records sheet must be provided by the client as this will be carried over to different database requiring the same information. Ask client not to leave any information blank. | C4: 3. All information in the project records sheet must be provided by the client through the CIS. Once forms are accomplished, input ALL information in the sheet. PLEASE DO NOT LEAVE ANY INFORMATION BLANK. | D4: 3. The columns E to H are automated. Choose/type the client's name from the drop down in the 'Client Name' column to generate information of columns E to H. Input all other information manually. PLEASE DO NOT LEAVE ANY INFORMATION BLANK.
B5: 4. Once forms are accomplished, input the client's information in the sheet. PLEASE DO NOT LEAVE ANY INFORMATION BLANK. | C5: 4. Follow this format for assigning Project ID: P-YYYY-XXX; (XXX is continuous the next year) | D5: 4. Follow this format for assigning Charge Slip No.: CS-YYYY-XXX (XXX is non-continuous the next year. Start with 001 every start of the year)
B6: 5. Follow this format for assigning Client ID: CL-YYYY-XXX; (XXX is continuous the next year) | D6: 5. There are instances that a charge slip may not push through until payment due to corrections, cancellation of service, and/or the service requested did not push through. During this instance, mark the released charge slip as 'Cancelled' to avoid including it in the total of revenues during reports.
D7: 6. Regularly update the status of each charging to know if payment has already been made.
D8: LEGEND: DV. No. - Disbursement Voucher Number; Proof of payment for payments made through procurement process. OR No. - Official Receipt Number provided by the cash office once OR has been released

Sheet SEARCH BAR
D1: a
B2: SEARCH CLIENT NAME
B3: aye m
A5: Client Name | B5: Client ID Number | C5: Affiliation (Department and Institution Name and Address) | D5: Sex | E5: Designation | F5: Email Address | G5: Mobile Number
A6: =IFERROR(__xludf.DUMMYFUNCTION("FILTER('Client ID Records_v2'!D:J, SEARCH(B3,'Client ID Records_v2'!D:D))"),"Aye Mee Bartocillo") -> Aye Mee Bartocillo | B6: =IFERROR(__xludf.DUMMYFUNCTION("""COMPUTED_VALUE"""),"CL-2025-297") -> CL-2025-297 | C6: =IFERROR(__xludf.DUMMYFUNCTION("""COMPUTED_VALUE"""),"Biology Department, Siliman University, Dumaguete City Negros Oriental") -> Biology Department, Siliman University, Dumaguete City Negros Oriental | D6: =IFERROR(__xludf.DUMMYFUNCTION("""COMPUTED_VALUE"""),"F") -> F | E6: =IFERROR(__xludf.DUMMYFUNCTION("""COMPUTED_VALUE"""),"Balik Scientist") -> Balik Scientist | F6: =IFERROR(__xludf.DUMMYFUNCTION("""COMPUTED_VALUE"""),"ayefbartocillo@su.edu.ph") -> ayefbartocillo@su.edu.ph | G6: =IFERROR(__xludf.DUMMYFUNCTION("""COMPUTED_VALUE"""),9.274310611E9) -> 9274310611
A12: Project Lead/ Contact Person | B12: Project Number | C12: Project Title | D12: Project Tag | E12: Status
A13: =IFERROR(__xludf.DUMMYFUNCTION("FILTER('Project Records_v2'!E:I, SEARCH(B3,'Project Records_v2'!E:E))"),"#N/A") -> #N/A
A18: Charge Slip No. (CS-yyyy-xxx) | B18: Client Name | C18: Amount | D18: Status
A19: =IFERROR(__xludf.DUMMYFUNCTION("FILTER('Charge SlipBilling'!C:F, SEARCH(B3,'Charge SlipBilling'!D:D))"),"CS-2025-046") -> CS-2025-046 | B19: =IFERROR(__xludf.DUMMYFUNCTION("""COMPUTED_VALUE"""),"Aye Mee Bartocillo") -> Aye Mee Bartocillo | C19: =IFERROR(__xludf.DUMMYFUNCTION("""COMPUTED_VALUE"""),28863.03) -> 28863.03 | D19: =IFERROR(__xludf.DUMMYFUNCTION("""COMPUTED_VALUE"""),"PAID") -> PAID

Sheet Client ID Records_v2
A1: Year | B1: Date Received | C1: Status | D1: Client Name | E1: Client ID Number | F1: Affiliation (Department and Institution Name and Address) | G1: Sex | H1: Designation | I1: Email Address | J1: Mobile Number
A2: 2019 | B2: 43508 | C2: Ongoing | D2: PGC VISAYAS | E2: CL-2019-000 | F2: PGC Visayas Laboratories Room 205, 2nd Floor Regional Research Center University of the Philippines Visayas Brgy. Mambatad, Miagao, Iloilo 5023 | G2: N/A | H2: Others | I2: pgc.upvisayas@up.edu.ph
A3: 2020 | B3: 43873 | C3: Completed | D3: Nowena S. Solidum | E3: CL-2020-001 | F3: Fishery Department, Capiz State University - Dayao Satellite College, Dayao, Roxas City, Capiz | G3: F | H3: Faculty | I3: nowena_solidum@yahoo.com | J3: 9983950535
A4: 2020 | B4: 43873 | C4: Completed | D4: Marissa C. Naorbe | E4: CL-2020-002 | F4: Fishery Department, Capiz State University - Dayao Satellite College, Dayao, Roxas City, Capiz | G4: F | H4: Faculty | I4: castromarissa99@gmail.com | J4: 9506798777
A5: 2020 | B5: 43873 | C5: Completed | D5: Shirleen Grace Brillantes | E5: CL-2020-003 | F5: Samar State University - Mercedes, Mercedes, Catbalogan City, Samar 6700 | G5: F | H5: Faculty | I5: sweetbrillantes@gmail.com | J5: 9177145364
A6: 2020 | B6: 43873 | C6: Completed | D6: Irene Jean C. Lagumbay | E6: CL-2020-004 | F6: Samar State University - Mercedes, Mercedes, Catbalogan City, Samar 6700 | G6: F | H6: Faculty | I6: irenelagumbay95@gmail.com | J6: 9165866013
A7: 2020 | B7: 43873 | C7: Completed | D7: Rhodmar D. Panis | E7: CL-2020-005 | F7: Samar State University - Mercedes, Mercedes, Catbalogan City, Samar 6700 | G7: M | H7: Researcher/Technical Assistant | I7: rhodmar.divino@ssu.up.edu.ph | J7: 9056728581
A8: 2020 | B8: 43873 | C8: Completed | D8: Jay T. Torrefiel | E8: CL-2020-006 | F8: UPV Tacloban College | G8: M | H8: Faculty | I8: jattorrefiel@gmail.com | J8: 9058848900
A9: 2020 | B9: 43873 | C9: Completed | D9: Rhyzz Jane Balinos | E9: CL-2020-007 | F9: CFOS IA (DOST TGMPPEFET) | G9: F | H9: Researcher/Technical Assistant | I9: rhyzz.jane@gmail.com | J9: 9666553130
A10: 2020 | B10: 43873 | C10: Completed | D10: Mary Antonette F. Atilano | E10: CL-2020-008 | F10: CFOS IA (DOST TGMPPEFET) | G10: F | H10: Researcher/Technical Assistant | I10: atilanomaryantonette@gmail.com | J10: 9062227281
A11: 2020 | B11: 43874 | C11: Completed | D11: Alvin M. Doroteo | E11: CL-2020-009 | F11: COFES, University of Antique | G11: M | H11: Faculty | I11: doroteoalvin@yahoo.com | J11: 9272051528
A12: 2020 | B12: 43902 | C12: Completed | D12: Rema C. Sibonga | E12: CL-2020-010 | F12: Institute of Aquaculture, College of Fisheries and Ocean Sciences, University of the Philippines Visayas, Miagao, 5023, Iloilo | G12: F | H12: Researcher/Technical Assistant | I12: rcsibonga@gmail.com | J12: 09171409960; 09985315320
A13: 2020 | B13: 43903 | C13: Completed | D13: Karen Claire S. Ebreo | E13: CL-2020-011 | F13: Room 124, CAS Bldg., Division of Biological Sciences, College of Arts and Sciences, University of the Philippines Visayas, Miagao, Iloilo | G13: F | H13: Researcher/Technical Assistant | I13: ksebreo@up.edu.ph | J13: 9174290778
A14: 2020 | B14: 43990 | C14: Completed | D14: Kyle R. Castañares | E14: CL-2020-012 | F14: IA-Hatchery Complex, University of the Philippines Visayas, Miagao 5023, Iloilo | G14: M | H14: Researcher/Technical Assistant | I14: kyleresmac@gmail.com | J14: 9171669790
A15: 2020 | B15: 43990 | C15: Completed | D15: Angel Queenee D. Dequito | E15: CL-2020-013 | F15: Institute of Aquaculture, College of Fisheries and Ocean Sciences, University of the Philippines Visayas, Miagao, 5023, Iloilo | G15: F | H15: Project Leader | I15: addequito@up.edu.ph | J15: 9177212519
A16: 2020 | B16: 44015 | C16: Completed | D16: Nadalene Faith N. Cartago | E16: CL-2020-014 | F16: Institute of Aquaculture, College of Fisheries and Ocean Sciences, University of the Philippines Visayas, Miagao, 5023, Iloilo | G16: F | H16: MS Student | I16: nadelenefaithcartago@yahoo.com | J16: 9452398275
A17: 2020 | B17: 44015 | C17: Ongoing | D17: Karl Angelo P. Tenizo | E17: CL-2020-015 | F17: Institute of Aquaculture, College of Fisheries and Ocean Sciences, University of the Philippines Visayas, Miagao, 5023, Iloilo | G17: M | H17: Researcher/Technical Assistant | I17: kptenizo@up.edu.ph | J17: 9983085275
A18: 2020 | B18: 44034 | C18: Completed | D18: Gabrielle Troy A. Cuevas | E18: CL-2020-016 | F18: Department of Chemistry, College of Arts and Sciences, UP Visayas | G18: M | H18: Project Leader | I18: gacuevas@up.edu.ph | J18: 9953856717
A19: 2020 | B19: 44034 | C19: Completed | D19: Wilson F. Medrocillo | E19: CL-2020-017 | F19: RA Lounge, CAS Basement, College of Arts and Sciences, UP Visayas | G19: M | H19: Researcher/Technical Assistant | I19: wfmedrocillo@up.edu.ph | J19: 936981029
A20: 2020 | B20: 44035 | C20: Cancelled | D20: Leonilo F. Endoma | E20: CL-2020-018 | F20: Institute of Fish Processing Technology, College of Fisheries and Ocean Sciences, University of the Philippines Visayas | G20: M | H20: Faculty | I20: lfendoma@up.edu.ph | J20: 9152715677
A21: 2020 | B21: 44048 | C21: Completed | D21: Dominique P. Mediodia | E21: CL-2020-019 | F21: Institute of Marine Fisheries and Oceanology, College of Fisheries and Ocean Sciences, University of the Philippines Visayas | G21: M | H21: Project Leader | I21: dpmediodia@up.edu.ph | J21: 9267259050
A22: 2020 | B22: 44048 | C22: Completed | D22: Ma. Novem Grace Ylayron | E22: CL-2020-020 | F22: Institute of Marine Fisheries and Oceanology, College of Fisheries and Ocean Sciences, University of the Philippines Visayas | G22: F | H22: Researcher/Technical Assistant | I22: maylayron@up.edu.ph | J22: 9292671029
A23: 2020 | B23: 44048 | C23: Ongoing | D23: Carmelo del Castillo | E23: CL-2020-021 | F23: Institute of Aquaculture, College of Fisheries and Ocean Sciences, University of the Philippines Visayas, Miagao, 5023, Iloilo | G23: M | H23: Faculty | I23: csdelcastillo@up.edu.ph | J23: 9177110107
A24: 2020 | B24: 44062 | C24: Cancelled | D24: Pretty Lee Silva | E24: CL-2020-022 | F24: School of Technology, University of the Philippines Visayas, Miagao, 5023, Iloilo | G24: F | H24: Faculty
A25: 2020 | B25: 44131 | C25: Completed | D25: Loina Henzel A. Delgado | E25: CL-2020-023 | F25: Room 124, CAS Bldg., Division of Biological Sciences, College of Arts and Sciences, University of the Philippines Visayas, Miagao, Iloilo | G25: F | H25: Researcher/Technical Assistant | I25: ladelgado1@up.edu.ph | J25: 9300953925
A26: 2020 | B26: 44168 | C26: Ongoing | D26: Denise V. Miranda | E26: CL-2020-024 | F26: Institute of Aquaculture, College of Fisheries and Ocean Sciences, University of the Philippines Visayas, Miagao, 5023, Iloilo | G26: F | H26: Researcher/Technical Assistant | I26: dvmiranda@up.edu.ph | J26: 9777305977
A27: 2021 | B27: 44216 | C27: Completed | D27: Alain C. Juayang | E27: CL-2021-025 | F27: Molecular Laboratory, Corazon L. Montelibano Memorial Regional Hospital, Burgos-Lacson St., Bacolod City | G27: M | H27: Staff | I27: alainjuayang@yahoo.com | J27: 9226942501
A28: 2021 | B28: 44216 | C28: Completed | D28: Jezreel Teruel Ywayan | E28: CL-2021-026 | F28: Bacolod Queen of Mercy Hospital Molecular Laboratory, LN Eroreco Drive, Mandalagan, Bacolod City 6100 | G28: F | H28: Staff | I28: jbtywayanmolecular2020@gmail.com | J28: 9231531678
A29: 2021 | B29: 44250 | C29: Completed | D29: Leni G. Yap-Dejeto | E29: CL-2021-027 | F29: UPV Tacloban College, Magsaysay Blvd., Tacloban City, Leyte 6500 | G29: F | H29: Faculty | I29: lgyapdejeto@up.edu.ph | J29: 639368135357
A30: 2021 | B30: 44280 | C30: Completed | D30: Dianne Frances Penuela | E30: CL-2021-028 | F30: Division of Biological Sciences, College of Arts and Sciences, University of the Philippines Visayas, Miagao, Iloilo | G30: F | H30: Researcher/Technical Assistant | I30: dapenuela@up.edu.ph | J30: 9052565544
A31: 2021 | B31: 44280 | C31: Completed | D31: Roxanne Cabebe | E31: CL-2021-029 | F31: Institute of Marine Fisheries and Oceanology, College of Fisheries and Ocean Sciences, University of the Philippines Visayas | G31: F | H31: Researcher/Technical Assistant | I31: racabebe@up.edu.ph | J31: 9760511920
A32: 2021 | B32: 44302 | C32: Completed | D32: Albert C. Noblezada | E32: CL-2021-030 | F32: Institute of Aquaculture, College of Fisheries and Ocean Sciences, University of the Philippines Visayas, Miagao, 5023, Iloilo | G32: M | H32: MS Student | I32: acnoblezada@up.edu.ph | J32: 9165448358
A33: 2021 | B33: 44334 | C33: Ongoing | D33: Arlene L . Avillanosa | E33: CL-2021-031 | F33: Room 9, Second Floor (ABBA R&D Center), College of Fisheries and Aquatic Science (CFAS), WPU-Puerto Princesa Campus, Sta. Monica, Puerto Princesa City | G33: F | H33: Project Leader | I33: arlene.avillanosa@wpu.edu.ph | J33: 9278173880
A34: 2021 | B34: 44334 | C34: Ongoing | D34: Reymart S. Dagaraga | E34: CL-2021-032 | F34: Room 9, Second Floor (ABBA R&D Center), College of Fisheries and Aquatic Science (CFAS), WPU-Puerto Princesa Campus, Sta. Monica, Puerto Princesa City | G34: M | H34: Researcher/Technical Assistant | I34: gemphilproject@gmail.com | J34: 09678700527 09475042638 09958698243
A35: 2021 | B35: 44334 | C35: Ongoing | D35: Jasper D. Pacho | E35: CL-2021-033 | F35: Room 9, Second Floor (ABBA R&D Center), College of Fisheries and Aquatic Science (CFAS), WPU-Puerto Princesa Campus, Sta. Monica, Puerto Princesa City | G35: M | H35: Researcher/Technical Assistant | I35: jasperpacho181@gmail.com | J35: 9507960935
A36: 2021 | B36: 44382 | C36: Completed | D36: Kristina Samantha Lacson | E36: CL-2021-034 | F36: College of Arts and Sciences (CAS) Buidling, University of the Philippines Visayas, Miagao, Iloilo 5023 | G36: F | H36: Researcher/Technical Assistant | I36: kblacson@up.edu.ph | J36: 9561765997
A37: 2021 | B37: 44382 | C37: Completed | D37: Concepcion Ponce | E37: CL-2021-035 | F37: College of Arts and Sciences (CAS) Buidling, University of the Philippines Visayas, Miagao, Iloilo 5023 | G37: F | H37: Project Leader | I37: cpponce@upv.edu.ph | J37: 9951970469
A38: 2021 | B38: 44435 | C38: Cancelled | D38: Carolyn T. Mejares | E38: CL-2021-036 | F38: School of Technology, University of the Philippines Visayas, Miagao, Iloilo | G38: F | H38: Faculty | I38: ctmejares@up.edu.ph | J38: 9174804428
A39: 2022 | B39: 44580 | C39: Cancelled | D39: Rowena E. Cadiz | E39: CL-2022-037 | F39: Institute of Aquaculutre, College of Fisheries and Ocean Science, University of the Philippines Visayas, Miagao, Iloilo | G39: F | H39: Researcher/Technical Assistant | I39: recadiz@up.edu.ph
A40: 2022 | B40: 44622 | C40: Ongoing | D40: Eric Zeus C. Rizo | E40: CL-2022-038 | F40: Division of Biological Sciences, College of Arts and Sciences, University of the Philippines Visayas, Miagao, Iloilo | G40: M | H40: Project Leader | I40: ecrizo@up.edu.ph | J40: 9153101800
A41: 2022 | B41: 44622 | C41: Ongoing | D41: Shea Kathleen P. Guinto | E41: CL-2022-039 | F41: Division of Biological Sciences, College of Arts and Sciences, University of the Philippines Visayas, Miagao, Iloilo | G41: F | H41: Researcher/Technical Assistant | I41: spguinto@up.edu.ph | J41: 9178587562
A42: 2022 | B42: 44622 | C42: Completed | D42: Rother M. Gaudiel | E42: CL-2022-040 | F42: Institute of Aquaculutre, College of Fisheries and Ocean Science, University of the Philippines Visayas, Miagao, Iloilo | G42: M | H42: MS Student | I42: rmgaudiel@up.edu.ph | J42: 9569874648
A43: 2022 | B43: 44624 | C43: Completed | D43: John Rey F. Rasgo | E43: CL-2022-041 | F43: Institute of Marine Fisheries and Oceanology, College of Fisheries and Ocean Sciences, University of the Philippines Visayas | G43: M | H43: Undergrad Student | I43: jfrasgo@up.edu.ph | J43: 9612217613
A44: 2022 | B44: 44628 | C44: Completed | D44: Luke Dranoel D. Atencio | E44: CL-2022-042 | F44: Regional Research Center, New Academic Complex, University of the Philippines Visayas, Miagao, Iloilo | G44: M | H44: Researcher/Technical Assistant | I44: ldatencio@up.edu.ph | J44: 9958160186
A45: 2022 | B45: 44634 | C45: Completed | D45: Whelver N. Surnido | E45: CL-2022-043 | F45: Institute of Aquaculutre, College of Fisheries and Ocean Science, University of the Philippines Visayas, Miagao, Iloilo | G45: M | H45: Researcher/Technical Assistant | I45: wnsurnido@up.edu.ph | J45: 936618579
A46: 2022 | B46: 44644 | C46: Completed | D46: Kingsley John de los Santos | E46: CL-2022-044 | F46: Division of Biological Sciences, College of Arts and Sciences, University of the Philippines Visayas, Miagao, Iloilo | G46: M | H46: MS Student | I46: kdelossantos@up.edu.ph | J46: 9995569350
A47: 2022 | B47: 44645 | C47: Completed | D47: Karl C. Abismo | E47: CL-2022-045 | F47: Institute of Aquaculutre, College of Fisheries and Ocean Science, University of the Philippines Visayas, Miagao, Iloilo | G47: M | H47: Undergrad Student | I47: kcabismo@up.edu.ph | J47: 9458533418
A48: 2022 | B48: 44663 | C48: Completed | D48: Stephen G. Sabinay | E48: CL-2022-046 | F48: 4th Floor, Roxas Hall Annex, College of Medicine, West Visayas State University, La Paz, Iloilo City | G48: M | H48: Faculty | I48: ssabinay@wvsu.edu.ph | J48: 9983115444
A49: 2022 | B49: 44680 | C49: Completed | D49: Benedict Maralit | E49: CL-2022-047 | F49: N/A | G49: M
A50: 2022 | B50: 44680 | C50: Ongoing | D50: Philip Alviola | E50: CL-2022-048 | F50: University of the Philippine Los Baños | G50: M
A51: 2022 | B51: 44705 | C51: Completed | D51: Isabel Grace Gatpatan | E51: CL-2022-049 | F51: Division of Biological Sciences, College of Arts and Sciences, University of the Philippines Visayas, Miagao, Iloilo | G51: F | H51: Researcher/Technical Assistant | I51: isabelagrasya@gmail.com | J51: 9507678137
A52: 2022 | B52: 44718 | C52: Completed | D52: Camille Rose T. Mueda | E52: CL-2022-050 | F52: Institute of Biological Sciences, University of the Philippine Los Baños | G52: F | H52: MS Student | I52: ctmueda@up.edu.ph | J52: 9086043843
A53: 2022 | B53: 44725 | C53: Completed | D53: Beverly T. Jaspe | E53: CL-2022-051 | F53: Fisheries and Marine Sciences Department, Aklan State University - New Washington Campus | G53: F | H53: Project Leader
A54: 2022 | B54: 44729 | C54: Completed | D54: Zeth Rodario Bebit | E54: CL-2022-052 | F54: Department of Chemistry, College of Arts and Sciences, UP Visayas, Miagao, Iloilo 5023 | G54: M | H54: Researcher/Technical Assistant | I54: N/A | J54: N/A
A55: 2022 | B55: 44725 | C55: Completed | D55: Kneessa Louie G. Dato-on | E55: CL-2022-053 | F55: Institute of Biological Sciences, University of the Philippine Los Baños | G55: F | H55: MS Student | I55: kgdatoon@up.edu.ph | J55: 9563167064
A56: 2022 | B56: 44733 | C56: Completed | D56: Leogiver G. Mañosca | E56: CL-2022-054 | F56: Philippine Science High School - MIMAROPA Region Campus | G56: M | H56: Faculty | I56: N/A | J56: N/A
A57: 2022 | B57: 44763 | C57: Completed | D57: Rhudith Cabulong | E57: CL-2022-055 | F57: Microbiology Laboratory, College of Arts and Sciences, University of the Philippines Visayas, 5023 Miagao, Iloilo | G57: F | H57: Faculty | I57: rbcabulong@up.edu.ph | J57: N/A
A58: 2022 | B58: 44785 | C58: Completed | D58: Viva Princess A. Basa | E58: CL-2022-056 | F58: Research and Development Extension, Mindoro State University | G58: F | H58: Researcher/Technical Assistant | I58: vivaprincessbasa@icloud.com | J58: 9065278053
A59: 2022 | B59: 44785 | C59: Completed | D59: Katherine P. Sanchez | E59: CL-2022-057 | F59: Research and Development Extension, Mindoro State University | G59: F | H59: Faculty | I59: nyctarinia@gmail.com | J59: 9166094464
A60: 2022 | B60: 44785 | C60: Completed | D60: Jermaine Ritzchelle D. Marquez | E60: CL-2022-058 | F60: College of Teacher Education, Mindoro State University | G60: F | H60: Faculty | I60: jrmarquez2790@gmail.com | J60: 9606937846
A61: 2022 | B61: 44785 | C61: Completed | D61: Elsie Y. Guibone | E61: CL-2022-059 | F61: Institute of Fisheries, MinSu, Bongabong Campus, Brgy. Labasan, Bongabong, Oriental Mindoro | G61: F | H61: Faculty, Researcher/Technical Assistant, Phd Student | I61: gebrielle10@gmail.com | J61: 9770898748
A62: 2022 | B62: 44868 | C62: Ongoing | D62: Rommel Gestuveo | E62: CL-2022-060 | F62: Division of Biological Sciences, College of Arts and Sciences, Tomas Fonacier Hall, UP Visayas, Miagao, Iloilo 5023 | G62: M | H62: Faculty, Project Leader | I62: rjgestuveo@up.edu.ph | J62: 9610914560
A63: 2022 | B63: 44869 | C63: Ongoing | D63: Frenche B. Hechanova | E63: CL-2022-061 | F63: Division of Biological Sciences, College of Arts and Sciences, Tomas Fonacier Hall, UP Visayas, Miagao, Iloilo 5023 | G63: F | H63: Researcher/Technical Assistant | I63: fbhechanova@up.edu.ph | J63: 9776634482
A64: 2022 | B64: 44859 | C64: Ongoing | D64: Jade G. Pahila | E64: CL-2022-062 | F64: Regional Research Center Building, University of the Philippines Visayas Miagao, 5023, Iloilo | G64: F | H64: Researcher/Technical Assistant | I64: jgpahila@up.edu.ph | J64: 9171740515
A65: 2022 | B65: 44859 | C65: Ongoing | D65: Cezarie L. Golingay | E65: CL-2022-063 | F65: Regional Research Center Building, University of the Philippines Visayas Miagao, 5023, Iloilo | G65: F | H65: Others, Staff, Researcher/Technical Assistant | I65: clgolingay@up.edu.ph | J65: N/A
A66: 2022 | B66: 44859 | C66: Ongoing | D66: Ella Marie E. Villaruz | E66: CL-2022-064 | F66: Regional Research Center Building, University of the Philippines Visayas Miagao, 5023, Iloilo | G66: F | H66: Researcher/Technical Assistant | I66: eevillaruz@up.edu.ph | J66: N/A
A67: 2022 | B67: 44859 | C67: Ongoing | D67: Antoniette Lorain Z. Dimaano | E67: CL-2022-065 | F67: Regional Research Center Building, University of the Philippines Visayas Miagao, 5023, Iloilo | G67: F | H67: Researcher/Technical Assistant | I67: azdimaano@up.edu.ph | J67: N/A
A68: 2022 | B68: 44902 | C68: Completed | D68: Pauline Anne Lamela | E68: CL-2022-066 | F68: College of Arts and Sciences Division of Biological Sciences, University of the Philippines Visayas Miagao, 5023, Iloilo | G68: F | H68: Undergrad Student | I68: pmlamela@up.edu.ph | J68: N/A
A69: 2022 | B69: 44910 | C69: Completed | D69: Raymond Cabarles | E69: CL-2022-067 | F69: Institute of Aquaculutre, College of Fisheries and Ocean Science, University of the Philippines Visayas, Miagao, Iloilo | G69: M | H69: Phd Student | J69: N/A
A70: 2022 | B70: 44910 | C70: Completed | D70: Emelyn Joy Mameloco | E70: CL-2022-068 | F70: Institute of Aquaculutre, College of Fisheries and Ocean Science, University of the Philippines Visayas, Miagao, Iloilo | G70: F | H70: Researcher/Technical Assistant | J70: N/A
A71: 2022 | B71: 44910 | C71: Completed | D71: Edcel T. Resano | E71: CL-2022-069 | F71: Institute of Aquaculutre, College of Fisheries and Ocean Science, University of the Philippines Visayas, Miagao, Iloilo | G71: F | J71: N/A
A72: 2022 | B72: 44925 | C72: Completed | D72: Yobhel Grace T. Diputado | E72: CL-2022-075A | F72: College of Arts and Sciences Division of Biological Sciences, University of the Philippines Visayas Miagao, 5023, Iloilo | G72: F | H72: Undergrad Student | I72: ytdiputado@up.edu.ph | J72: 9756763834
A73: 2023 | B73: 44951 | C73: Ongoing | D73: Persie Persie Mark Sienes | E73: CL-2023-070 | F73: Siliman University | G73: M | H73: Faculty | I73: persiesienes@su.edu.ph | J73: 9366517382
A74: 2023 | B74: 44964 | C74: Ongoing | D74: Dr. Sitti Zayda Halun | E74: CL-2023-071 | F74: Seaweed Research and Development Center, Mindanao State University in Tawi-Tawi Sanga-Sanga, Bongao, Tawi-Tawi, Philippines | G74: F | H74: Project Leader | I74: szhalun@msutawi-tawi.edu.ph | J74: 9985307495
A75: 2023 | B75: 44972 | C75: Completed | D75: Reynaldo P. Peja Jr. | E75: CL-2023-072 | F75: Visayas State University - Alangalang | G75: M | H75: Project Leader
A76: 2023 | B76: 44985 | C76: Completed | D76: June Rey A. Montajes | E76: CL-2023-073 | F76: ODREIC, 2/F KOICA (New Administration) Building, Maharlika Highway, Tanghas, Tolosa, Leyte | G76: M | H76: Faculty | I76: junerey.montajes@vsu.edu.ph | J76: 0992 933 7825 | 0997 069 9927
A77: 2023 | B77: 44985 | C77: Completed | D77: Shereen A. Merro | E77: CL-2023-074 | F77: ODAA, G/F KOICA (New Administration) Building, Maharlika Highway, Tanghas, Tolosa, Leyte | G77: F | H77: Faculty | I77: shereen.merro@vsu.edu.ph | J77: 0917 407 6762
A78: 2023 | B78: 44985 | C78: Completed | D78: Jay Marie V. Lumantas | E78: CL-2023-075 | F78: College of Arts and Sciences Division of Biological Sciences, University of the Philippines Visayas Miagao, 5023, Iloilo | G78: F | H78: Undergrad Student
A79: 2023 | B79: 44985 | C79: Completed | D79: Arnel Adrian Rara | E79: CL-2023-076 | F79: DOST Dried Microalgal Biomass Project (Food, Feeds, and Functional Nutrition Laboratory) | G79: M | H79: Undergrad Student
A80: 2023 | B80: 44999 | C80: Ongoing | D80: Claire Samantha Juanico | E80: CL-2023-077 | F80: Institute of Aquaculutre, College of Fisheries and Ocean Science, University of the Philippines Visayas, Miagao, Iloilo | G80: F | H80: Phd Student | I80: gebrielle10@gmail.com
A81: 2023 | B81: 44999 | C81: Cancelled | D81: Elsie Y. Guibone | E81: CL-2023-078 | F81: Institute of Aquaculutre, College of Fisheries and Ocean Science, University of the Philippines Visayas, Miagao, Iloilo | G81: F
A82: 2023 | B82: 45007 | C82: Completed | D82: Rose Ann Lumapan | E82: CL-2023-079 | F82: Institute of Fish Processing Technology, College of Fisheries and Ocean Sciences, University of the Philippines Visayas | G82: F | H82: Undergrad Student | I82: rvlumapan@up.edu.ph | J82: 9491129316
A83: 2023 | B83: 45020 | C83: Completed | D83: Karmelie Jane Monaya | E83: CL-2023-080 | F83: Institute of Fish Processing Technology, College of Fisheries and Ocean Sciences, University of the Philippines Visayas | G83: F | H83: Researcher/Technical Assistant | I83: kmmonaya@up.edu.ph | J83: 9179155714
A84: 2023 | B84: 45035 | C84: Completed | D84: Beatrice L. Anacita | E84: CL-2023-081 | F84: College of Arts and Sciences Division of Biological Sciences, University of the Philippines Visayas Miagao, 5023, Iloilo | G84: F | H84: Undergrad Student | I84: blanacita@up.edu.ph | J84: 9183304418
A85: 2023 | B85: 45035 | C85: Completed | D85: Kyla Julienne P. Talaman | E85: CL-2023-082 | F85: College of Arts and Sciences Division of Biological Sciences, University of the Philippines Visayas Miagao, 5023, Iloilo | G85: F | H85: Undergrad Student | I85: kptalaman@up.edu.ph | J85: 9156252447
A86: 2023 | B86: 45036 | C86: Completed | D86: Trisha Marie Santos | E86: CL-2023-083 | F86: Division of Biological Sciences, College of Arts and Sciences, UP Visayas Miagao Iloilo | G86: F | H86: Undergrad Student | I86: tesantos2@up.edu.ph | J86: 9500034025
A87: 2023 | B87: 45051 | C87: Completed | D87: Trisha Catalya | E87: CL-2023-084 | F87: Institute of Fish Processing Technology, College of Fisheries and Ocean Sciences, University of the Philippines Visayas | G87: F | H87: Undergrad Student | I87: tccatalya@up.edu.ph | J87: 9451027090
A88: 2023 | B88: 45054 | C88: Ongoing | D88: Josie Mar G. Cabalo | E88: CL-2023-085 | F88: Institute of Aquaculutre, College of Fisheries and Ocean Science, University of the Philippines Visayas, Miagao, Iloilo | G88: F | H88: Researcher/Technical Assistant | I88: jgcabalo1@up.edu.ph | J88: 9150466811
A89: 2023 | B89: 45062 | C89: Completed | D89: Carlo S. Gregorio | E89: CL-2023-086 | F89: Institute of Marine Fisheries and Oceanology, College of Fisheries and Ocean Sciences, University of the Philippines Visayas | G89: M | H89: MS Student | I89: csgregorio@up.edu.ph | J89: 9381797811
A90: 2023 | B90: 45062 | C90: Completed | D90: Elize Margareth C. Sibulan | E90: CL-2023-087 | F90: Institute of Marine Fisheries and Oceanology, College of Fisheries and Ocean Sciences, University of the Philippines Visayas | G90: F | H90: MS Student | I90: ecsibulan@up.edu.ph | J90: 9611424133
A91: 2023 | B91: 45083 | C91: Completed | D91: Abigail F. Padua | E91: CL-2023-088 | F91: WVSU Biotechnology & Biomedical Research Labroatory | G91: F | H91: Undergrad Student | I91: abigail.padua@wvsu.edu.ph | J91: 9510585545
A92: 2023 | B92: 45083 | C92: Completed | D92: Rachel A. Casio | E92: CL-2023-089 | F92: DENR Regional Office 6, Pepita Aquino St., Port Area, Iloilo City | G92: F | I92: oisaacra@gmail.com; denrcddr6.2018@gmail.com | J92: 9948480119
A93: 2023 | B93: 45083 | C93: Completed | D93: Jojie P. Gereza | E93: CL-2023-090 | F93: DENR CENRO Guimbal, Brgy. Guibongan, Miagao, Iloilo | G93: F | I93: cenroiloilo@denr.gov.ph | J93: 9062648390
A94: 2023 | B94: 45085 | C94: Completed | D94: Ella Marie Kristine Baldove | E94: CL-2023-091 | F94: Feedmix Specialist Inc. II | G94: F
A95: 2023 | B95: 45091 | C95: Completed | D95: Ma Jowina Galarion | E95: CL-2023-092 | F95: Medical Research Council, University of Glasgow | G95: F | I95: m.galarion.1@research.gla.ac.uk | J95: 9955359003
A96: 2023 | B96: 45103 | C96: Completed | D96: Harold P. Mediodia | E96: CL-2023-093 | F96: PSHS Western Visayas Campus, Bitoon, Jaro, 5000 Iloilo City | G96: M | I96: hmediodia@wvc.pshs.edu.ph | J96: 9458039067
A97: 2023 | B97: 45103 | C97: Completed | D97: Dorothy Jade P. Tacuel | E97: CL-2023-094 | F97: PSHS Western Visayas Campus, Bitoon, Jaro, 5000 Iloilo City | G97: F | I97: dptacuel@wvc.pshs.edu.ph | J97: 9101570895
A98: 2023 | B98: 45103 | C98: Completed | D98: Jemiah Ashelle Grace K. Vasquez | E98: CL-2023-095 | F98: PSHS Western Visayas Campus, Bitoon, Jaro, 5000 Iloilo City | G98: F | I98: jvasquez2025@wvc.pshs.edu.ph | J98: 9291552319
A99: 2023 | B99: 45119 | C99: Ongoing | D99: Mark S. Calabon | E99: CL-2023-096 | F99: Division of Biological Sciences, College of Arts and Sciences, UP Visayas Miagao Iloilo | G99: M | I99: mscalabon@up.edu.ph
A100: 2023 | B100: 45119 | C100: Ongoing | D100: James Nim | E100: CL-2023-097 | F100: Division of Biological Sciences, College of Arts and Sciences, UP Visayas Miagao Iloilo | G100: M | I100: jmnim@up.edu.ph
...

Sheet Project Records_v2
A1: Year | B1: Start date | C1: End date | D1: Client Names | E1: Project Lead/ Contact Person | F1: Project Number | G1: Project Title | H1: Project Tag | I1: Status | J1: Sending Institution | K1: Funding Category | L1: Funding Institution | M1: Service Requested | N1: Personnel Assigned | O1: Notes
A2: 2019 | B2: 43525 | D2: N/A | E2: PGC VISAYAS | F2: P-2019-000 | G2: PGC VISAYAS SATELLITE FACILITY | H2: PGCV | I2: Ongoing | J2: N/A | K2: In-House | L2: DOST-PCHRD | M2: N/A
A3: 2020 | B3: 43903 | C3: 44196 | D3: N/A | E3: Rema C. Sibonga | F3: P-2020-001 | G3: Global Seaweed STAR Project | H3: GSStar | I3: Completed | J3: UP System | K3: External | L3: UK Research and Innovation - Global Challenges Research Fund (UKRI-GCRF) | M3: Equipment Use | N3: Ma Carmel Javier
A4: 2020 | B4: 43903 | C4: 44408 | D4: Loina Henzel A. Delgado | E4: Karen Claire S. Ebreo | F4: P-2020-002 | G4: Taklong Barcoding Initiative | H4: TBI | I4: Completed | J4: UP System | K4: External | L4: N/A | M4: Equipment Use | N4: Ma Carmel Javier
A5: 2020 | B5: 43990 | C5: 44316 | D5: Kyle R. Castañares Mary Antonette F. Atilano | E5: Angel Queenee D. Dequito | F5: P-2020-003 | G5: Transcriptome and Gut Metagenome Profile of Penaeus vannamei Exposed to Fluctuating Environmental Temperatures | H5: TGMPPEFET | I5: Completed | J5: UP System | K5: External | L5: DOST-PCAARRD | M5: Equipment Use | N5: Jasmine Velo
A6: 2020 | B6: 44015 | C6: 44347 | E6: Nadelene Faith N. Cartago | F6: P-2020-004 | G6: Transcriptional Response of Selected Genes of the Green Mussel (Perna viridis) Exposed to Heat Stress | H6: Cartago | I6: Completed | J6: UP System | K6: External | L6: DOST-ASTHRDP | M6: Equipment Use | N6: Ma Carmel Javier
A7: 2020 | B7: 44034 | D7: Denise V. Miranda | E7: Karl Angelo P. Tenizo | F7: P-2020-005 | G7: Transcriptome and metabolome profiling of seaweeds to elucidate "ice-ice" disease and epiphyte infestation mechanisms | H7: Ice-Ice | I7: Ongoing | J7: UP System | K7: External | L7: DOST-PCAARRD | M7: Equipment Use | N7: Ma Carmel Javier
A8: 2020 | B8: 44034 | C8: 44742 | D8: Wilson F. Medrocillo | E8: Gabrielle Troy A. Cuevas | F8: P-2020-006 | G8: Purification and Characterization of Linamarase from Lakan-1 and Java Variety Cassava (Manihot esculenta Crantz) | H8: Cuevas | I8: Completed | J8: UP System | K8: External | L8: UPV In-House Project | M8: Equipment Use | N8: Ma Carmel Javier
A9: 2020 | B9: 44035 | E9: Leonilo F. Endoma | F9: P-2020-007 | G9: Instructional videos for Fish 111, Fish 236, Fish 238, Fish 321 | H9: Endoma | I9: Cancelled | J9: UP System | K9: External | L9: N/A | M9: Equipment Use | N9: Jasmine Velo
A10: 2020 | B10: 44048 | C10: 44620 | D10: Ma. Novem Grace Ylayron Carmelo del Castillo | E10: Dominique P. Mediodia | F10: P-2020-008 | G10: Marine Fisheries Assessment of Panay: Building Local Fisheries Information through Research Capability Enhancement on Higher Education Insitutions | H10: Panay Marfish Project | I10: Completed | J10: UP System | K10: External | L10: CHED | M10: Equipment Use | N10: Jasmine Velo
A11: 2020 | B11: 44062 | E11: Pretty Lee Silva | F11: P-2020-009 | G11: MS in Chemical Engineering | H11: Silva | I11: Cancelled | J11: UP System | K11: External | L11: N/A | M11: Equipment Use | N11: Marj Gem Bunda-Fajunio
A12: 2021 | B12: 44250 | C12: 44377 | E12: Leni G. Yap-Dejeto | F12: P-2021-010 | G12: c/o UP Visayas Tacloban College | H12: Glycogen | I12: Completed | J12: SUC/HEI | K12: External | L12: N/A | M12: Laboratory Services | N12: Jasmine Velo
A13: 2021 | B13: 44280 | C13: 44882 | D13: Roxanne Cabebe | E13: Dianne Frances Penuela | F13: P-2021-011 | G13: DNA barcoding of fishes from Western Visayas, Philippines | H13: DNA Barcoding | I13: Completed | J13: UP System | K13: External | L13: CHED | M13: Equipment Use
A14: 2021 | B14: 44302 | C14: 44681 | E14: Albert C. Noblezada | F14: P-2021-012 | G14: Population Structure of Green Mussel (Perna viridis) in Panay Island, Philippines using D-loop Sequences | H14: Noblezada | I14: Completed | J14: UP System | K14: External | L14: DOST-ASTHRDP Thesis Grant | M14: Equipment Use
A15: 2021 | B15: 44334 | D15: Reymart S. Dagaraga Jasper D. Pacho | E15: Arlene L . Avillanosa | F15: P-2021-013 | G15: Genetic Characterization of Macrobrachium populations in the Philippines for broodstock development and seed production | H15: GeM-PHIL | I15: Ongoing | J15: SUC/HEI | K15: External | L15: DOST-PCAARRD | M15: Laboratory Services | N15: Nadelene Faith Cartago
A16: 2021 | B16: 44382 | C16: 44553 | D16: Kristina Samantha Lacson | E16: Concepcion Ponce | F16: P-2021-014 | G16: Pre-commercialization of Microwave Extracted Pectin from Waste Calamansi Peels | H16: Calamansi Project | I16: Completed | J16: SUC/HEI | K16: External | L16: CHED | M16: Retail Sales | N16: N/A
A17: 2021 | B17: 44435 | E17: Carolyn T. Mejares | F17: P-2021-015 | G17: Effect of high temperature treatments on buffalo milk and buffalo bovine milk blends | H17: Mejares | I17: Cancelled | J17: UP System | L17: N/A | N17: N/A
A18: 2022 | B18: 44579 | E18: Rowena E. Cadiz | F18: P-2022-016 | G18: Development of immunoactive and growth promoting AquaFeed additive from Ulva seaweed | H18: AquaFeed | I18: Cancelled | J18: UP System | K18: External | L18: DOST-PCAARRD | M18: Equipment Use | N18: N/A
A19: 2022 | B19: 44622 | D19: Shea Kathleen P. Guinto | E19: Eric Zeus C. Rizo | F19: P-2022-017 | G19: Development of a Water Quality Biological Monitoring Protocol using Genetic, Phylogenetic and Functional Diversity on Freshwater Zooplankton Communitites in Inland Waters of Panay Island, Philippines | H19: PFZ | I19: Ongoing | J19: UP System | K19: External | L19: DOST-PCIEERD | M19: Equipment Use | N19: Nadelene Faith Cartago
A20: 2022 | B20: 44622 | C20: 44865 | E20: Rother M. Gaudiel | F20: P-2022-018 | G20: Fishery and Some Aspects on the Biology and Ecology of the Sergestid Shrimp, Acetes, in Miagao, Iloilo | H20: RGaudiel | I20: Completed | J20: UP System | K20: External | L20: DOST-ASTHRDP Thesis Grant | M20: Equipment Use | N20: Nadelene Faith Cartago
A21: 2022 | B21: 44624 | C21: 44687 | E21: John Rey F. Rasgo | F21: P-2022-019 | G21: Genetic Marker Assessment of 12s and 18s of Kappaphycus striatus collected in Palawan | H21: JRRasgo | I21: Completed | J21: UP System | K21: External | L21: c/o Global Seaweed STAR Project | M21: Equipment Use | N21: Nadelene Faith Cartago
A22: 2022 | B22: 44628 | C22: 44986 | E22: Luke Dranoel D. Atencio | F22: P-2022-020 | G22: ESKAPE Pathogens in Intensive Care Unit from a Tertiary Healthcare Setting | H22: LDAtencio | I22: Completed | J22: SUC/HEI | K22: External | L22: N/A | M22: Equipment Use | N22: Jasmine Velo
A23: 2022 | B23: 44634 | C23: 44687 | E23: Whelver N. Surnido | F23: P-2022-021 | G23: Dynamics of the Epibacterial Community Structure and Composition of Kappaphycus alvarezii in Response to Thermal-induced Ice-ice Disease | H23: WNSurnido | I23: Completed | J23: UP System | K23: External | L23: c/o Ice-ice Project | M23: Equipment Use | N23: Ma Carmel Javier
A24: 2022 | B24: 44644 | C24: 44712 | E24: Kingsley John de los Santos | F24: P-2022-022 | G24: Assessment of Anthropogenic Marine Debris and Mangrove Forest Health in Iloilo Strait, Western Visayas, Philippines | H24: KDSantos | I24: Completed | J24: UP System | K24: External | L24: DOST-ASTHRDP Thesis Grant | M24: Retail Sales | N24: N/A
A25: 2022 | B25: 44645 | C25: 44727 | E25: Karl C. Abismo | F25: P-2022-023 | G25: Assessment of Antimicrobial Activitiy of Selected Fungi from Tilapia Greenwater Technology Against Vibrio parahaemolyticus in Blood Cockle, Anadara granosa | H25: KCAbismo | I25: Completed | J25: UP System | K25: External | L25: DOST Thesis Grant | M25: Equipment Use | N25: Jasmine Velo
A26: 2022 | B26: 44680 | C26: 45016 | E26: Benedict Maralit | F26: P-2022-024 | G26: Sequencing and Analysis of SARS-CoV-2 genomes in swab specimens collected by subnational / DOH-accredited COVID-19 laboratories in the Philippines from March to October 2020 | H26: Retrospective Biosurveillance | I26: Completed | J26: UP System | K26: External | L26: PGC Visayas | M26: Equipment Use | N26: N/A
A27: 2022 | B27: 44680 | E27: Philip Alviola | F27: P-2022-025 | G27: Molecular detection of Henipa and Coronavirus in Flying Fox (Order Chiroptera: Family Pteropodidae) roost within First Gas Plant Site, Batangas City | H27: Bats | I27: Ongoing | J27: UP System | K27: In-House | L27: PGC Visayas | M27: Equipment Use | N27: Jasmine Velo
A28: 2022 | B28: 44682 | E28: Persie Persie Mark Sienes | F28: P-2022-026 | G28: Whole Genome Sequencing of the Philippine spotted deer (Rusa alfredi) | H28: PGCV_Deer WGS | I28: Ongoing | J28: SUC/HEI | K28: In-House | L28: PGC Visayas | M28: Laboratory Services | N28: Ma Carmel Javier
A29: 2022 | B29: 44682 | C29: 45229 | E29: Beverly T. Jaspe | F29: P-2022-027 | G29: Genomic variations among different (meta) populations of oriental angelwing clam (Pholas orientalis) in the Western Visayas, Philippines: basis for conservation breeding program | H29: Pholas | I29: Completed | J29: SUC/HEI | K29: External | L29: DOST-NRCP NSTEP | M29: Equipment Use | N29: Ma Carmel Javier
A30: 2022 | B30: 44718 | C30: 44926 | E30: Camille Rose T. Mueda | F30: P-2022-028 | G30: Metagenomic Characterization of Oil-degrading Microbial Communities from Slipper-shaped Oyster (Magallana bilineata) in Oil-contaminated Areas along Iloilo Strait, Philippines | H30: Mueda | I30: Completed | J30: UP System | K30: External | L30: PGC Visayas | M30: Equipment Use | N30: Ma Carmel Javier
A31: 2022 | B31: 44725 | D31: Kneessa Louie G. Dato-on | E31: Therese Javellana | F31: P-2022-029 | G31: Isolation, Characterization and Phylogenetic identification of Thraustochytrids from mangrove habitats around Panay Island, Philippines | H31: Thrausto | I31: Ongoing | J31: UP System | K31: In-House | L31: PGC Visayas | M31: Laboratory Services | N31: kgdatoon@up.edu.ph
A32: 2022 | B32: 44729 | C32: 44773 | E32: Zeth Rodario Bebit | F32: P-2022-030 | G32: Marine Fisheries Assessment of Panay: Building Local Fisheries Information through Research Capability Enhancement in HEIs Component 3: Chemical Composition of Marine Fishes – Leverage Research Project (SP20-14) | H32: Bebit | I32: Completed | J32: UP System | K32: External | L32: CHED | M32: Equipment Use | N32: Ma Carmel Javier
A33: 2022 | B33: 44754 | C33: 44773 | E33: Angel Queenee D. Dequito | F33: P-2022-031 | G33: Transcriptome and Gut Metagenome Profile of Penaeus vannamei Exposed to Fluctuating Environmental Temperatures | H33: TGMPPEFET | I33: Completed | J33: UP System | K33: External | L33: DOST-PCAARRD | M33: Equipment Use | N33: Ma Carmel Javier
A34: 2022 | B34: 44763 | C34: 45107 | D34: Isabel Grace Gatpatan | E34: Rhudith Cabulong | F34: P-2022-032 | G34: Diversity and screening of culturable cellulytic microorganisms from mangrove forests, natural parks, paddy field, and sugar plantation in Panay Island, Philippines | H34: Cabulong, (OM,CM) | I34: Completed | J34: UP System | K34: In-House | L34: UPV Regular In-House Research (RIR) | M34: Laboratory Services | N34: Jasmine Velo
A35: 2022 | B35: 44835 | D35: Frenche B. Hechanova | E35: Rommel Gestuveo | F35: P-2022-033 | G35: Development of Novel Antiviral Compounds against Arthropod-borne Viruses | H35: DeNoVac | I35: Ongoing | J35: UP System | K35: External | L35: DOST-DST JRP | M35: Equipment Use | N35: Ma Carmel Javier
A36: 2022 | B36: 44859 | D36: Cezarie L. Golingay Ella Marie E. Villaruz Antoniette Lorain Z. Dimaano Arnel Adrian Rara | E36: Jade G. Pahila | F36: P-2022-034 | G36: Production and evaluation of Dried Microalgal Biomass for improved shelf life and product diversification | H36: Microalgae | I36: Completed | J36: UP System | K36: External | L36: DOST-PCAARD | M36: Equipment Use | N36: Jasmine Velo
A37: 2022 | B37: 44902 | C37: 45107 | E37: Pauline Anne Lamela | F37: P-2022-035 | G37: Isolation, Characterization, And Identification of Plastic-Degrading Bacteria From Bago City Landfill, Negros Occidental, Philippines | H37: Lamela | I37: Completed | J37: UP System | K37: External | L37: N/A | M37: Laboratory Services | N37: Nadelene Faith Cartago
A38: 2022 | B38: 44910 | C38: 45069 | D38: Emelyn Joy Mameloco Edcel T. Resano | E38: Raymond Cabarles | F38: P-2022-036 | G38: MS Aqua Fish 219 (Advanced Genetics) | H38: Cabarles et al | I38: Completed | J38: UP System | K38: In-House | L38: N/A | M38: Laboratory Services | N38: Jasmine Velo
A39: 2023 | B39: 44964 | E39: Dr. Sitti Zayda Halun | F39: P-2023-037 | G39: Amplicon Sequencing of Seaweed | H39: Halun | I39: Ongoing | J39: SUC/HEI | K39: External | L39: MSU TCTO | M39: Laboratory Services | N39: Nadelene Faith Cartago
A40: 2023 | B40: 44993 | C40: 45069 | E40: PGC Visayas | F40: P-2023-038 | G40: Molecular identification of Dugong (Batch 1) | H40: Dugong - Miagao | I40: Completed | J40: UP System | K40: In-House | L40: PGC Visayas | M40: Laboratory Services, Bioinformatics Analysis | N40: N/A
A41: 2023 | B41: 44999 | C41: 45199 | D41: Claire Samantha Juanico | E41: Elsie Y. Guibone | F41: P-2023-039 | G41: Fish 258 - Marine Biotechnology: Identification of Lernaea using 18s primers | H41: Lernaea | I41: Completed | J41: UP System | K41: In-House | L41: PGC Visayas | M41: Equipment Use | N41: N/A
A42: 2023 | B42: 44999 | E42: Claire Samantha Juanico | F42: P-2023-040 | G42: Gut Metabarcoding | H42: Fish Gut | I42: Ongoing | J42: UP System | K42: In-House | L42: PGC Visayas | M42: Equipment Use | N42: N/A
A43: 2023 | B43: 45007 | C43: 45072 | D43: Karmelie Jane Monaya | E43: Rose Ann Lumapan | F43: P-2023-041 | G43: Real-time PCR Detection of Foodborne Pathogens in Oyster from local markets in Iloilo | H43: Lumapan | I43: Completed | J43: UP System | K43: In-House | L43: PGC Visayas | M43: Equipment Use | N43: Nadelene Faith Cartago
A44: 2023 | B44: 45035 | C44: 45083 | E44: Beatrice L. Anacita | F44: P-2023-042 | G44: Bacterial Biofilm Formation and Inhibition Potential of Wild Macrofungi from Miagao, Iloilo | H44: Anacita | I44: Completed | J44: UP System | K44: External | L44: N/A | M44: Equipment Use | N44: stevenmosura@gmail.com
A45: 2023 | B45: 45035 | C45: 45083 | E45: Kyla Julienne P. Talaman | F45: P-2023-043 | G45: Prebiotic potential of Beta-glucan extracted from macrofungu found in Miagao, Iloilo | H45: Talaman | I45: Completed | J45: UP System | K45: External | L45: N/A | M45: Equipment Use | N45: stevenmosura@gmail.com
A46: 2023 | B46: 45036 | C46: 45083 | E46: Trisha Marie Santos | F46: P-2023-044 | G46: Prebiotic potential of Beta-glucan extracted from macrofungu found in Miagao, Iloilo | H46: Santos | I46: Completed | J46: UP System | K46: External | L46: N/A | M46: Equipment Use | N46: stevenmosura@gmail.com
A47: 2023 | B47: 45051 | C47: 45079 | E47: Trisha Catalya | F47: P-2023-045 | G47: Detection of E. coli and Salmonella using Culture-Independent Methods in Spiked Oyster Ostreidaei | H47: Catalya | I47: Completed | J47: UP System | K47: In-House | L47: N/A | M47: Equipment Use | N47: Nadelene Faith Cartago
A48: 2023 | B48: 45051 | C48: 45079 | E48: Josie Mar G. Cabalo_Thesis | F48: P-2023-046 | G48: Detection of Vibrio parahaemolyticus and Vibrio cholerae in Oyster using Quantitative Real-Time Polymerase Chain Reaction (qPCR) | H48: Cabalo | I48: Completed | J48: UP System | K48: In-House | L48: N/A | M48: Equipment Use | N48: Nadelene Faith Cartago
A49: 2023 | B49: 45062 | C49: 45107 | E49: Carlo S. Gregorio | F49: P-2023-047 | G49: Detection of Vibrio parahaemolyticus and Vibrio cholerae in Oyster using Quantitative Real-Time Polymerase Chain Reaction (qPCR) Characterization Of Picophytoplankton Abundance And Distribution In Relation To Varying Environmental Conditions In The Bay Zone Of The Batan Bay Estuary | H49: LN - Gregorio, Sibulan | I49: Completed | J49: UP System | K49: In-House | L49: N/A | M49: Retail Sales | N49: alex.cayanan2@gmail.com
A50: 2023 | B50: 45062 | C50: 45107 | E50: Elize Margareth C. Sibulan | F50: P-2023-047 | G50: Detection of Vibrio parahaemolyticus and Vibrio cholerae in Oyster using Quantitative Real-Time Polymerase Chain Reaction (qPCR) Characterization Of Picophytoplankton Abundance And Distribution In Relation To Varying Environmental Conditions In The Bay Zone Of The Batan Bay Estuary | H50: LN - Gregorio, Sibulan | I50: Completed | J50: UP System | K50: In-House | L50: N/A | M50: Retail Sales | N50: alex.cayanan2@gmail.com
A51: 2023 | B51: 45082 | C51: 45229 | E51: Ella Marie Kristine Baldove | F51: P-2023-048 | G51: Molecular identification of microalgae | H51: Feedmix | I51: Completed | J51: UP System | K51: External | L51: PGC Visayas | M51: Laboratory Services | N51: Ma Carmel Javier
A52: 2023 | B52: 45083 | C52: 45107 | E52: Abigail F. Padua | F52: P-2023-049 | G52: The effect of fermented silage on sperm quality of mixed-breed anglo nubian goats in Romblon | H52: LN - Padua | I52: Completed | J52: UP System | K52: External | L52: N/A | M52: Retail Sales | N52: alex.cayanan2@gmail.com
A53: 2023 | B53: 45083 | C53: 45229 | D53: Jojie P. Gereza | E53: Rachel A. Casio | F53: P-2023-050 | G53: Molecular identification of Warty Pig and Hawk Eagle | H53: DENR | I53: Completed | J53: Government | K53: In-House | L53: PGC Visayas | M53: Laboratory Services | N53: Nadelene Faith Cartago
A54: 2023 | B54: 45091 | C54: 45199 | E54: Ma Jowina Galarion | F54: P-2023-051 | G54: Assessing the feasibility of implementing field deployable sequencing applied to dengue virus surveillance in the Philippines | H54: Dengue Seq | I54: Completed | J54: UP System | K54: External | L54: Medical Research Council - University of Glasgow Centre for Virus Research | M54: Equipment Use | N54: Ma Carmel Javier
A55: 2023 | B55: 45119 | D55: James Nim Jan Felnesh Exe Bagacay | E55: Mark S. Calabon | F55: P-2023-052 | G55: Unraveling the Hidden Diversity of Aquatic Fungi from Panay Island, Philippines Project | H55: AQFP | I55: Ongoing | J55: UP System | K55: In-House | L55: DOST | M55: Laboratory Services | N55: Jasmine Velo
A56: 2023 | B56: 45125 | C56: 45229 | E56: Sheryll Mesa | F56: P-2023-053 | G56: Molecular identification of Kogiid whale stranded in Sicogon Island, Carles, Iloilo | H56: BFAR Sperm Whale | I56: Completed | J56: International | K56: External | L56: PGC Visayas | M56: Laboratory Services | N56: Nadelene Faith Cartago
A57: 2023 | B57: 45140 | C57: 45149 | E57: Krshna Mahakaola A. Dueñas | F57: P-2023-054 | G57: Effects of Crown-of-Thorns (Acanthaster planci) Starfish as a Growth Enhacer in White Mice (Mus musculus) | H57: LN - Dueñas | I57: Completed | J57: UP System | K57: External | L57: N/A | M57: Retail Sales | N57: alex.cayanan2@gmail.com
A58: 2023 | B58: 45154 | C58: 45301 | D58: Danielle L. Elevado Yoo Ki Bastol Zeb Jose Joshua C. Cabalfin Maio Vendell V. Sabidong Jemma Dawn C. Leonardo Leopoldo T. Bacquial II Kathleen Mae V. Donoso Nove Kris B. Herida Angel Mae T. Malones Adrienne Marrie S. Bugayon-Janagap Stephen G. Sabinay | E58: Franco MIguel N. Nodado | F58: P-2023-055 | G58: Inhibitory Activity of Vitex negundo (Lagundi) Leaf Extract Against Biofilm Formation and Quorom Sensing of Vibrio cholerae | H58: V. cholerae (WVSU) | I58: Completed | J58: SUC/HEI | K58: In-House | L58: N/A | M58: Laboratory Services | N58: Jasmine Velo
A59: 2023 | B59: 45167 | C59: 45189 | E59: Joseph Faisan Jr. | F59: P-2023-056 | G59: Fish Species ID | H59: SEAFDEC (Eel) | I59: Completed | J59: International | K59: External | L59: N/A | M59: Laboratory Services | N59: Ma Carmel Javier
A60: 2023 | B60: 45180 | E60: Nadine Belas | F60: P-2023-057 | G60: The Complete Mitogenome of Placuna placenta and its Phylogenetic Implications | H60: Kapis | I60: Completed | J60: UP System | K60: External | L60: N/A | M60: Equipment Use | N60: Ma Carmel Javier
A61: 2023 | B61: 45190 | D61: Eric Zeus C. Rizo | E61: Maureen Emily V. Niño | F61: P-2023-058 | G61: Diversity assessment of freshwater zooplankton and macroinvertebrates towards identification of centers of biodiversity conservation in the Jalaur River Basin, Iloilo, Philippines | H61: DAFZooMacro | I61: Ongoing | J61: UP System | K61: External | L61: OVPAA Balik PhD | M61: Equipment Use | N61: dapenuela@up.edu.ph
A62: 2023 | B62: 45222 | C62: 45308 | E62: PGC VISAYAS | F62: P-2023-059 | G62: Comparative analyses of genomic DNA extracted from fish tissue preserved in 70% alcohol, LN, and absolute ethanol in different periods of time and temperature | H62: Commercial Alcohol Preservation | I62: Ongoing | J62: UP System | K62: In-House | M62: Laboratory Services | N62: Nadelene Faith Cartago
A63: 2023 | B63: 45239 | C63: 45239 | E63: MinSU Bioinfo | F63: P-2023-060 | G63: MinSU Bioinfo Analysis | H63: MinSU Bioinfo | I63: Cancelled | J63: UP System | K63: N/A | L63: N/A | M63: Equipment Use
A64: 2023 | B64: 45240 | C64: 45272 | D64: Christine Teves | E64: Philip Ian P. Padilla | F64: P-2023-061 | G64: Integrating early warning systems for community outbreaks using water-based epidemiology during post-COVID-19 pandemic | H64: PIPP - EIDR | I64: Completed | J64: UP System | K64: In-House | L64: UP OVPAA EIDR Cycle 9 | M64: Laboratory Services | N64: Ma Carmel Javier
A65: 2023 | B65: 45247 | E65: LC May C. Gasit | F65: P-2023-062 | G65: Development of spawning and hatchery techniques for the blood cockle (Anadara granosa) for sustainable aquaculture | H65: Blood Cockle Project | I65: Ongoing | J65: UP System | K65: External | L65: DOST-PCAARRD | M65: Equipment Use | N65: Ma Carmel Javier
A66: 2023 | B66: 45272 | C66: 45316 | E66: Jojie P. Gereza | F66: P-2023-063 | G66: Molecular identification of Snake | H66: DENR - Snake | I66: Completed | J66: Government | K66: In-House | L66: N/A | M66: Laboratory Services | N66: Nadelene Faith Cartago
A67: 2024 | B67: 45316 | E67: Jonie C. Yee, Ph.D. | F67: P-2024-064 | G67: Detection of Natural Products Derived from Sediment Microbes in Mangrove | H67: Nat Prod (USC) - Dr. Yee | I67: Ongoing | J67: SUC/HEI | K67: External | L67: NRCP-DOST | M67: Laboratory Services
A68: 2024 | B68: 45321 | E68: PGC Visayas | F68: P-2024-065 | G68: Diwal Long Range PCR | H68: Diwal WGS | I68: Completed | J68: UP System | K68: In-House | L68: PGC Visayas | M68: Laboratory Services
A69: 2024 | B69: 45321 | E69: PGC Visayas | F69: P-2024-066 | G69: Shotgun metagenomic analysis of DNA preserved whale ambergris from Antique | H69: Ambergris | I69: Ongoing | J69: UP System | K69: In-House | L69: PGC Visayas | M69: Laboratory Services
A70: 2024 | B70: 45329 | C70: 45329 | E70: Kaylen Yvon K. Jalandoni | F70: P-2024-067 | G70: Mango Leaves-derived Biochar for the Removal of Amoxicillin in Aqueous Solution | H70: Jalandoni - Type II | I70: Completed | J70: UP System | K70: External | L70: N/A | M70: Retail Sales | N70: alex.cayanan2@gmail.com
A71: 2024 | B71: 45335 | C71: 45335 | E71: Ram Nikko U. Delegero | F71: P-2024-068 | G71: Transesterification of Waste Vegetable Oil from Oil-based Thermal Disinfection Technology using SrO/CaO Bamboo Biochar Composite | H71: Delegero - Type II | I71: Completed | J71: UP System | K71: External | L71: N/A | M71: Retail Sales | N71: alex.cayanan2@gmail.com
A72: 2024 | B72: 45337 | D72: Jordan F. Dorado | E72: Vincent Jay H. Gado | F72: P-2024-069 | G72: Composition and diversity of gut microbiota of Conomurex luhuanus | H72: Gastropod (RSU) | I72: Completed | J72: SUC/HEI | K72: In-House | L72: PGC Visayas | M72: Equipment Use | N72: dapenuela@up.edu.ph
A73: 2024 | B73: 45344 | D73: Caryl Anne G. Abulencia | E73: Jessette Mary Pauline Garcia | F73: P-2024-070 | G73: DNA Barcoding and Depuration Protocol of Windowpane oysters (Placuna placenta) from Oton, Iloilo | H73: Capiz Shell (WVSU) | I73: Completed | J73: SUC/HEI | K73: In-House | L73: N/A | M73: Laboratory Services
A74: 2024 | B74: 45355 | E74: Dianne A. Peralta | F74: P-2024-071 | G74: Development of Probiotics from roselle (Hibiscus sabdariffa), mulberry (Morus alba), and corn (Zea mays) | H74: DMMMSU - Amplicon | I74: Completed | J74: SUC/HEI | K74: External | L74: CHED-LAKAS | M74: Laboratory Services | N74: Ma Carmel Javier
A75: 2024 | B75: 45355 | E75: Dianne A. Peralta | F75: P-2024-072 | G75: Development of Probiotics from roselle (Hibiscus sabdariffa), mulberry (Morus alba), and corn (Zea mays) | H75: DMMMSU - 16s | I75: Completed | J75: SUC/HEI | K75: External | L75: CHED-LAKAS | M75: Laboratory Services | N75: Ma Carmel Javier
A76: 2024 | B76: 45355 | E76: Dianne A. Peralta | F76: P-2024-073 | H76: Sea Cucumber (16s) | I76: Completed | J76: SUC/HEI | K76: External | L76: N/A | M76: Laboratory Services | N76: Ma Carmel Javier
A77: 2024 | B77: 45364 | E77: Mae Dell S. Silfavan | F77: P-2024-074 | G77: Optimization of DNA Extraction and DNA Barcoding of Farmed Eucheumatoid Species in San Dionisio, Iloilo | H77: Seaweed (BSF) A | I77: Completed | J77: UP System | K77: In-House | L77: PGC Visayas | M77: Equipment Use | N77: Nadelene Faith Cartago | O77: with Dianne
A78: 2024 | B78: 45364 | E78: Jinelyn D. Kapaw-an | F78: P-2024-075 | G78: Optimization of Different DNA Extraction Protocols for Ulva spp. | H78: Seaweed (BSF) B | I78: Completed | J78: UP System | K78: In-House | L78: PGC Visayas | M78: Equipment Use | N78: Nadelene Faith Cartago | O78: with Dianne
A79: 2024 | B79: 45364 | E79: Princess Sarah Gabiota | F79: P-2024-076 | G79: Optimization of DNA Extraction Protocol and DNA Barcoding of Sargassum sp. found in San Lorenzo, Guimaras | H79: Seaweed (BSF) C | I79: Completed | J79: UP System | K79: In-House | L79: PGC Visayas | M79: Equipment Use | N79: Nadelene Faith Cartago | O79: with Dianne
A80: 2024 | B80: 45364 | D80: Kharl Marx Adorado | E80: Stephanie Faith Apines | F80: P-2024-077 | G80: Microbial Community Assemblage of Heliopora corulea coral in Nogas Island Intertidal Zone. | H80: Corals | I80: Completed | J80: UP System | K80: In-House | L80: CFOS-IMFO | M80: Equipment Use | N80: Nadelene Faith Cartago
A81: 2024 | B81: 45364 | E81: - | F81: P-2024-078 | G81: DNA Barcoding of Marine Microalgae (Tetraselmis sp.) | H81: Tetraselmis | I81: Completed | J81: UP System | K81: In-House | L81: CFOS-IMFO | M81: Equipment Use
A82: 2024 | B82: 45364 | E82: Kristina Casandra Pava | F82: P-2024-079 | G82: . | H82: Pava - Bioinfo | I82: Completed | J82: SUC/HEI | K82: External | L82: PGC Visayas | M82: Laboratory Services | O82: Bioinfo
A83: 2024 | B83: 45362 | E83: Marielle B. Chu | F83: P-2024-080 | G83: Isolation and characterization of cellulolytic bacteria from decomposing leaf litter | H83: UPHSI - Chu | I83: Completed | J83: UP System | K83: External | L83: N/A | M83: Laboratory Services | N83: stevenmosura@gmail.com
A84: 2024 | B84: 45378 | C84: 45393 | E84: Clarissa L. Gomez | F84: P-2024-081 | G84: Role of Type VI Secretion System During Shrimp Infection of Vibrio spp. - Causing Acute Hepatopancreatic Necrosis Disease (AHPND) | H84: Vibrio - Bioinfo | I84: Completed | J84: Government | K84: External | L84: N/A | M84: Laboratory Services
A85: 2024 | B85: 45385 | C85: 45399 | D85: Vien Lowell M. Mapa Lesther G. Tadeña Joshua Miguel Javelosa | E85: Arlz Dominic E. Libanan | F85: P-2024-082 | G85: Effects of pH and Temperature on the Biofilm Formation and algD Gene Expression in Pseudomonas aeruginosa Clinical Isolates | H85: USLS - gene expression | I85: Completed | J85: SUC/HEI | K85: External | L85: N/A | M85: Laboratory Services | N85: Jasmine Velo
A86: 2024 | B86: 45385 | C86: 45399 | D86: Elizabeth D. Fernandez Karyl Jisabel D. Genosa Maria Alexandra S. Geolingo | E86: Briane S. Deo | F86: P-2024-083 | G86: Characterizing the Water Physiochemical Properties and Resident Microalgae Community of Cabaghauan Creek, Bacolod City | H86: USLS - algae | I86: Completed | J86: SUC/HEI | K86: External | L86: N/A | M86: Laboratory Services | N86: Jasmine Velo
A87: 2024 | B87: 45390 | D87: Carmelo del Castillo | E87: Josie Mar G. Cabalo | F87: P-2024-084 | G87: Improvement of Milkfish Larval Rearing and Nursery Culture through Gut Metagenome, Transcriptome Analysis, and Gut Microbial Community Manipulations | H87: MF Gut | I87: Ongoing | J87: UP System | K87: External | L87: DOST-PCAARRD | M87: Laboratory Services | N87: Ma Carmel Javier
A88: 2024 | B88: 45399 | E88: Angel Ann H. Vargas | F88: P-2024-085 | G88: Evaluation on the use of Lachancea spp. and Nannochlopsis occulata paste to improve the yield and quality of rotifer Brachionus rotundiformis | H88: Yeast (BSF) | I88: Completed | J88: UP System | K88: In-House | L88: N/A | M88: Equipment Use | N88: Ma Carmel Javier
A89: 2024 | B89: 45414 | C89: 45469 | E89: Anne-Nora N. Sabirin | F89: P-2024-086 | G89: Metabarcoding of Goat feces for Gastrointestinal nematode identification | H89: Goat (Sabirin, MSU IIT) | I89: Completed | J89: SUC/HEI | K89: External | M89: Laboratory Services | O89: Anne
A90: 2024 | B90: 45415 | D90: Gleann P. Salido Charles R. Andrade Clarnic A. Berbegal | E90: Sanny David Lumayno | F90: P-2024-087 | G90: Molecular Guided Techniques for Improvement of Reproduction Performance of Saline-Tolerant Tilapia | H90: RepPer SPIN | I90: Ongoing | J90: UP System | K90: External | L90: DOST-PCAARRD | M90: Laboratory Services, Equipment Use | N90: Ma Carmel Javier
A91: 2024 | B91: 45418 | C91: 45469 | E91: Gavin Louie M. Amolo | F91: P-2024-088 | G91: Microbes Beneath the Surface: Exploring Diversity and Distribution of Microbial Species on Different Soil Samples in Siargao Island | H91: Soil 16s (Siargao NHS) | I91: Completed | J91: SUC/HEI | K91: External | L91: N/A | M91: Laboratory Services | N91: stevenmosura@gmail.com
A92: 2024 | B92: 45419 | C92: 45447 | E92: John Paul Resano | F92: P-2024-089 | G92: Detection of Salmonella in Barn Swallow (Hirundu rustica) in Banga, Aklan | H92: Salmonella sp. | I92: Completed | J92: SUC/HEI | K92: External | L92: N/A | M92: Laboratory Services | N92: Jasmine Velo
A93: 2024 | B93: 45427 | D93: Dr. Jeannemar Genevive Y. Figueras | E93: Laura Elyse J. Cambel | F93: P-2024-090 | G93: Understanding Endophytic Fungi in Medicinal Plants and their Antibacterial Potential on Common and Antibiotic-Resistant Bacteria (ESKAPE pathogens) | H93: WVSU_16s Amplicon | I93: Completed | J93: SUC/HEI | K93: External | L93: DOST/WVSU Main | M93: Laboratory Services | N93: Jasmine Velo
A94: 2024 | B94: 45414 | D94: Carmelo del Castillo | E94: Nikka Marie Murallon | F94: P-2024-091 | G94: Marker assisted selection of saline tolerant tilapia for enhanced growth and feed conversion efficiency (del Castillo) | H94: CdC_Tilapia Mitogenome | I94: Ongoing | J94: UP System | K94: External | L94: DOST-PCAARRD | M94: Laboratory Services | N94: Ma Carmel Javier
A95: 2024 | B95: 45456 | E95: Ryuya Matsuda | F95: P-2024-092 | G95: Identification of seaweed species using DNA sequence | H95: JIRCAS - Matsuda | I95: Completed | J95: International | K95: External | L95: N/A | M95: Laboratory Services | N95: Ma Carmel Javier
A96: 2024 | B96: 45483 | E96: Dencee Jean T. Ledesma | F96: P-2024-093 | G96: Development of a LAMP-Based Detection Kit for Tomato Yellow Leaf Curl Virus (TYLCV) Philippine Strains | H96: DOST VIP_Tomato WGS | I96: Completed | J96: Government | K96: External | L96: DOST VIP | M96: Laboratory Services | N96: Jasmine Velo
A97: 2024 | B97: 45491 | E97: Noeme D. Pajarillo | F97: P-2024-094 | G97: Evaluation of the Reproductive Condition and Environmental DNA of Green Mussel Culture in Samar, Philippines | H97: Mussel eDNA | I97: Completed | J97: UP System | K97: External | L97: DOST-ASTHRDP | M97: Laboratory Services | N97: Jasmine Velo
A98: 2024 | B98: 45518 | E98: Fermina Genson | F98: P-2024-095 | G98: Extraction of Larvae from VSU | H98: VSU Larvae | I98: Completed | J98: SUC/HEI | K98: External | L98: NA | M98: Laboratory Services | N98: dapenuela@up.edu.ph
A99: 2024 | B99: 45531 | E99: Fausto dela Cruz | F99: P-2024-096 | G99: Growth Performance and Genetic Characterization of Tilapia Strains in Culasi, Antique, Phiippines | H99: iBest/inbreed | I99: Completed | J99: SUC/HEI | K99: External | L99: BFAR | M99: Laboratory Services | N99: Jasmine Velo
A100: 2024 | B100: 45539 | E100: DA-BAI | F100: P-2024-097 | G100: Validation of Protocol for Enriched Amplicon Sequencing of ASFV | H100: ASFV | I100: Completed | J100: Government | K100: External | L100: TBA | M100: Laboratory Services | N100: Ma Carmel Javier
...

Sheet Charge SlipBilling
A1: Year | B1: Date | C1: Charge Slip No. (CS-yyyy-xxx) | D1: Client Name | E1: Amount | F1: Status | G1: Client ID | H1: Address | I1: Project/Training Request No. | J1: Payment For (Project/Training Title) | K1: Service Requested | L1: Service Details | M1: R&D Category | N1: DV No. | O1: OR No. | P1: Date of OR | Q1: Notes
A2: 2020 | B2: 44176 | C2: CS-2020-12-001 | D2: Dominique P. Mediodia | E2: 8597.6 | F2: PAID | G2: =IFERROR(VLOOKUP(D2,'Client ID Records_v2'!D:E, 2, FALSE), "") -> CL-2020-019 | H2: =IFERROR(VLOOKUP(G2,'Client ID Records_v2'!E:F, 2, FALSE), "") -> Institute of Marine Fisheries and Oceanology, College of Fisheries and Ocean Sciences, University of the Philippines Visayas | I2: =IFERROR(VLOOKUP(D2,'Project Records_v2'!E:F, 2, FALSE), "") -> P-2020-008 | J2: =IFERROR(VLOOKUP(I2,'Project Records_v2'!F:G, 2, FALSE), "") -> Marine Fisheries Assessment of Panay: Building Local Fisheries Information through Research Capability Enhancement on Higher Education Insitutions | K2: Equipment Use | L2: N/A | M2: Laboratory Service | N2: TF-2020-12-09150
A3: 2021 | B3: 44258 | C3: CS-2021-03-002 | D3: Dominique P. Mediodia | E3: 7335.24 | F3: PAID | G3: =IFERROR(VLOOKUP(D3,'Client ID Records_v2'!D:E, 2, FALSE), "") -> CL-2020-019 | H3: =IFERROR(VLOOKUP(G3,'Client ID Records_v2'!E:F, 2, FALSE), "") -> Institute of Marine Fisheries and Oceanology, College of Fisheries and Ocean Sciences, University of the Philippines Visayas | I3: =IFERROR(VLOOKUP(D3,'Project Records_v2'!E:F, 2, FALSE), "") -> P-2020-008 | J3: =IFERROR(VLOOKUP(I3,'Project Records_v2'!F:G, 2, FALSE), "") -> Marine Fisheries Assessment of Panay: Building Local Fisheries Information through Research Capability Enhancement on Higher Education Insitutions | K3: Equipment Use | L3: N/A | M3: Laboratory Service | N3: TF-2021-04-02791 | O3: 493079 | P3: 44305
A4: 2021 | B4: 44341 | C4: CS-2021-05-003 | D4: Dominique P. Mediodia | E4: 24210.2 | F4: PAID | G4: =IFERROR(VLOOKUP(D4,'Client ID Records_v2'!D:E, 2, FALSE), "") -> CL-2020-019 | H4: =IFERROR(VLOOKUP(G4,'Client ID Records_v2'!E:F, 2, FALSE), "") -> Institute of Marine Fisheries and Oceanology, College of Fisheries and Ocean Sciences, University of the Philippines Visayas | I4: =IFERROR(VLOOKUP(D4,'Project Records_v2'!E:F, 2, FALSE), "") -> P-2020-008 | J4: =IFERROR(VLOOKUP(I4,'Project Records_v2'!F:G, 2, FALSE), "") -> Marine Fisheries Assessment of Panay: Building Local Fisheries Information through Research Capability Enhancement on Higher Education Insitutions | K4: Equipment Use | L4: N/A | M4: Laboratory Service | N4: TF-2021-06-04996 | O4: 495221 | P4: 44368
A5: 2021 | B5: 44384 | C5: CS-2021-07-004 | D5: Dominique P. Mediodia | E5: 24210.2 | F5: PAID | G5: =IFERROR(VLOOKUP(D5,'Client ID Records_v2'!D:E, 2, FALSE), "") -> CL-2020-019 | H5: =IFERROR(VLOOKUP(G5,'Client ID Records_v2'!E:F, 2, FALSE), "") -> Institute of Marine Fisheries and Oceanology, College of Fisheries and Ocean Sciences, University of the Philippines Visayas | I5: =IFERROR(VLOOKUP(D5,'Project Records_v2'!E:F, 2, FALSE), "") -> P-2020-008 | J5: =IFERROR(VLOOKUP(I5,'Project Records_v2'!F:G, 2, FALSE), "") -> Marine Fisheries Assessment of Panay: Building Local Fisheries Information through Research Capability Enhancement on Higher Education Insitutions | K5: Equipment Use | L5: N/A | M5: Laboratory Service | N5: TF-2021-07-06176 | O5: 497555 | P5: 44405
A6: 2021 | B6: 44392 | C6: CS-2021-07-005 | D6: Arlene L . Avillanosa | E6: 600000.85 | F6: PAID | G6: =IFERROR(VLOOKUP(D6,'Client ID Records_v2'!D:E, 2, FALSE), "") -> CL-2021-031 | H6: =IFERROR(VLOOKUP(G6,'Client ID Records_v2'!E:F, 2, FALSE), "") -> Room 9, Second Floor (ABBA R&D Center), College of Fisheries and Aquatic Science (CFAS), WPU-Puerto Princesa Campus, Sta. Monica, Puerto Princesa City | I6: =IFERROR(VLOOKUP(D6,'Project Records_v2'!E:F, 2, FALSE), "") -> P-2021-013 | J6: =IFERROR(VLOOKUP(I6,'Project Records_v2'!F:G, 2, FALSE), "") -> Genetic Characterization of Macrobrachium populations in the Philippines for broodstock development and seed production | K6: Laboratory Service | L6: Extraction to Amplicon Sequencing | M6: R&D | N6: Thru Bank Deposit | O6: 498868 | P6: 44459
A7: 2021 | B7: 44403 | C7: CS-2021-07-006 | D7: Concepcion Ponce | F7: CANCELLED | G7: =IFERROR(VLOOKUP(D7,'Client ID Records_v2'!D:E, 2, FALSE), "") -> CL-2021-035 | H7: =IFERROR(VLOOKUP(G7,'Client ID Records_v2'!E:F, 2, FALSE), "") -> College of Arts and Sciences (CAS) Buidling, University of the Philippines Visayas, Miagao, Iloilo 5023 | I7: =IFERROR(VLOOKUP(D7,'Project Records_v2'!E:F, 2, FALSE), "") -> P-2021-014 | J7: =IFERROR(VLOOKUP(I7,'Project Records_v2'!F:G, 2, FALSE), "") -> Pre-commercialization of Microwave Extracted Pectin from Waste Calamansi Peels | K7: Retail Sales | L7: Type II Water | M7: Cancelled | N7: N/A | Q7: combined with CS-2021-10-11
A8: 2021 | B8: 44413 | C8: CS-2021-08-007 | D8: Concepcion Ponce | F8: CANCELLED | G8: =IFERROR(VLOOKUP(D8,'Client ID Records_v2'!D:E, 2, FALSE), "") -> CL-2021-035 | H8: =IFERROR(VLOOKUP(G8,'Client ID Records_v2'!E:F, 2, FALSE), "") -> College of Arts and Sciences (CAS) Buidling, University of the Philippines Visayas, Miagao, Iloilo 5023 | I8: =IFERROR(VLOOKUP(D8,'Project Records_v2'!E:F, 2, FALSE), "") -> P-2021-014 | J8: =IFERROR(VLOOKUP(I8,'Project Records_v2'!F:G, 2, FALSE), "") -> Pre-commercialization of Microwave Extracted Pectin from Waste Calamansi Peels | K8: Retail Sales | L8: Type II Water | M8: Cancelled | N8: N/A | Q8: combined with CS-2021-10-12
A9: 2021 | B9: 44420 | C9: CS-2021-08-008 | D9: Concepcion Ponce | F9: CANCELLED | G9: =IFERROR(VLOOKUP(D9,'Client ID Records_v2'!D:E, 2, FALSE), "") -> CL-2021-035 | H9: =IFERROR(VLOOKUP(G9,'Client ID Records_v2'!E:F, 2, FALSE), "") -> College of Arts and Sciences (CAS) Buidling, University of the Philippines Visayas, Miagao, Iloilo 5023 | I9: =IFERROR(VLOOKUP(D9,'Project Records_v2'!E:F, 2, FALSE), "") -> P-2021-014 | J9: =IFERROR(VLOOKUP(I9,'Project Records_v2'!F:G, 2, FALSE), "") -> Pre-commercialization of Microwave Extracted Pectin from Waste Calamansi Peels | K9: Retail Sales | L9: Type II Water | M9: Cancelled | N9: N/A | Q9: combined with CS-2021-10-13
A10: 2021 | B10: 44424 | C10: CS-2021-08-009 | D10: Concepcion Ponce | F10: CANCELLED | G10: =IFERROR(VLOOKUP(D10,'Client ID Records_v2'!D:E, 2, FALSE), "") -> CL-2021-035 | H10: =IFERROR(VLOOKUP(G10,'Client ID Records_v2'!E:F, 2, FALSE), "") -> College of Arts and Sciences (CAS) Buidling, University of the Philippines Visayas, Miagao, Iloilo 5023 | I10: =IFERROR(VLOOKUP(D10,'Project Records_v2'!E:F, 2, FALSE), "") -> P-2021-014 | J10: =IFERROR(VLOOKUP(I10,'Project Records_v2'!F:G, 2, FALSE), "") -> Pre-commercialization of Microwave Extracted Pectin from Waste Calamansi Peels | K10: Retail Sales | L10: Type II Water | M10: Cancelled | N10: N/A | Q10: combined with CS-2021-10-14
A11: 2021 | B11: 44441 | C11: CS-2021-09-010 | D11: Dominique P. Mediodia | E11: 24210.2 | F11: CANCELLED | G11: =IFERROR(VLOOKUP(D11,'Client ID Records_v2'!D:E, 2, FALSE), "") -> CL-2020-019 | H11: =IFERROR(VLOOKUP(G11,'Client ID Records_v2'!E:F, 2, FALSE), "") -> Institute of Marine Fisheries and Oceanology, College of Fisheries and Ocean Sciences, University of the Philippines Visayas | I11: =IFERROR(VLOOKUP(D11,'Project Records_v2'!E:F, 2, FALSE), "") -> P-2020-008 | J11: =IFERROR(VLOOKUP(I11,'Project Records_v2'!F:G, 2, FALSE), "") -> Marine Fisheries Assessment of Panay: Building Local Fisheries Information through Research Capability Enhancement on Higher Education Insitutions | K11: Equipment Use | L11: N/A | M11: Laboratory Service | N11: N/A
A12: 2021 | B12: 44484 | C12: CS-2021-10-011 | D12: Dominique P. Mediodia | E12: 8800 | F12: PAID | G12: =IFERROR(VLOOKUP(D12,'Client ID Records_v2'!D:E, 2, FALSE), "") -> CL-2020-019 | H12: =IFERROR(VLOOKUP(G12,'Client ID Records_v2'!E:F, 2, FALSE), "") -> Institute of Marine Fisheries and Oceanology, College of Fisheries and Ocean Sciences, University of the Philippines Visayas | I12: =IFERROR(VLOOKUP(D12,'Project Records_v2'!E:F, 2, FALSE), "") -> P-2020-008 | J12: =IFERROR(VLOOKUP(I12,'Project Records_v2'!F:G, 2, FALSE), "") -> Marine Fisheries Assessment of Panay: Building Local Fisheries Information through Research Capability Enhancement on Higher Education Insitutions | K12: Equipment Use | L12: N/A | M12: Laboratory Service | N12: TF-2021-12-10531 | O12: 508210 | P12: 44553
A13: 2022 | B13: 44673 | C13: CS-2022-01-001 | D13: Kingsley John de los Santos | E13: 1320 | F13: PAID | G13: =IFERROR(VLOOKUP(D13,'Client ID Records_v2'!D:E, 2, FALSE), "") -> CL-2022-044 | H13: =IFERROR(VLOOKUP(G13,'Client ID Records_v2'!E:F, 2, FALSE), "") -> Division of Biological Sciences, College of Arts and Sciences, University of the Philippines Visayas, Miagao, Iloilo | I13: =IFERROR(VLOOKUP(D13,'Project Records_v2'!E:F, 2, FALSE), "") -> P-2022-022 | J13: =IFERROR(VLOOKUP(I13,'Project Records_v2'!F:G, 2, FALSE), "") -> Assessment of Anthropogenic Marine Debris and Mangrove Forest Health in Iloilo Strait, Western Visayas, Philippines | K13: Retail Sales | L13: Liquid Nitrogen (LN) | M13: Laboratory Service | N13: Bank Deposit | O13: 512050 | P13: 44673
A14: 2022 | B14: 44673 | C14: CS-2022-01-002 | D14: Karl Angelo P. Tenizo | E14: 1205945 | F14: PAID | G14: =IFERROR(VLOOKUP(D14,'Client ID Records_v2'!D:E, 2, FALSE), "") -> CL-2020-015 | H14: =IFERROR(VLOOKUP(G14,'Client ID Records_v2'!E:F, 2, FALSE), "") -> Institute of Aquaculture, College of Fisheries and Ocean Sciences, University of the Philippines Visayas, Miagao, 5023, Iloilo | I14: =IFERROR(VLOOKUP(D14,'Project Records_v2'!E:F, 2, FALSE), "") -> P-2020-005 | J14: =IFERROR(VLOOKUP(I14,'Project Records_v2'!F:G, 2, FALSE), "") -> Transcriptome and metabolome profiling of seaweeds to elucidate "ice-ice" disease and epiphyte infestation mechanisms | K14: Laboratory Service | L14: Extraction to Transcriptomics | M14: R&D | N14: TF-2022-05-3955
A15: 2022 | B15: 44697 | C15: CS-2022-05-003 | D15: Rema C. Sibonga | E15: 3033.36 | F15: PAID | G15: =IFERROR(VLOOKUP(D15,'Client ID Records_v2'!D:E, 2, FALSE), "") -> CL-2020-010 | H15: =IFERROR(VLOOKUP(G15,'Client ID Records_v2'!E:F, 2, FALSE), "") -> Institute of Aquaculture, College of Fisheries and Ocean Sciences, University of the Philippines Visayas, Miagao, 5023, Iloilo | I15: =IFERROR(VLOOKUP(D15,'Project Records_v2'!E:F, 2, FALSE), "") -> P-2020-001 | J15: =IFERROR(VLOOKUP(I15,'Project Records_v2'!F:G, 2, FALSE), "") -> Global Seaweed STAR Project | K15: Equipment Use | L15: N/A | M15: Laboratory Service | N15: Bank Deposit | O15: 514345 | P15: 44722
A16: 2022 | B16: 44701 | C16: CS-2022-05-004 | D16: Kingsley John de los Santos | E16: 1320 | F16: PAID | G16: =IFERROR(VLOOKUP(D16,'Client ID Records_v2'!D:E, 2, FALSE), "") -> CL-2022-044 | H16: =IFERROR(VLOOKUP(G16,'Client ID Records_v2'!E:F, 2, FALSE), "") -> Division of Biological Sciences, College of Arts and Sciences, University of the Philippines Visayas, Miagao, Iloilo | I16: =IFERROR(VLOOKUP(D16,'Project Records_v2'!E:F, 2, FALSE), "") -> P-2022-022 | J16: =IFERROR(VLOOKUP(I16,'Project Records_v2'!F:G, 2, FALSE), "") -> Assessment of Anthropogenic Marine Debris and Mangrove Forest Health in Iloilo Strait, Western Visayas, Philippines | K16: Retail Sales | L16: Liquid Nitrogen (LN) | M16: Laboratory Service | N16: Bank Deposit | O16: 512685 | P16: 44701
A17: 2022 | B17: 44733 | C17: CS-2022-06-005 | D17: Arlene L . Avillanosa | E17: 193203.97 | F17: PAID | G17: =IFERROR(VLOOKUP(D17,'Client ID Records_v2'!D:E, 2, FALSE), "") -> CL-2021-031 | H17: =IFERROR(VLOOKUP(G17,'Client ID Records_v2'!E:F, 2, FALSE), "") -> Room 9, Second Floor (ABBA R&D Center), College of Fisheries and Aquatic Science (CFAS), WPU-Puerto Princesa Campus, Sta. Monica, Puerto Princesa City | I17: =IFERROR(VLOOKUP(D17,'Project Records_v2'!E:F, 2, FALSE), "") -> P-2021-013 | J17: =IFERROR(VLOOKUP(I17,'Project Records_v2'!F:G, 2, FALSE), "") -> Genetic Characterization of Macrobrachium populations in the Philippines for broodstock development and seed production | K17: Laboratory Service | L17: Extraction to Amplicon Sequencing | M17: R&D | N17: Bank Deposit | O17: 0517969 | P17: 44792
A18: 2022 | B18: 44551 | C18: CS-2021-12-012 / CS-2022-07-006 | D18: Angel Queenee D. Dequito | E18: 76402.48 | G18: =IFERROR(VLOOKUP(D18,'Client ID Records_v2'!D:E, 2, FALSE), "") -> CL-2020-013 | H18: =IFERROR(VLOOKUP(G18,'Client ID Records_v2'!E:F, 2, FALSE), "") -> Institute of Aquaculture, College of Fisheries and Ocean Sciences, University of the Philippines Visayas, Miagao, 5023, Iloilo | I18: =IFERROR(VLOOKUP(D18,'Project Records_v2'!E:F, 2, FALSE), "") -> P-2020-003 | J18: =IFERROR(VLOOKUP(I18,'Project Records_v2'!F:G, 2, FALSE), "") -> Transcriptome and Gut Metagenome Profile of Penaeus vannamei Exposed to Fluctuating Environmental Temperatures | K18: Laboratory Service | L18: Extraction to qPCR | M18: Cancelled | N18: Bank Deposit
A19: 2022 | B19: 44803 | C19: CS-2022-08-007 | D19: Beverly T. Jaspe | E19: 123497 | F19: PAID | G19: =IFERROR(VLOOKUP(D19,'Client ID Records_v2'!D:E, 2, FALSE), "") -> CL-2022-051 | H19: =IFERROR(VLOOKUP(G19,'Client ID Records_v2'!E:F, 2, FALSE), "") -> Fisheries and Marine Sciences Department, Aklan State University - New Washington Campus | I19: =IFERROR(VLOOKUP(D19,'Project Records_v2'!E:F, 2, FALSE), "") -> P-2022-027 | J19: =IFERROR(VLOOKUP(I19,'Project Records_v2'!F:G, 2, FALSE), "") -> Genomic variations among different (meta) populations of oriental angelwing clam (Pholas orientalis) in the Western Visayas, Philippines: basis for conservation breeding program | K19: Laboratory Service | L19: Extraction to Bioinformatics Analysis | M19: R&D | N19: Thru Bank Deposit | O19: 0520397 | P19: 44816
A20: 2022 | B20: 44816 | C20: CS-2022-09-009 | D20: Viva Princess A. Basa | E20: 58367.86 | F20: PAID | G20: =IFERROR(VLOOKUP(D20,'Client ID Records_v2'!D:E, 2, FALSE), "") -> CL-2022-056 | H20: =IFERROR(VLOOKUP(G20,'Client ID Records_v2'!E:F, 2, FALSE), "") -> Research and Development Extension, Mindoro State University | I20: PGCV-BT-2022-001 | J20: =IFERROR(VLOOKUP(I20,'Project Records_v2'!F:G, 2, FALSE), "") | K20: Training | L20: Bioinformatics Analysis | M20: Laboratory Service | N20: Bank Deposit | O20: 0520474 | P20: 44817 | Q20: Other Payee: MS. KATHERINE P. SANCHEZ MS. JERMAINE RITZCHELLE D. MARQUEZ MS. ELSIE Y. GUIBONE
A21: 2022 | B21: 44881 | C21: CS-2022-11-010 | D21: Eric Zeus C. Rizo | E21: 569499.72 | F21: PAID | G21: =IFERROR(VLOOKUP(D21,'Client ID Records_v2'!D:E, 2, FALSE), "") -> CL-2022-038 | H21: =IFERROR(VLOOKUP(G21,'Client ID Records_v2'!E:F, 2, FALSE), "") -> Division of Biological Sciences, College of Arts and Sciences, University of the Philippines Visayas, Miagao, Iloilo | I21: =IFERROR(VLOOKUP(D21,'Project Records_v2'!E:F, 2, FALSE), "") -> P-2022-017 | J21: =IFERROR(VLOOKUP(I21,'Project Records_v2'!F:G, 2, FALSE), "") -> Development of a Water Quality Biological Monitoring Protocol using Genetic, Phylogenetic and Functional Diversity on Freshwater Zooplankton Communitites in Inland Waters of Panay Island, Philippines | K21: Laboratory Service | L21: Extraction to Sequencing | M21: R&D | N21: 2022-11-11214 | O21: Check No: 63422 | P21: 44917
A22: 2022 | B22: 44901 | C22: CS-2022-12-011 | D22: Rhudith Cabulong | E22: 126740.68 | F22: CANCELLED | G22: =IFERROR(VLOOKUP(D22,'Client ID Records_v2'!D:E, 2, FALSE), "") -> CL-2022-055 | H22: =IFERROR(VLOOKUP(G22,'Client ID Records_v2'!E:F, 2, FALSE), "") -> Microbiology Laboratory, College of Arts and Sciences, University of the Philippines Visayas, 5023 Miagao, Iloilo | I22: =IFERROR(VLOOKUP(D22,'Project Records_v2'!E:F, 2, FALSE), "") -> P-2022-032 | J22: =IFERROR(VLOOKUP(I22,'Project Records_v2'!F:G, 2, FALSE), "") -> Diversity and screening of culturable cellulytic microorganisms from mangrove forests, natural parks, paddy field, and sugar plantation in Panay Island, Philippines | K22: Laboratory Service | L22: Extraction to Sequencing | M22: Cancelled | N22: N/A | O22: N/A | P22: N/A | Q22: PLEASE DISREGARD, updated and final charge slip is CS-2022-12-012
A23: 2022 | B23: 44904 | C23: CS-2022-12-012 | D23: Rhudith Cabulong | E23: 140870.31 | F23: PAID | G23: =IFERROR(VLOOKUP(D23,'Client ID Records_v2'!D:E, 2, FALSE), "") -> CL-2022-055 | H23: =IFERROR(VLOOKUP(G23,'Client ID Records_v2'!E:F, 2, FALSE), "") -> Microbiology Laboratory, College of Arts and Sciences, University of the Philippines Visayas, 5023 Miagao, Iloilo | I23: =IFERROR(VLOOKUP(D23,'Project Records_v2'!E:F, 2, FALSE), "") -> P-2022-032 | J23: =IFERROR(VLOOKUP(I23,'Project Records_v2'!F:G, 2, FALSE), "") -> Diversity and screening of culturable cellulytic microorganisms from mangrove forests, natural parks, paddy field, and sugar plantation in Panay Island, Philippines | K23: Laboratory Service | L23: Extraction to Sequencing | M23: R&D | N23: 2022-12-12406 | O23: Check No. 122888 | P23: 44915
A24: 2022 | B24: 44909 | C24: CS-2023-12-013 | D24: Eric Zeus C. Rizo | E24: 43309.98 | F24: PAID | G24: =IFERROR(VLOOKUP(D24,'Client ID Records_v2'!D:E, 2, FALSE), "") -> CL-2022-038 | H24: =IFERROR(VLOOKUP(G24,'Client ID Records_v2'!E:F, 2, FALSE), "") -> Division of Biological Sciences, College of Arts and Sciences, University of the Philippines Visayas, Miagao, Iloilo | I24: =IFERROR(VLOOKUP(D24,'Project Records_v2'!E:F, 2, FALSE), "") -> P-2022-017 | J24: =IFERROR(VLOOKUP(I24,'Project Records_v2'!F:G, 2, FALSE), "") -> Development of a Water Quality Biological Monitoring Protocol using Genetic, Phylogenetic and Functional Diversity on Freshwater Zooplankton Communitites in Inland Waters of Panay Island, Philippines | K24: Laboratory Service | L24: Extraction to Sequencing | M24: R&D | N24: 2022-12-12069 | O24: Check No: 63513 | P24: 44923
A25: 2022 | B25: 44915 | C25: CS-2023-12-014 | D25: Alain C. Juayang | F25: CANCELLED | G25: =IFERROR(VLOOKUP(D25,'Client ID Records_v2'!D:E, 2, FALSE), "") -> CL-2021-025 | H25: =IFERROR(VLOOKUP(G25,'Client ID Records_v2'!E:F, 2, FALSE), "") -> Molecular Laboratory, Corazon L. Montelibano Memorial Regional Hospital, Burgos-Lacson St., Bacolod City | I25: T-2023-001 | J25: =IFERROR(VLOOKUP(I25,'Project Records_v2'!F:G, 2, FALSE), "") | K25: Training | L25: WGS | M25: Cancelled | Q25: PLEASE DISREGARD, updated and final charge slip is CS-2023-01-002
A26: 2023 | B26: 44946 | C26: CS-2023-01-001 | D26: Karl Angelo P. Tenizo | E26: 420582.18 | F26: CANCELLED | G26: =IFERROR(VLOOKUP(D26,'Client ID Records_v2'!D:E, 2, FALSE), "") -> CL-2020-015 | H26: =IFERROR(VLOOKUP(G26,'Client ID Records_v2'!E:F, 2, FALSE), "") -> Institute of Aquaculture, College of Fisheries and Ocean Sciences, University of the Philippines Visayas, Miagao, 5023, Iloilo | I26: =IFERROR(VLOOKUP(D26,'Project Records_v2'!E:F, 2, FALSE), "") -> P-2020-005 | J26: =IFERROR(VLOOKUP(I26,'Project Records_v2'!F:G, 2, FALSE), "") -> Transcriptome and metabolome profiling of seaweeds to elucidate "ice-ice" disease and epiphyte infestation mechanisms | K26: Laboratory Service | L26: Extraction to Transcriptomics | M26: Cancelled
A27: 2023 | B27: 44959 | C27: CS-2023-01-002 | D27: Alain C. Juayang | E27: 173723.9 | F27: PAID | G27: =IFERROR(VLOOKUP(D27,'Client ID Records_v2'!D:E, 2, FALSE), "") -> CL-2021-025 | H27: =IFERROR(VLOOKUP(G27,'Client ID Records_v2'!E:F, 2, FALSE), "") -> Molecular Laboratory, Corazon L. Montelibano Memorial Regional Hospital, Burgos-Lacson St., Bacolod City | I27: T-2023-001 | J27: =IFERROR(VLOOKUP(I27,'Project Records_v2'!F:G, 2, FALSE), "") | K27: Training | L27: WGS | M27: Laboratory Service | N27: Thru Bank Deposit | O27: 537350 | P27: 44986
A28: 2023 | B28: 44964 | C28: CS-2023-02-003 | D28: Dr. Sitti Zayda Halun | E28: 332625.61 | F28: PAID | G28: =IFERROR(VLOOKUP(D28,'Client ID Records_v2'!D:E, 2, FALSE), "") -> CL-2023-071 | H28: =IFERROR(VLOOKUP(G28,'Client ID Records_v2'!E:F, 2, FALSE), "") -> Seaweed Research and Development Center, Mindanao State University in Tawi-Tawi Sanga-Sanga, Bongao, Tawi-Tawi, Philippines | I28: =IFERROR(VLOOKUP(D28,'Project Records_v2'!E:F, 2, FALSE), "") -> P-2023-037 | J28: =IFERROR(VLOOKUP(I28,'Project Records_v2'!F:G, 2, FALSE), "") -> Amplicon Sequencing of Seaweed | K28: Laboratory Service | L28: Extraction to Amplicon Sequencing | M28: R&D | N28: Thru Bank Deposit | O28: 538133 | P28: 45006
A29: 2023 | B29: 44987 | C29: CS-2023-03-004 | D29: June Rey A. Montajes | E29: 116320.49 | F29: PAID | G29: =IFERROR(VLOOKUP(D29,'Client ID Records_v2'!D:E, 2, FALSE), "") -> CL-2023-073 | H29: =IFERROR(VLOOKUP(G29,'Client ID Records_v2'!E:F, 2, FALSE), "") -> ODREIC, 2/F KOICA (New Administration) Building, Maharlika Highway, Tanghas, Tolosa, Leyte | I29: T-2023-002 | J29: =IFERROR(VLOOKUP(I29,'Project Records_v2'!F:G, 2, FALSE), "") | K29: Training | L29: 16s Metagenomics | M29: Laboratory Service | N29: Cheque to Cash Office | O29: 538943 | P29: 45033
A30: 2023 | B30: 44987 | C30: CS-2023-03-004 | D30: Shereen A. Merro | E30: 87039.49 | F30: PAID | G30: =IFERROR(VLOOKUP(D30,'Client ID Records_v2'!D:E, 2, FALSE), "") -> CL-2023-074 | H30: =IFERROR(VLOOKUP(G30,'Client ID Records_v2'!E:F, 2, FALSE), "") -> ODAA, G/F KOICA (New Administration) Building, Maharlika Highway, Tanghas, Tolosa, Leyte | I30: T-2023-003 | J30: =IFERROR(VLOOKUP(I30,'Project Records_v2'!F:G, 2, FALSE), "") | K30: Training | L30: 16s Metagenomics and Amplicon Sequencing | M30: Laboratory Service | N30: Cheque to Cash Office | O30: 538942 | P30: 45033
A31: 2023 | B31: 45035 | C31: CS-2023-03-005 | D31: Pauline Anne Lamela | E31: 6944.08 | F31: CANCELLED | G31: =IFERROR(VLOOKUP(D31,'Client ID Records_v2'!D:E, 2, FALSE), "") -> CL-2022-066 | H31: =IFERROR(VLOOKUP(G31,'Client ID Records_v2'!E:F, 2, FALSE), "") -> College of Arts and Sciences Division of Biological Sciences, University of the Philippines Visayas Miagao, 5023, Iloilo | I31: =IFERROR(VLOOKUP(D31,'Project Records_v2'!E:F, 2, FALSE), "") -> P-2022-035 | J31: =IFERROR(VLOOKUP(I31,'Project Records_v2'!F:G, 2, FALSE), "") -> Isolation, Characterization, And Identification of Plastic-Degrading Bacteria From Bago City Landfill, Negros Occidental, Philippines | K31: Equipment Use | L31: N/A | M31: Cancelled | Q31: PLEASE DISREGARD, updated and final charge slip is CS-2023-05-006
A32: 2023 | B32: 45077 | C32: CS-2023-04-006 | D32: Pauline Anne Lamela | E32: 12834.8 | F32: PAID | G32: =IFERROR(VLOOKUP(D32,'Client ID Records_v2'!D:E, 2, FALSE), "") -> CL-2022-066 | H32: =IFERROR(VLOOKUP(G32,'Client ID Records_v2'!E:F, 2, FALSE), "") -> College of Arts and Sciences Division of Biological Sciences, University of the Philippines Visayas Miagao, 5023, Iloilo | I32: =IFERROR(VLOOKUP(D32,'Project Records_v2'!E:F, 2, FALSE), "") -> P-2022-035 | J32: =IFERROR(VLOOKUP(I32,'Project Records_v2'!F:G, 2, FALSE), "") -> Isolation, Characterization, And Identification of Plastic-Degrading Bacteria From Bago City Landfill, Negros Occidental, Philippines | K32: Equipment Use | L32: N/A | M32: Laboratory Service | N32: Thru Bank Deposit | O32: 544663 | P32: 45111
A33: 2023 | B33: 45084 | C33: CS-2023-05-007 | D33: Trisha Marie Santos | E33: 3080 | F33: PAID | G33: =IFERROR(VLOOKUP(D33,'Client ID Records_v2'!D:E, 2, FALSE), "") -> CL-2023-083 | H33: =IFERROR(VLOOKUP(G33,'Client ID Records_v2'!E:F, 2, FALSE), "") -> Division of Biological Sciences, College of Arts and Sciences, UP Visayas Miagao Iloilo | I33: =IFERROR(VLOOKUP(D33,'Project Records_v2'!E:F, 2, FALSE), "") -> P-2023-044 | J33: =IFERROR(VLOOKUP(I33,'Project Records_v2'!F:G, 2, FALSE), "") -> Prebiotic potential of Beta-glucan extracted from macrofungu found in Miagao, Iloilo | K33: Equipment Use | L33: N/A | M33: Laboratory Service | N33: Thru Bank Deposit | O33: 542787 | P33: 45098
A34: 2023 | B34: 45084 | C34: CS-2023-06-008 | D34: Beatrice L. Anacita | E34: 4004 | F34: PAID | G34: =IFERROR(VLOOKUP(D34,'Client ID Records_v2'!D:E, 2, FALSE), "") -> CL-2023-081 | H34: =IFERROR(VLOOKUP(G34,'Client ID Records_v2'!E:F, 2, FALSE), "") -> College of Arts and Sciences Division of Biological Sciences, University of the Philippines Visayas Miagao, 5023, Iloilo | I34: =IFERROR(VLOOKUP(D34,'Project Records_v2'!E:F, 2, FALSE), "") -> P-2023-042 | J34: =IFERROR(VLOOKUP(I34,'Project Records_v2'!F:G, 2, FALSE), "") -> Bacterial Biofilm Formation and Inhibition Potential of Wild Macrofungi from Miagao, Iloilo | K34: Equipment Use | L34: N/A | M34: Laboratory Service | N34: Thru Bank Deposit | O34: 542525 | P34: 45093
A35: 2023 | B35: 45084 | C35: CS-2023-06-009 | D35: Kyla Julienne P. Talaman | E35: 4004 | F35: PAID | G35: =IFERROR(VLOOKUP(D35,'Client ID Records_v2'!D:E, 2, FALSE), "") -> CL-2023-082 | H35: =IFERROR(VLOOKUP(G35,'Client ID Records_v2'!E:F, 2, FALSE), "") -> College of Arts and Sciences Division of Biological Sciences, University of the Philippines Visayas Miagao, 5023, Iloilo | I35: =IFERROR(VLOOKUP(D35,'Project Records_v2'!E:F, 2, FALSE), "") -> P-2023-043 | J35: =IFERROR(VLOOKUP(I35,'Project Records_v2'!F:G, 2, FALSE), "") -> Prebiotic potential of Beta-glucan extracted from macrofungu found in Miagao, Iloilo | K35: Equipment Use | L35: N/A | M35: Laboratory Service | N35: Thru Bank Deposit | O35: 542494 | P35: 45092
A36: 2023 | B36: 45086 | C36: CS-2023-06-010 | D36: Carlo S. Gregorio | E36: 2728 | F36: PAID | G36: =IFERROR(VLOOKUP(D36,'Client ID Records_v2'!D:E, 2, FALSE), "") -> CL-2023-086 | H36: =IFERROR(VLOOKUP(G36,'Client ID Records_v2'!E:F, 2, FALSE), "") -> Institute of Marine Fisheries and Oceanology, College of Fisheries and Ocean Sciences, University of the Philippines Visayas | I36: =IFERROR(VLOOKUP(D36,'Project Records_v2'!E:F, 2, FALSE), "") -> P-2023-047 | J36: =IFERROR(VLOOKUP(I36,'Project Records_v2'!F:G, 2, FALSE), "") -> Detection of Vibrio parahaemolyticus and Vibrio cholerae in Oyster using Quantitative Real-Time Polymerase Chain Reaction (qPCR) Characterization Of Picophytoplankton Abundance And Distribution In Relation To Varying Environmental Conditions In The Bay Zone Of The Batan Bay Estuary | K36: Retail Sales | L36: LN | M36: Laboratory Service | N36: Thru Bank Deposit | O36: 545015 | P36: 45118
A37: 2023 | B37: 45086 | C37: CS-2023-06-011 | D37: Elize Margareth C. Sibulan | E37: 2728 | F37: PAID | G37: =IFERROR(VLOOKUP(D37,'Client ID Records_v2'!D:E, 2, FALSE), "") -> CL-2023-087 | H37: =IFERROR(VLOOKUP(G37,'Client ID Records_v2'!E:F, 2, FALSE), "") -> Institute of Marine Fisheries and Oceanology, College of Fisheries and Ocean Sciences, University of the Philippines Visayas | I37: =IFERROR(VLOOKUP(D37,'Project Records_v2'!E:F, 2, FALSE), "") -> P-2023-047 | J37: =IFERROR(VLOOKUP(I37,'Project Records_v2'!F:G, 2, FALSE), "") -> Detection of Vibrio parahaemolyticus and Vibrio cholerae in Oyster using Quantitative Real-Time Polymerase Chain Reaction (qPCR) Characterization Of Picophytoplankton Abundance And Distribution In Relation To Varying Environmental Conditions In The Bay Zone Of The Batan Bay Estuary | K37: Retail Sales | L37: LN | M37: Laboratory Service | N37: Thru Bank Deposit | O37: 545017 | P37: 45118
A38: 2023 | B38: 45086 | C38: CS-2023-06-012 | D38: Abigail F. Padua | E38: 3273.6 | F38: PAID | G38: =IFERROR(VLOOKUP(D38,'Client ID Records_v2'!D:E, 2, FALSE), "") -> CL-2023-088 | H38: =IFERROR(VLOOKUP(G38,'Client ID Records_v2'!E:F, 2, FALSE), "") -> WVSU Biotechnology & Biomedical Research Labroatory | I38: =IFERROR(VLOOKUP(D38,'Project Records_v2'!E:F, 2, FALSE), "") -> P-2023-049 | J38: =IFERROR(VLOOKUP(I38,'Project Records_v2'!F:G, 2, FALSE), "") -> The effect of fermented silage on sperm quality of mixed-breed anglo nubian goats in Romblon | K38: Retail Sales | L38: LN | M38: Laboratory Service | N38: Thru Bank Deposit | O38: 545023 | P38: 45118
A39: 2023 | B39: 45103 | C39: CS-2023-06-013 | D39: Carlo S. Gregorio | E39: 2182.4 | F39: PAID | G39: =IFERROR(VLOOKUP(D39,'Client ID Records_v2'!D:E, 2, FALSE), "") -> CL-2023-086 | H39: =IFERROR(VLOOKUP(G39,'Client ID Records_v2'!E:F, 2, FALSE), "") -> Institute of Marine Fisheries and Oceanology, College of Fisheries and Ocean Sciences, University of the Philippines Visayas | I39: =IFERROR(VLOOKUP(D39,'Project Records_v2'!E:F, 2, FALSE), "") -> P-2023-047 | J39: =IFERROR(VLOOKUP(I39,'Project Records_v2'!F:G, 2, FALSE), "") -> Detection of Vibrio parahaemolyticus and Vibrio cholerae in Oyster using Quantitative Real-Time Polymerase Chain Reaction (qPCR) Characterization Of Picophytoplankton Abundance And Distribution In Relation To Varying Environmental Conditions In The Bay Zone Of The Batan Bay Estuary | K39: Retail Sales | L39: LN | M39: Laboratory Service | N39: Thru Bank Deposit | O39: 545016 | P39: 45118
A40: 2023 | B40: 45146 | C40: CS-2023-06-014 | D40: Krshna Mahakaola A. Dueñas | E40: 1636.8 | F40: PAID | G40: =IFERROR(VLOOKUP(D40,'Client ID Records_v2'!D:E, 2, FALSE), "") -> CL-2023-100 | H40: =IFERROR(VLOOKUP(G40,'Client ID Records_v2'!E:F, 2, FALSE), "") -> West Visayas State University, College of Arts and Sciences - Biology Department | I40: =IFERROR(VLOOKUP(D40,'Project Records_v2'!E:F, 2, FALSE), "") -> P-2023-054 | J40: =IFERROR(VLOOKUP(I40,'Project Records_v2'!F:G, 2, FALSE), "") -> Effects of Crown-of-Thorns (Acanthaster planci) Starfish as a Growth Enhacer in White Mice (Mus musculus) | K40: Retail Sales | L40: LN | M40: Laboratory Service | N40: Thru Bank Deposit | O40: 549227 | P40: 45149
A41: 2023 | B41: 45156 | C41: CS-2023-08-015 | D41: Joseph Faisan Jr. | E41: 21520 | F41: PAID | G41: =IFERROR(VLOOKUP(D41,'Client ID Records_v2'!D:E, 2, FALSE), "") -> CL-2023-112 | H41: =IFERROR(VLOOKUP(G41,'Client ID Records_v2'!E:F, 2, FALSE), "") -> SEAFDEC/AQD, Barangay Buyu-an, Tigbauan, Iloilo | I41: =IFERROR(VLOOKUP(D41,'Project Records_v2'!E:F, 2, FALSE), "") -> P-2023-056 | J41: =IFERROR(VLOOKUP(I41,'Project Records_v2'!F:G, 2, FALSE), "") -> Fish Species ID | K41: Laboratory Service | L41: Extraction to Amplicon Sequencing | M41: Laboratory Service | N41: Thru Bank Deposit | O41: 552424 | P41: 45177
A42: 2023 | B42: 45239 | C42: CS-2023-08-016 | D42: Mark S. Calabon | E42: 199974.72 | F42: PAID | G42: =IFERROR(VLOOKUP(D42,'Client ID Records_v2'!D:E, 2, FALSE), "") -> CL-2023-096 | H42: =IFERROR(VLOOKUP(G42,'Client ID Records_v2'!E:F, 2, FALSE), "") -> Division of Biological Sciences, College of Arts and Sciences, UP Visayas Miagao Iloilo | I42: =IFERROR(VLOOKUP(D42,'Project Records_v2'!E:F, 2, FALSE), "") -> P-2023-052 | J42: =IFERROR(VLOOKUP(I42,'Project Records_v2'!F:G, 2, FALSE), "") -> Unraveling the Hidden Diversity of Aquatic Fungi from Panay Island, Philippines Project | K42: Laboratory Service | L42: Extraction to Amplicon Sequencing | M42: R&D | N42: TF-2023-12-13391 | O42: N/A | P42: 45274
A43: 2023 | B43: 45245 | C43: CS-2023-09-017 | D43: April Joy Monsale | E43: 11693.352 | F43: PAID | G43: =IFERROR(VLOOKUP(D43,'Client ID Records_v2'!D:E, 2, FALSE), "") | H43: =IFERROR(VLOOKUP(G43,'Client ID Records_v2'!E:F, 2, FALSE), "") | I43: =IFERROR(VLOOKUP(D43,'Project Records_v2'!E:F, 2, FALSE), "") | J43: =IFERROR(VLOOKUP(I43,'Project Records_v2'!F:G, 2, FALSE), "") | K43: Training | L43: Bioinformatics Analysis | M43: Laboratory Service | N43: Thru Bank Deposit | O43: 556948 | P43: 45246
A44: 2023 | B44: 45245 | C44: CS-2023-10-018 | D44: Mary Grace Gonzales | E44: 11693.352 | F44: PAID | G44: =IFERROR(VLOOKUP(D44,'Client ID Records_v2'!D:E, 2, FALSE), "") | H44: =IFERROR(VLOOKUP(G44,'Client ID Records_v2'!E:F, 2, FALSE), "") | I44: =IFERROR(VLOOKUP(D44,'Project Records_v2'!E:F, 2, FALSE), "") | J44: =IFERROR(VLOOKUP(I44,'Project Records_v2'!F:G, 2, FALSE), "") | K44: Training | L44: Bioinformatics Analysis | M44: Laboratory Service | N44: Thru Bank Deposit | O44: 556949 | P44: 45246
A45: 2023 | B45: 45245 | C45: CS-2023-10-019 | D45: Kenneth Wilson A. Si | E45: 11693.352 | F45: PAID | G45: =IFERROR(VLOOKUP(D45,'Client ID Records_v2'!D:E, 2, FALSE), "") | H45: =IFERROR(VLOOKUP(G45,'Client ID Records_v2'!E:F, 2, FALSE), "") | I45: =IFERROR(VLOOKUP(D45,'Project Records_v2'!E:F, 2, FALSE), "") | J45: =IFERROR(VLOOKUP(I45,'Project Records_v2'!F:G, 2, FALSE), "") | K45: Training | L45: Bioinformatics Analysis | M45: Laboratory Service | N45: Thru Bank Deposit | O45: 556952 | P45: 45246
A46: 2023 | B46: 45245 | C46: CS-2023-10-020 | D46: Jay Nolan J. Alonsabe | E46: 11693.352 | F46: PAID | G46: =IFERROR(VLOOKUP(D46,'Client ID Records_v2'!D:E, 2, FALSE), "") | H46: =IFERROR(VLOOKUP(G46,'Client ID Records_v2'!E:F, 2, FALSE), "") | I46: =IFERROR(VLOOKUP(D46,'Project Records_v2'!E:F, 2, FALSE), "") | J46: =IFERROR(VLOOKUP(I46,'Project Records_v2'!F:G, 2, FALSE), "") | K46: Training | L46: Bioinformatics Analysis | M46: Laboratory Service | N46: Thru Bank Deposit | O46: 556951 | P46: 45246
A47: 2023 | B47: 45245 | C47: CS-2023-10-021 | D47: Kenneth John C. Chiquito | E47: 11693.352 | F47: PAID | G47: =IFERROR(VLOOKUP(D47,'Client ID Records_v2'!D:E, 2, FALSE), "") | H47: =IFERROR(VLOOKUP(G47,'Client ID Records_v2'!E:F, 2, FALSE), "") | I47: =IFERROR(VLOOKUP(D47,'Project Records_v2'!E:F, 2, FALSE), "") | J47: =IFERROR(VLOOKUP(I47,'Project Records_v2'!F:G, 2, FALSE), "") | K47: Training | L47: Bioinformatics Analysis | M47: Laboratory Service | N47: Thru Bank Deposit | O47: 556950 | P47: 45246
A48: 2023 | B48: 45245 | C48: CS-2023-10-022 | D48: LC May C. Gasit | E48: 199883.2 | F48: CANCELLED | G48: =IFERROR(VLOOKUP(D48,'Client ID Records_v2'!D:E, 2, FALSE), "") -> CL-2023-126 | H48: =IFERROR(VLOOKUP(G48,'Client ID Records_v2'!E:F, 2, FALSE), "") -> Institute of Aquaculutre, College of Fisheries and Ocean Science, University of the Philippines Visayas, Miagao, Iloilo | I48: =IFERROR(VLOOKUP(D48,'Project Records_v2'!E:F, 2, FALSE), "") -> P-2023-062 | J48: =IFERROR(VLOOKUP(I48,'Project Records_v2'!F:G, 2, FALSE), "") -> Development of spawning and hatchery techniques for the blood cockle (Anadara granosa) for sustainable aquaculture | K48: Laboratory Service | L48: N/A | M48: Cancelled
A49: 2023 | B49: 45251 | C49: CS-2023-11-023 | D49: Dianne A. Peralta | E49: 411000 | F49: PAID | G49: =IFERROR(VLOOKUP(D49,'Client ID Records_v2'!D:E, 2, FALSE), "") -> CL-2024-131 | H49: =IFERROR(VLOOKUP(G49,'Client ID Records_v2'!E:F, 2, FALSE), "") -> DMMMSU Probiotics Research Project, Central Administration Building, Don Mariano Marcos Memorial State University, Sapilang, Bacnotan, La Union 2515 | I49: =IFERROR(VLOOKUP(D49,'Project Records_v2'!E:F, 2, FALSE), "") -> P-2024-071 | J49: =IFERROR(VLOOKUP(I49,'Project Records_v2'!F:G, 2, FALSE), "") -> Development of Probiotics from roselle (Hibiscus sabdariffa), mulberry (Morus alba), and corn (Zea mays) | K49: Training | L49: 16s Metagenomics | M49: Laboratory Service | N49: Thru Bank Deposit | O49: 580750 | P49: 45525 | Q49: DMMMSU CHED LAKAS PROJECT
A50: 2023 | B50: 45265 | C50: CS-2023-11-024 | D50: Dencee Jean T. Ledesma | E50: 195980.67 | F50: PAID | G50: =IFERROR(VLOOKUP(D50,'Client ID Records_v2'!D:E, 2, FALSE), "") -> CL-2023-127 | H50: =IFERROR(VLOOKUP(G50,'Client ID Records_v2'!E:F, 2, FALSE), "") -> DOST-ITDI-VIP, DOST Cmpd., General Santos Avenue, Bicutan, Taguig City, Philippines | I50: =IFERROR(VLOOKUP(D50,'Project Records_v2'!E:F, 2, FALSE), "") -> P-2024-093 | J50: =IFERROR(VLOOKUP(I50,'Project Records_v2'!F:G, 2, FALSE), "") -> Development of a LAMP-Based Detection Kit for Tomato Yellow Leaf Curl Virus (TYLCV) Philippine Strains | K50: Training | L50: WGS | M50: Laboratory Service | N50: Thru Bank Deposit | O50: 564168 | P50: 45335
A51: 2023 | B51: 45272 | C51: CS-2023-12-025 | D51: Philip Ian P. Padilla | E51: 2710.4 | F51: PAID | G51: =IFERROR(VLOOKUP(D51,'Client ID Records_v2'!D:E, 2, FALSE), "") -> CL-2023-119 | H51: =IFERROR(VLOOKUP(G51,'Client ID Records_v2'!E:F, 2, FALSE), "") -> Division of Biological Sciences, College of Arts and Sciences, UP Visayas Miagao Iloilo | I51: =IFERROR(VLOOKUP(D51,'Project Records_v2'!E:F, 2, FALSE), "") -> P-2023-061 | J51: =IFERROR(VLOOKUP(I51,'Project Records_v2'!F:G, 2, FALSE), "") -> Integrating early warning systems for community outbreaks using water-based epidemiology during post-COVID-19 pandemic | K51: Equipment Use | L51: N/A | M51: Laboratory Service | N51: TF-2024-01-00212 | O51: N/A | P51: 45299
A52: 2024 | B52: 45302 | C52: CS-2024-01-001 | D52: Franco Miguel N. Nodado | E52: 35763.2 | F52: PAID | G52: =IFERROR(VLOOKUP(D52,'Client ID Records_v2'!D:E, 2, FALSE), "") -> CL-2023-101 | H52: =IFERROR(VLOOKUP(G52,'Client ID Records_v2'!E:F, 2, FALSE), "") -> Biotechnology and Microbiology Laboratory, College of Medicine, West Visayas State University | I52: =IFERROR(VLOOKUP(D52,'Project Records_v2'!E:F, 2, FALSE), "") -> P-2023-055 | J52: =IFERROR(VLOOKUP(I52,'Project Records_v2'!F:G, 2, FALSE), "") -> Inhibitory Activity of Vitex negundo (Lagundi) Leaf Extract Against Biofilm Formation and Quorom Sensing of Vibrio cholerae | K52: Laboratory Service | L52: Extraction to qPCR | M52: Laboratory Service | N52: Thru Bank Deposit | O52: 560693 | P52: 45310 | Q52: Danielle L. Elevado Yoo Ki Bastol Zeb Jose Joshua C. Cabalfin Maio Vendell V. Sabidong Jemma Dawn C. Leonardo Leopoldo T. Bacquial II Kathleen Mae V. Donoso Nove Kris B. Herida Angel Mae T. Malones
A53: 2024 | B53: 45308 | C53: CS-2024-01-001 | D53: Jonie C. Yee, Ph.D. | E53: 50000 | F53: PAID | G53: =IFERROR(VLOOKUP(D53,'Client ID Records_v2'!D:E, 2, FALSE), "") -> CL-2024-128 | H53: =IFERROR(VLOOKUP(G53,'Client ID Records_v2'!E:F, 2, FALSE), "") -> Biology Department, College of Science and Arts, University of San Carlos, Nasipit, Talamban, Cebu City | I53: =IFERROR(VLOOKUP(D53,'Project Records_v2'!E:F, 2, FALSE), "") -> P-2024-064 | J53: =IFERROR(VLOOKUP(I53,'Project Records_v2'!F:G, 2, FALSE), "") -> Detection of Natural Products Derived from Sediment Microbes in Mangrove | K53: Laboratory Service | L53: Extraction to Amplicon Sequencing | M53: R&D | N53: Thru Bank Deposit | O53: 572780 | P53: 45457 | Q53: University of San Carlos, TIN 000-666-548-000.
A54: 2024 | B54: 45329 | C54: CS-2024-02-003 | D54: Kaylen Yvon K. Jalandoni | E54: 1232 | F54: PAID | G54: =IFERROR(VLOOKUP(D54,'Client ID Records_v2'!D:E, 2, FALSE), "") -> CL-2024-135 | H54: =IFERROR(VLOOKUP(G54,'Client ID Records_v2'!E:F, 2, FALSE), "") -> School of Technology, University of the Philippines Visayas | I54: =IFERROR(VLOOKUP(D54,'Project Records_v2'!E:F, 2, FALSE), "") -> P-2024-067 | J54: =IFERROR(VLOOKUP(I54,'Project Records_v2'!F:G, 2, FALSE), "") -> Mango Leaves-derived Biochar for the Removal of Amoxicillin in Aqueous Solution | K54: Retail Sales | L54: Type II Water | M54: Laboratory Service | N54: Thru Bank Deposit | O54: 564179 | P54: 45334 | Q54: Type II Water
A55: 2024 | B55: 45335 | C55: CS-2024-02-004 | D55: Ram Nikko U. Delegero | E55: 492.8 | F55: PAID | G55: =IFERROR(VLOOKUP(D55,'Client ID Records_v2'!D:E, 2, FALSE), "") -> CL-2024-139 | H55: =IFERROR(VLOOKUP(G55,'Client ID Records_v2'!E:F, 2, FALSE), "") -> School of Technology, University of the Philippines Visayas | I55: =IFERROR(VLOOKUP(D55,'Project Records_v2'!E:F, 2, FALSE), "") -> P-2024-068 | J55: =IFERROR(VLOOKUP(I55,'Project Records_v2'!F:G, 2, FALSE), "") -> Transesterification of Waste Vegetable Oil from Oil-based Thermal Disinfection Technology using SrO/CaO Bamboo Biochar Composite | K55: Retail Sales | L55: Type II Water | M55: Laboratory Service | N55: Thru Bank Deposit | O55: 569183 | P55: 45405 | Q55: Type II Water
A56: 2024 | B56: 45349 | C56: CS-2024-02-005 | D56: NEED Project, ℅ UPV-SPSO, PR No. NEED-2023-12-1 | E56: 204506.72 | F56: CANCELLED | G56: =IFERROR(VLOOKUP(D56,'Client ID Records_v2'!D:E, 2, FALSE), "") | H56: =IFERROR(VLOOKUP(G56,'Client ID Records_v2'!E:F, 2, FALSE), "") | I56: =IFERROR(VLOOKUP(D56,'Project Records_v2'!E:F, 2, FALSE), "") | J56: =IFERROR(VLOOKUP(I56,'Project Records_v2'!F:G, 2, FALSE), "") | L56: N/A | M56: Cancelled | Q56: Cancelled. Refer to revised 2024-031
A57: 2024 | B57: 45349 | C57: CS-2024-02-006 | D57: Jessette Mary Pauline Garcia | E57: 8976 | F57: PAID | G57: =IFERROR(VLOOKUP(D57,'Client ID Records_v2'!D:E, 2, FALSE), "") -> CL-2024-142 | H57: =IFERROR(VLOOKUP(G57,'Client ID Records_v2'!E:F, 2, FALSE), "") -> College of Medicine - Biotechnology and Biomedical Research Laboratory, West Visayas State University | I57: =IFERROR(VLOOKUP(D57,'Project Records_v2'!E:F, 2, FALSE), "") -> P-2024-070 | J57: =IFERROR(VLOOKUP(I57,'Project Records_v2'!F:G, 2, FALSE), "") -> DNA Barcoding and Depuration Protocol of Windowpane oysters (Placuna placenta) from Oton, Iloilo | K57: Laboratory Service | L57: Extraction to Amplicon Sequencing | M57: Laboratory Service | N57: Thru Bank Deposit | O57: 565598 | P57: 45357 | Q57: Caryl Anne G. Abulencia
A58: 2024 | B58: 45355 | C58: CS-2024-03-007 | D58: Dianne A. Peralta | E58: 25036 | F58: PAID | G58: =IFERROR(VLOOKUP(D58,'Client ID Records_v2'!D:E, 2, FALSE), "") -> CL-2024-131 | H58: =IFERROR(VLOOKUP(G58,'Client ID Records_v2'!E:F, 2, FALSE), "") -> DMMMSU Probiotics Research Project, Central Administration Building, Don Mariano Marcos Memorial State University, Sapilang, Bacnotan, La Union 2515 | I58: =IFERROR(VLOOKUP(D58,'Project Records_v2'!E:F, 2, FALSE), "") -> P-2024-071 | J58: =IFERROR(VLOOKUP(I58,'Project Records_v2'!F:G, 2, FALSE), "") -> Development of Probiotics from roselle (Hibiscus sabdariffa), mulberry (Morus alba), and corn (Zea mays) | K58: Laboratory Service | L58: Extraction to 16s Metagenomics Sequencing | M58: Laboratory Service | N58: Thru Bank Deposit | O58: 565477 | P58: 45356
A59: 2024 | B59: 45362 | C59: CS-2024-03-008 | D59: Kristina Casandra Pava | E59: 2175.9 | F59: PAID | G59: =IFERROR(VLOOKUP(D59,'Client ID Records_v2'!D:E, 2, FALSE), "") -> CL-2024-144 | H59: =IFERROR(VLOOKUP(G59,'Client ID Records_v2'!E:F, 2, FALSE), "") -> Central Mindanao University, University Town, Musuan, Maramag, Bukidnon 8710 | I59: =IFERROR(VLOOKUP(D59,'Project Records_v2'!E:F, 2, FALSE), "") -> P-2024-079 | J59: =IFERROR(VLOOKUP(I59,'Project Records_v2'!F:G, 2, FALSE), "") -> . | K59: Bioinformatics Analysis | L59: Customized Analysis | M59: Laboratory Service | N59: Thru Bank Deposit | O59: 565885 | P59: 45365
A60: 2024 | B60: 45363 | C60: CS-2024-03-009 | D60: Marielle B. Chu | E60: 1839.2 | F60: PAID | G60: =IFERROR(VLOOKUP(D60,'Client ID Records_v2'!D:E, 2, FALSE), "") -> CL-2024-151 | H60: =IFERROR(VLOOKUP(G60,'Client ID Records_v2'!E:F, 2, FALSE), "") -> University of the Philippines High School in Iloilo, College of Arts and Science | I60: =IFERROR(VLOOKUP(D60,'Project Records_v2'!E:F, 2, FALSE), "") -> P-2024-080 | J60: =IFERROR(VLOOKUP(I60,'Project Records_v2'!F:G, 2, FALSE), "") -> Isolation and characterization of cellulolytic bacteria from decomposing leaf litter | K60: Laboratory Service | L60: Extraction to Amplicon Sequencing | M60: Laboratory Service | N60: Thru Bank Deposit | O60: 568383 | P60: 45378
A61: 2024 | B61: 45393 | C61: CS-2024-04-010 | D61: Clarissa L. Gomez | E61: 10096.15 | F61: PAID | G61: =IFERROR(VLOOKUP(D61,'Client ID Records_v2'!D:E, 2, FALSE), "") | H61: =IFERROR(VLOOKUP(G61,'Client ID Records_v2'!E:F, 2, FALSE), "") | I61: =IFERROR(VLOOKUP(D61,'Project Records_v2'!E:F, 2, FALSE), "") -> P-2024-081 | J61: =IFERROR(VLOOKUP(I61,'Project Records_v2'!F:G, 2, FALSE), "") -> Role of Type VI Secretion System During Shrimp Infection of Vibrio spp. - Causing Acute Hepatopancreatic Necrosis Disease (AHPND) | K61: Bioinformatics Analysis | L61: Customized Analysis | M61: Laboratory Service | N61: Thru Bank Deposit | O61: 568985 | Q61: Mary Nia M. Santos, Ph.D.
A62: 2024 | B62: 45385 | C62: CS-2024-03-011 | D62: Mark S. Calabon | E62: 99040 | F62: PAID | G62: =IFERROR(VLOOKUP(D62,'Client ID Records_v2'!D:E, 2, FALSE), "") -> CL-2023-096 | H62: =IFERROR(VLOOKUP(G62,'Client ID Records_v2'!E:F, 2, FALSE), "") -> Division of Biological Sciences, College of Arts and Sciences, UP Visayas Miagao Iloilo | I62: =IFERROR(VLOOKUP(D62,'Project Records_v2'!E:F, 2, FALSE), "") -> P-2023-052 | J62: =IFERROR(VLOOKUP(I62,'Project Records_v2'!F:G, 2, FALSE), "") -> Unraveling the Hidden Diversity of Aquatic Fungi from Panay Island, Philippines Project | K62: Laboratory Service | L62: Extraction to Amplicon Sequencing | M62: R&D | N62: TF-2024-05-04359 | P62: 45421
A63: 2024 | B63: 45442 | C63: CS-2024-05-012 | D63: Anne-Nora N. Sabirin | E63: 8228 | F63: PAID | G63: =IFERROR(VLOOKUP(D63,'Client ID Records_v2'!D:E, 2, FALSE), "") -> CL-2024-167 | H63: =IFERROR(VLOOKUP(G63,'Client ID Records_v2'!E:F, 2, FALSE), "") -> Animal Ecology Laboratory, PRISM 2nd Floor, Mindanao State University - Iligan Institute of Technology, Andres Bonifacio Ave., Tibanga, Iligan City 9200, Philippines | I63: =IFERROR(VLOOKUP(D63,'Project Records_v2'!E:F, 2, FALSE), "") -> P-2024-086 | J63: =IFERROR(VLOOKUP(I63,'Project Records_v2'!F:G, 2, FALSE), "") -> Metabarcoding of Goat feces for Gastrointestinal nematode identification | K63: Laboratory Service | L63: Extraction to Metabarcoding | M63: Laboratory Service | N63: Thru Bank Deposit | O63: 572084 | P63: 45447
A64: 2024 | B64: 45443 | C64: CS-2024-05-013 | D64: John Paul Resano | E64: 5579.2 | F64: PAID | G64: =IFERROR(VLOOKUP(D64,'Client ID Records_v2'!D:E, 2, FALSE), "") -> CL-2024-171 | H64: =IFERROR(VLOOKUP(G64,'Client ID Records_v2'!E:F, 2, FALSE), "") -> Aklan State University | I64: =IFERROR(VLOOKUP(D64,'Project Records_v2'!E:F, 2, FALSE), "") -> P-2024-089 | J64: =IFERROR(VLOOKUP(I64,'Project Records_v2'!F:G, 2, FALSE), "") -> Detection of Salmonella in Barn Swallow (Hirundu rustica) in Banga, Aklan | K64: Laboratory Service | L64: Extraction to Amplicon Sequencing | M64: Laboratory Service | N64: Thru Bank Deposit | O64: 570950 | P64: 45446
A65: 2024 | B65: 45447 | C65: CS-2024-06-014 | D65: Gavin Louie M. Amolo | E65: 14989.88 | F65: PAID | G65: =IFERROR(VLOOKUP(D65,'Client ID Records_v2'!D:E, 2, FALSE), "") -> CL-2024-170 | H65: =IFERROR(VLOOKUP(G65,'Client ID Records_v2'!E:F, 2, FALSE), "") -> Siargao National High School, Barangay 6, Dapa, Surigao del Norte 8417 | I65: =IFERROR(VLOOKUP(D65,'Project Records_v2'!E:F, 2, FALSE), "") -> P-2024-088 | J65: =IFERROR(VLOOKUP(I65,'Project Records_v2'!F:G, 2, FALSE), "") -> Microbes Beneath the Surface: Exploring Diversity and Distribution of Microbial Species on Different Soil Samples in Siargao Island | K65: Laboratory Service | L65: Extraction to 16s Metagenomics Sequencing | M65: Laboratory Service | N65: Thru Bank Deposit | O65: 574342
A66: 2024 | B66: 45456 | C66: CS-2024-06-015 | D66: Ryuya Matsuda | E66: 8976 | F66: PAID | G66: =IFERROR(VLOOKUP(D66,'Client ID Records_v2'!D:E, 2, FALSE), "") -> CL-2024-175 | H66: =IFERROR(VLOOKUP(G66,'Client ID Records_v2'!E:F, 2, FALSE), "") -> Japan International Research Center for Agricultural Sciences (JIRCAS) | I66: =IFERROR(VLOOKUP(D66,'Project Records_v2'!E:F, 2, FALSE), "") -> P-2024-092 | J66: =IFERROR(VLOOKUP(I66,'Project Records_v2'!F:G, 2, FALSE), "") -> Identification of seaweed species using DNA sequence | K66: Laboratory Service | L66: Extraction to Amplicon Sequencing | M66: Laboratory Service | N66: Thru Bank Deposit | O66: 572622 | P66: 45456
A67: 2024 | B67: 45478 | C67: CS-2024-07-016 | D67: Josie Mar G. Cabalo | E67: 249962.98 | F67: PAID | G67: =IFERROR(VLOOKUP(D67,'Client ID Records_v2'!D:E, 2, FALSE), "") -> CL-2023-085 | H67: =IFERROR(VLOOKUP(G67,'Client ID Records_v2'!E:F, 2, FALSE), "") -> Institute of Aquaculutre, College of Fisheries and Ocean Science, University of the Philippines Visayas, Miagao, Iloilo | I67: =IFERROR(VLOOKUP(D67,'Project Records_v2'!E:F, 2, FALSE), "") -> P-2024-084 | J67: =IFERROR(VLOOKUP(I67,'Project Records_v2'!F:G, 2, FALSE), "") -> Improvement of Milkfish Larval Rearing and Nursery Culture through Gut Metagenome, Transcriptome Analysis, and Gut Microbial Community Manipulations | K67: Laboratory Service | L67: Extraction to WGS | M67: R&D | N67: 2024-07-06932 | O67: 71003 | P67: 45988 | Q67: 2025
A68: 2024 | B68: 45498 | C68: CS-2024-07-017 | D68: Jhianaly Erestingcol | E68: 1120 | F68: PAID | G68: =IFERROR(VLOOKUP(D68,'Client ID Records_v2'!D:E, 2, FALSE), "") -> CL-2024-178 | H68: =IFERROR(VLOOKUP(G68,'Client ID Records_v2'!E:F, 2, FALSE), "") -> Passi National High School | I68: =IFERROR(VLOOKUP(D68,'Project Records_v2'!E:F, 2, FALSE), "") | J68: =IFERROR(VLOOKUP(I68,'Project Records_v2'!F:G, 2, FALSE), "") | K68: Equipment Use | L68: N/A | M68: Laboratory Service | N68: Thru Bank Deposit | O68: 579984 | P68: 45518
A69: 2024 | B69: 45538 | C69: CS-2024-09-019 | D69: Fausto dela Cruz | E69: 23943.52 | F69: PAID | G69: =IFERROR(VLOOKUP(D69,'Client ID Records_v2'!D:E, 2, FALSE), "") -> CL-2024-181 | H69: =IFERROR(VLOOKUP(G69,'Client ID Records_v2'!E:F, 2, FALSE), "") -> Iloilo State University of Fisheries Science and Technology | I69: =IFERROR(VLOOKUP(D69,'Project Records_v2'!E:F, 2, FALSE), "") -> P-2024-096 | J69: =IFERROR(VLOOKUP(I69,'Project Records_v2'!F:G, 2, FALSE), "") -> Growth Performance and Genetic Characterization of Tilapia Strains in Culasi, Antique, Phiippines | K69: Laboratory Service | L69: Extraction to Amplicon Sequencing | M69: Laboratory Service | N69: Thru Bank Deposit | O69: 581654 | P69: 45549
A70: 2024 | B70: 45548 | C70: CS-2024-09-020 | D70: Dianne A. Peralta | E70: 37878.95 | F70: PAID | G70: =IFERROR(VLOOKUP(D70,'Client ID Records_v2'!D:E, 2, FALSE), "") -> CL-2024-131 | H70: =IFERROR(VLOOKUP(G70,'Client ID Records_v2'!E:F, 2, FALSE), "") -> DMMMSU Probiotics Research Project, Central Administration Building, Don Mariano Marcos Memorial State University, Sapilang, Bacnotan, La Union 2515 | I70: =IFERROR(VLOOKUP(D70,'Project Records_v2'!E:F, 2, FALSE), "") -> P-2024-071 | J70: =IFERROR(VLOOKUP(I70,'Project Records_v2'!F:G, 2, FALSE), "") -> Development of Probiotics from roselle (Hibiscus sabdariffa), mulberry (Morus alba), and corn (Zea mays) | K70: Laboratory Service | L70: Extraction to 16s Metagenomics Sequencing | M70: R&D | N70: 1075-2024 | O70: 0593484 | P70: 45712 | Q70: VMENF-SOA-2024-003_56k.png
A71: 2024 | B71: 45554 | C71: CS-2024-09-021 | D71: Josh Emmanuel Castro | E71: 350 | G71: =IFERROR(VLOOKUP(D71,'Client ID Records_v2'!D:E, 2, FALSE), "") -> CL-2024-186 | H71: =IFERROR(VLOOKUP(G71,'Client ID Records_v2'!E:F, 2, FALSE), "") -> UP HSI | I71: =IFERROR(VLOOKUP(D71,'Project Records_v2'!E:F, 2, FALSE), "") | J71: =IFERROR(VLOOKUP(I71,'Project Records_v2'!F:G, 2, FALSE), "") | K71: Equipment Use | L71: N/A | M71: Laboratory Service
A72: 2024 | B72: 45555 | C72: CS-2024-09-022 | D72: Dencee Jean T. Ledesma | E72: 466170 | F72: CANCELLED | G72: =IFERROR(VLOOKUP(D72,'Client ID Records_v2'!D:E, 2, FALSE), "") -> CL-2023-127 | H72: =IFERROR(VLOOKUP(G72,'Client ID Records_v2'!E:F, 2, FALSE), "") -> DOST-ITDI-VIP, DOST Cmpd., General Santos Avenue, Bicutan, Taguig City, Philippines | I72: =IFERROR(VLOOKUP(D72,'Project Records_v2'!E:F, 2, FALSE), "") -> P-2024-093 | J72: =IFERROR(VLOOKUP(I72,'Project Records_v2'!F:G, 2, FALSE), "") -> Development of a LAMP-Based Detection Kit for Tomato Yellow Leaf Curl Virus (TYLCV) Philippine Strains | L72: Extraction to WGS | M72: Cancelled | Q72: 11/15/24- charge slip sent to itdi
A73: 2024 | B73: 45559 | C73: CS-2024-09-023 | D73: Laura Elyse J. Cambel | E73: 206965.44 | F73: PAID | G73: =IFERROR(VLOOKUP(D73,'Client ID Records_v2'!D:E, 2, FALSE), "") -> CL-2024-172 | H73: =IFERROR(VLOOKUP(G73,'Client ID Records_v2'!E:F, 2, FALSE), "") -> Biological Sciences Department, West Visayas State University, Luna Street, Lapaz, Iloilo City 5001 | I73: =IFERROR(VLOOKUP(D73,'Project Records_v2'!E:F, 2, FALSE), "") -> P-2024-090 | J73: =IFERROR(VLOOKUP(I73,'Project Records_v2'!F:G, 2, FALSE), "") -> Understanding Endophytic Fungi in Medicinal Plants and their Antibacterial Potential on Common and Antibiotic-Resistant Bacteria (ESKAPE pathogens) | K73: Laboratory Service | L73: Extraction to WGS and Amplicon Sequencing | M73: R&D | N73: N/A | O73: 589222 | P73: 45665 | Q73: CS-2024-09-023_206k
A74: 2024 | B74: 45567 | C74: CS-2024-09-024 | D74: Dencee Jean T. Ledesma | E74: 298625 | F74: PROCESSING | G74: =IFERROR(VLOOKUP(D74,'Client ID Records_v2'!D:E, 2, FALSE), "") -> CL-2023-127 | H74: =IFERROR(VLOOKUP(G74,'Client ID Records_v2'!E:F, 2, FALSE), "") -> DOST-ITDI-VIP, DOST Cmpd., General Santos Avenue, Bicutan, Taguig City, Philippines | I74: =IFERROR(VLOOKUP(D74,'Project Records_v2'!E:F, 2, FALSE), "") -> P-2024-093 | J74: =IFERROR(VLOOKUP(I74,'Project Records_v2'!F:G, 2, FALSE), "") -> Development of a LAMP-Based Detection Kit for Tomato Yellow Leaf Curl Virus (TYLCV) Philippine Strains | K74: Laboratory Service | L74: Extraction to WGS | M74: Laboratory Service | N74: PO #: GIA-WO-2024-03-0034
A75: 2024 | B75: 45567 | C75: CS-2024-09-025 | D75: Dencee Jean T. Ledesma | E75: 146288 | F75: PROCESSING | G75: =IFERROR(VLOOKUP(D75,'Client ID Records_v2'!D:E, 2, FALSE), "") -> CL-2023-127 | H75: =IFERROR(VLOOKUP(G75,'Client ID Records_v2'!E:F, 2, FALSE), "") -> DOST-ITDI-VIP, DOST Cmpd., General Santos Avenue, Bicutan, Taguig City, Philippines | I75: =IFERROR(VLOOKUP(D75,'Project Records_v2'!E:F, 2, FALSE), "") -> P-2024-093 | J75: =IFERROR(VLOOKUP(I75,'Project Records_v2'!F:G, 2, FALSE), "") -> Development of a LAMP-Based Detection Kit for Tomato Yellow Leaf Curl Virus (TYLCV) Philippine Strains | K75: Bioinformatics Analysis | L75: WGS Assembly | M75: Laboratory Service | N75: PO #: GIA-WO-2024-03-0033
A76: 2024 | B76: 45567 | C76: CS-2024-09-026 | D76: Dencee Jean T. Ledesma | E76: 21257.6 | F76: CANCELLED | G76: =IFERROR(VLOOKUP(D76,'Client ID Records_v2'!D:E, 2, FALSE), "") -> CL-2023-127 | H76: =IFERROR(VLOOKUP(G76,'Client ID Records_v2'!E:F, 2, FALSE), "") -> DOST-ITDI-VIP, DOST Cmpd., General Santos Avenue, Bicutan, Taguig City, Philippines | I76: =IFERROR(VLOOKUP(D76,'Project Records_v2'!E:F, 2, FALSE), "") -> P-2024-093 | J76: =IFERROR(VLOOKUP(I76,'Project Records_v2'!F:G, 2, FALSE), "") -> Development of a LAMP-Based Detection Kit for Tomato Yellow Leaf Curl Virus (TYLCV) Philippine Strains | L76: WGS Assembly | M76: Cancelled
A77: 2024 | B77: 45567 | C77: CS-2024-09-027 | D77: Dianne A. Peralta | E77: 8564.03 | F77: PAID | G77: =IFERROR(VLOOKUP(D77,'Client ID Records_v2'!D:E, 2, FALSE), "") -> CL-2024-131 | H77: =IFERROR(VLOOKUP(G77,'Client ID Records_v2'!E:F, 2, FALSE), "") -> DMMMSU Probiotics Research Project, Central Administration Building, Don Mariano Marcos Memorial State University, Sapilang, Bacnotan, La Union 2515 | I77: =IFERROR(VLOOKUP(D77,'Project Records_v2'!E:F, 2, FALSE), "") -> P-2024-071 | J77: =IFERROR(VLOOKUP(I77,'Project Records_v2'!F:G, 2, FALSE), "") -> Development of Probiotics from roselle (Hibiscus sabdariffa), mulberry (Morus alba), and corn (Zea mays) | K77: Bioinformatics Analysis | L77: WGS Assembly | M77: Laboratory Service | N77: Thru Bank Deposit | O77: O582579 | P77: 45569
A78: 2024 | B78: 45568 | C78: CS-2024-09-028 | D78: Dianne A. Peralta | E78: 47958.56 | F78: PAID | G78: =IFERROR(VLOOKUP(D78,'Client ID Records_v2'!D:E, 2, FALSE), "") -> CL-2024-131 | H78: =IFERROR(VLOOKUP(G78,'Client ID Records_v2'!E:F, 2, FALSE), "") -> DMMMSU Probiotics Research Project, Central Administration Building, Don Mariano Marcos Memorial State University, Sapilang, Bacnotan, La Union 2515 | I78: =IFERROR(VLOOKUP(D78,'Project Records_v2'!E:F, 2, FALSE), "") -> P-2024-071 | J78: =IFERROR(VLOOKUP(I78,'Project Records_v2'!F:G, 2, FALSE), "") -> Development of Probiotics from roselle (Hibiscus sabdariffa), mulberry (Morus alba), and corn (Zea mays) | K78: Bioinformatics Analysis | L78: 16s rRNA Metagenomics Analysis | M78: Laboratory Service | N78: CS-2024-09-028_47k.pdf | Q78: Request OR
A79: 2024 | B79: 45569 | C79: CS-2024-09-029 | D79: Carmelo del Castillo | E79: 149943.2 | F79: CANCELLED | G79: =IFERROR(VLOOKUP(D79,'Client ID Records_v2'!D:E, 2, FALSE), "") -> CL-2020-021 | H79: =IFERROR(VLOOKUP(G79,'Client ID Records_v2'!E:F, 2, FALSE), "") -> Institute of Aquaculture, College of Fisheries and Ocean Sciences, University of the Philippines Visayas, Miagao, 5023, Iloilo | I79: =IFERROR(VLOOKUP(D79,'Project Records_v2'!E:F, 2, FALSE), "") -> P-2024-101 | J79: =IFERROR(VLOOKUP(I79,'Project Records_v2'!F:G, 2, FALSE), "") -> Field Testing of Hatchery & Nursery Production & Development of Broodstock Transport Protocols for the Native Catfish Clarias macrocephalus | L79: Extraction to Amplicon Sequencing | M79: R&D
A80: 2024 | B80: 45575 | C80: CS-2024-09-030 | D80: Carmelo del Castillo | E80: 144851.04 | F80: CANCELLED | G80: =IFERROR(VLOOKUP(D80,'Client ID Records_v2'!D:E, 2, FALSE), "") -> CL-2020-021 | H80: =IFERROR(VLOOKUP(G80,'Client ID Records_v2'!E:F, 2, FALSE), "") -> Institute of Aquaculture, College of Fisheries and Ocean Sciences, University of the Philippines Visayas, Miagao, 5023, Iloilo | I80: =IFERROR(VLOOKUP(D80,'Project Records_v2'!E:F, 2, FALSE), "") -> P-2024-101 | J80: =IFERROR(VLOOKUP(I80,'Project Records_v2'!F:G, 2, FALSE), "") -> Field Testing of Hatchery & Nursery Production & Development of Broodstock Transport Protocols for the Native Catfish Clarias macrocephalus | L80: Extraction to Bioinformatics Analysis | M80: R&D
A81: 2024 | B81: 45579 | C81: CS-2024-09-031 | D81: Fredson H. Huervana | E81: 158526.72 | F81: PAID | G81: =IFERROR(VLOOKUP(D81,'Client ID Records_v2'!D:E, 2, FALSE), "") -> CL-2024-202 | H81: =IFERROR(VLOOKUP(G81,'Client ID Records_v2'!E:F, 2, FALSE), "") -> CFOS-IA, University of the Philippines Visayas | I81: =IFERROR(VLOOKUP(D81,'Project Records_v2'!E:F, 2, FALSE), "") -> P-2024-104 | J81: =IFERROR(VLOOKUP(I81,'Project Records_v2'!F:G, 2, FALSE), "") -> Development of Brackishwater Nursery Culturing Systems for Tropical Anguilid Eel, Anguilla marmorata, in the Philippines | K81: Laboratory Service | L81: Extraction to Amplicon Sequencing | M81: R&D | N81: TF-2024-10-0610 | O81: 584484 | P81: 45601 | Q81: NEED Project, ℅ UPV-SPSO, PR No. NEED-2023-12-1
A82: 2024 | B82: 45594 | C82: CS-2024-09-032 | D82: Jessa Cortes | E82: 4343.31 | G82: =IFERROR(VLOOKUP(D82,'Client ID Records_v2'!D:E, 2, FALSE), "") -> CL-2024-185 | H82: =IFERROR(VLOOKUP(G82,'Client ID Records_v2'!E:F, 2, FALSE), "") -> IMFO, University of the Philippines Visayas | I82: =IFERROR(VLOOKUP(D82,'Project Records_v2'!E:F, 2, FALSE), "") -> P-2024-100 | J82: =IFERROR(VLOOKUP(I82,'Project Records_v2'!F:G, 2, FALSE), "") -> Equipment Use | K82: Bioinformatics Analysis | L82: Customized Analysis | M82: Laboratory Service
A83: 2024 | B83: 45601 | C83: CS-2024-09-033 | D83: Christian Molina | E83: 151156.52 | F83: CANCELLED | G83: =IFERROR(VLOOKUP(D83,'Client ID Records_v2'!D:E, 2, FALSE), "") -> CL-2024-205 | H83: =IFERROR(VLOOKUP(G83,'Client ID Records_v2'!E:F, 2, FALSE), "") -> Ilocos Sur Polytechnic State College | I83: T-2024-006 | J83: =IFERROR(VLOOKUP(I83,'Project Records_v2'!F:G, 2, FALSE), "") | L83: WGS | M83: Cancelled | Q83: Disregard; See CS-2024-033
A84: 2024 | B84: 45608 | C84: CS-2024-09-033b | D84: Christian Molina | E84: 130996.52 | F84: CANCELLED | G84: =IFERROR(VLOOKUP(D84,'Client ID Records_v2'!D:E, 2, FALSE), "") -> CL-2024-205 | H84: =IFERROR(VLOOKUP(G84,'Client ID Records_v2'!E:F, 2, FALSE), "") -> Ilocos Sur Polytechnic State College | I84: T-2024-006 | J84: =IFERROR(VLOOKUP(I84,'Project Records_v2'!F:G, 2, FALSE), "") | L84: WGS | M84: Cancelled | Q84: Disregard; See CS-2024-036
A85: 2024 | B85: 45609 | C85: CS-2024-034 | D85: Janiela Marie Castaño | E85: =(280*7)-(280*7*12%) -> 1724.8 | F85: PAID | G85: =IFERROR(VLOOKUP(D85,'Client ID Records_v2'!D:E, 2, FALSE), "") -> CL-2024-210 | H85: =IFERROR(VLOOKUP(G85,'Client ID Records_v2'!E:F, 2, FALSE), "") -> SOTECH, UP Visayas | I85: N/A | J85: =IFERROR(VLOOKUP(I85,'Project Records_v2'!F:G, 2, FALSE), "") | K85: Retail Sales | L85: Type II Water | M85: Laboratory Service | N85: Thru Bank Deposit | O85: 584828 | P85: 45610
A86: 2024 | B86: 45609 | C86: CS-2024-035 | D86: Jennifer S. Noveda | E86: 19944.32 | F86: PAID | G86: =IFERROR(VLOOKUP(D86,'Client ID Records_v2'!D:E, 2, FALSE), "") -> CL-2024-219 | H86: =IFERROR(VLOOKUP(G86,'Client ID Records_v2'!E:F, 2, FALSE), "") -> UPV-IFPT | I86: =IFERROR(VLOOKUP(D86,'Project Records_v2'!E:F, 2, FALSE), "") -> P-2024-105 | J86: =IFERROR(VLOOKUP(I86,'Project Records_v2'!F:G, 2, FALSE), "") | K86: Laboratory Service | L86: Extraction to 16s Metagenomics Sequencing | M86: Laboratory Service | N86: Thru Bank Deposit | O86: 584802 | P86: 45610
A87: 2024 | B87: 45610 | C87: CS-2024-036 | D87: Christian Molina | E87: 140239.9 | F87: CANCELLED | G87: =IFERROR(VLOOKUP(D87,'Client ID Records_v2'!D:E, 2, FALSE), "") -> CL-2024-205 | H87: =IFERROR(VLOOKUP(G87,'Client ID Records_v2'!E:F, 2, FALSE), "") -> Ilocos Sur Polytechnic State College | I87: T-2024-006 | J87: =IFERROR(VLOOKUP(I87,'Project Records_v2'!F:G, 2, FALSE), "") | K87: Training | L87: WGS | M87: Cancelled | Q87: Disregard; See CS-2024-039
A88: 2024 | B88: 45611 | C88: CS-2024-037 | D88: Eric Zeus C. Rizo | E88: 199987.04 | F88: CANCELLED | G88: =IFERROR(VLOOKUP(D88,'Client ID Records_v2'!D:E, 2, FALSE), "") -> CL-2022-038 | H88: =IFERROR(VLOOKUP(G88,'Client ID Records_v2'!E:F, 2, FALSE), "") -> Division of Biological Sciences, College of Arts and Sciences, University of the Philippines Visayas, Miagao, Iloilo | I88: =IFERROR(VLOOKUP(D88,'Project Records_v2'!E:F, 2, FALSE), "") -> P-2022-017 | J88: =IFERROR(VLOOKUP(I88,'Project Records_v2'!F:G, 2, FALSE), "") -> Development of a Water Quality Biological Monitoring Protocol using Genetic, Phylogenetic and Functional Diversity on Freshwater Zooplankton Communitites in Inland Waters of Panay Island, Philippines | L88: Extraction to Amplicon Sequencing | M88: Cancelled
A89: 2024 | B89: 45611 | C89: CS-2024-038 | D89: Maximino R. Abejo III | E89: 97979.59 | F89: PAID | G89: =IFERROR(VLOOKUP(D89,'Client ID Records_v2'!D:E, 2, FALSE), "") -> CL-2024-221 | H89: =IFERROR(VLOOKUP(G89,'Client ID Records_v2'!E:F, 2, FALSE), "") -> Center for Limnological, Aquatic Biodiversity, and Mariculture Studies, Cebu Technological University - San Francisco | I89: T-2024-007 | J89: =IFERROR(VLOOKUP(I89,'Project Records_v2'!F:G, 2, FALSE), "") | K89: Training | L89: Basic Mol to NGS | M89: Laboratory Service | N89: N/A | Q89: OR not in file; Deposit slip only
A90: 2024 | B90: 45615 | C90: CS-2024-039 | D90: Christian Molina | E90: 130996.52 | F90: PAID | G90: =IFERROR(VLOOKUP(D90,'Client ID Records_v2'!D:E, 2, FALSE), "") -> CL-2024-205 | H90: =IFERROR(VLOOKUP(G90,'Client ID Records_v2'!E:F, 2, FALSE), "") -> Ilocos Sur Polytechnic State College | I90: T-2024-006 | J90: =IFERROR(VLOOKUP(I90,'Project Records_v2'!F:G, 2, FALSE), "") | K90: Training | L90: WGS | M90: Laboratory Service | N90: 2024-11-2406 | O90: 0587742 | P90: 45638 | Q90: OR Released
A91: 2024 | B91: 45616 | C91: CS-2024-040 | D91: Maureen Emily V. Niño | E91: 199996.72 | F91: PAID | G91: =IFERROR(VLOOKUP(D91,'Client ID Records_v2'!D:E, 2, FALSE), "") -> CL-2023-114 | H91: =IFERROR(VLOOKUP(G91,'Client ID Records_v2'!E:F, 2, FALSE), "") -> Division of Biological Sciences, CAS Bldg., UP Visayas, Miagao, Iloilo 5023 | I91: =IFERROR(VLOOKUP(D91,'Project Records_v2'!E:F, 2, FALSE), "") -> P-2023-058 | J91: =IFERROR(VLOOKUP(I91,'Project Records_v2'!F:G, 2, FALSE), "") -> Diversity assessment of freshwater zooplankton and macroinvertebrates towards identification of centers of biodiversity conservation in the Jalaur River Basin, Iloilo, Philippines | K91: Laboratory Service | L91: Extraction to Amplicon Sequencing | M91: R&D | N91: RF-2024-11-01783 | O91: 587978 | P91: 45646 | Q91: Request for OR copy from Mau
A92: 2024 | B92: 45618 | C92: CS-2024-041 | D92: Jihan Santanina Alumbro | E92: 52162.67 | F92: PROCESSING | G92: =IFERROR(VLOOKUP(D92,'Client ID Records_v2'!D:E, 2, FALSE), "") -> CL-2024-201 | H92: =IFERROR(VLOOKUP(G92,'Client ID Records_v2'!E:F, 2, FALSE), "") -> School of Technology, UPV | I92: T-2024-005 | J92: =IFERROR(VLOOKUP(I92,'Project Records_v2'!F:G, 2, FALSE), "") | K92: Training | L92: Extraction and PCR | M92: Laboratory Service | Q92: Follow up
A93: 2024 | B93: 45623 | C93: CS-2024-042 | D93: Dr. Mary Jane S. Apines-Amar | E93: 79966.04 | F93: PROCESSING | G93: =IFERROR(VLOOKUP(D93,'Client ID Records_v2'!D:E, 2, FALSE), "") -> CL-2024-224 | H93: =IFERROR(VLOOKUP(G93,'Client ID Records_v2'!E:F, 2, FALSE), "") -> Institute of Aquaculutre, College of Fisheries and Ocean Science, University of the Philippines Visayas, Miagao, Iloilo | I93: =IFERROR(VLOOKUP(D93,'Project Records_v2'!E:F, 2, FALSE), "") -> P-2024-109 | J93: =IFERROR(VLOOKUP(I93,'Project Records_v2'!F:G, 2, FALSE), "") -> Developing insect-based feed using traditional and molecular approaches for sustainable production of Nile Tilapia in the Philippines | K93: Laboratory Service | L93: Extraction, 16s Metagenomics, Bioinformatics Analysis | M93: Laboratory Service | Q93: Requested change of date to Dec. 6, 2024; Original CS sent
A94: 2024 | B94: 45624 | C94: CS-2024-043 | D94: Christian Jay Rosal | E94: 2640 | F94: PAID | G94: =IFERROR(VLOOKUP(D94,'Client ID Records_v2'!D:E, 2, FALSE), "") -> CL-2024-225 | H94: =IFERROR(VLOOKUP(G94,'Client ID Records_v2'!E:F, 2, FALSE), "") -> College of Science, University of the Philippines Visayas | I94: =IFERROR(VLOOKUP(D94,'Project Records_v2'!E:F, 2, FALSE), "") -> P-2024-110 | J94: =IFERROR(VLOOKUP(I94,'Project Records_v2'!F:G, 2, FALSE), "") -> Seasonal Variability of Ingested Microplastics in Stolephorus indicus (van Hasselt,1823) in Tangalan, Aklan Philippines | K94: Retail Sales | L94: Type 1 Water | M94: Laboratory Service | N94: NA | O94: 0587319 | P94: 45625 | Q94: 4 Liters remaining ao Feb 10
A95: 2024 | B95: 45638 | C95: CS-2024-044 | D95: Christian Molina | E95: 89000 | F95: PAID | G95: =IFERROR(VLOOKUP(D95,'Client ID Records_v2'!D:E, 2, FALSE), "") -> CL-2024-205 | H95: =IFERROR(VLOOKUP(G95,'Client ID Records_v2'!E:F, 2, FALSE), "") -> Ilocos Sur Polytechnic State College | I95: =IFERROR(VLOOKUP(D95,'Project Records_v2'!E:F, 2, FALSE), "") -> P-2024-112 | J95: =IFERROR(VLOOKUP(I95,'Project Records_v2'!F:G, 2, FALSE), "") -> Probiotics Project | K95: Omics + Bioinfo | L95: 16s and WGS | M95: Laboratory Service | N95: 2024-12-2618 | Q95: Waiting for DV from client for OR Request
A96: 2025 | B96: 45664 | C96: CS-2025-001 | D96: Sabrina Gatdula | E96: 1380 | F96: PAID | G96: =IFERROR(VLOOKUP(D96,'Client ID Records_v2'!D:E, 2, FALSE), "") -> CL-2025-235 | H96: =IFERROR(VLOOKUP(G96,'Client ID Records_v2'!E:F, 2, FALSE), "") -> Colegio delas Hijas | I96: N/A | J96: Equipment Use | K96: Equipment Use | L96: spectro and micropipette | M96: Laboratory Service | P96: 45665 | Q96: waiting for OR from Cash Office
A97: 2025 | B97: 45666 | C97: CS-2025-002 | D97: Dianne A. Peralta | E97: 18777.44 | F97: PAID | G97: =IFERROR(VLOOKUP(D97,'Client ID Records_v2'!D:E, 2, FALSE), "") -> CL-2024-131 | H97: =IFERROR(VLOOKUP(G97,'Client ID Records_v2'!E:F, 2, FALSE), "") -> DMMMSU Probiotics Research Project, Central Administration Building, Don Mariano Marcos Memorial State University, Sapilang, Bacnotan, La Union 2515 | I97: =IFERROR(VLOOKUP(D97,'Project Records_v2'!E:F, 2, FALSE), "") -> P-2024-071 | J97: =IFERROR(VLOOKUP(I97,'Project Records_v2'!F:G, 2, FALSE), "") -> Development of Probiotics from roselle (Hibiscus sabdariffa), mulberry (Morus alba), and corn (Zea mays) | K97: Laboratory Service | L97: WGS (1 sample) | M97: Laboratory Service | N97: 1075-2024 | O97: 0593484 | P97: 45712 | Q97: VMENF-SOA-2024-003_56k.png
A98: 2025 | B98: 45680 | C98: CS-2025-003 | D98: Albaris Tahiluddin | E98: 96964.38 | F98: PAID | G98: =IFERROR(VLOOKUP(D98,'Client ID Records_v2'!D:E, 2, FALSE), "") -> CL-2024-220 | H98: =IFERROR(VLOOKUP(G98,'Client ID Records_v2'!E:F, 2, FALSE), "") -> MSU Tawi Tawi | I98: =IFERROR(VLOOKUP(D98,'Project Records_v2'!E:F, 2, FALSE), "") -> P-2024-106 | J98: Amplicon Sequencing of Bacterial and Fungal Isolates | K98: Laboratory Service | L98: 20 samples | M98: Laboratory Service | N98: thru Bank Transfer | O98: waiting for cash office | P98: 45693
A99: 2025 | B99: 45686 | C99: CS-2025-004 | D99: Bhea Olga de Panay | E99: 985.6 | F99: PAID | G99: =IFERROR(VLOOKUP(D99,'Client ID Records_v2'!D:E, 2, FALSE), "") -> CL-2025-252 | H99: SOTECH, UP Visayas | I99: N/A | J99: Purchase of Type 2 water/distilled | K99: Retail Sales | L99: 4 liters water | M99: Laboratory Service | N99: NA | Q99: waiting for OR from Cash Office
A100: 2025 | B100: 45322 | C100: CS-2025-005 | D100: Josie Mar G. Cabalo | E100: 249981.6 | F100: PROCESSING | G100: =IFERROR(VLOOKUP(D100,'Client ID Records_v2'!D:E, 2, FALSE), "") -> CL-2023-085 | H100: =IFERROR(VLOOKUP(G100,'Client ID Records_v2'!E:F, 2, FALSE), "") -> Institute of Aquaculutre, College of Fisheries and Ocean Science, University of the Philippines Visayas, Miagao, Iloilo | I100: =IFERROR(VLOOKUP(D100,'Project Records_v2'!E:F, 2, FALSE), "") -> P-2024-084 | J100: =IFERROR(VLOOKUP(I100,'Project Records_v2'!F:G, 2, FALSE), "") -> Improvement of Milkfish Larval Rearing and Nursery Culture through Gut Metagenome, Transcriptome Analysis, and Gut Microbial Community Manipulations | K100: Omics + Bioinfo | L100: 6 samples WGS Extraction to Bioinformatics Analysis | M100: Laboratory Service
...

Sheet Income Summary
A2: Category | B2: Income
A3: R&D | B3: =SUMIF('Charge SlipBilling'!M:M, "R&D",'Charge SlipBilling'!E:E) -> 4710518.6 | D3: =B3/B5 -> 0.51820489 | E3: =B8*D3 -> 2019645.3
A4: Laboratory Service | B4: =SUMIF('Charge SlipBilling'!M:M, "Laboratory Service",'Charge SlipBilling'!E:E) -> 4379551.2 | D4: =B4/B5 -> 0.48179511 | E4: =B8*D4 -> 1877742.3
A5: TOTAL | B5: =sum(B3:B4) -> 9090069.7 | D5: PGC Visayas Revenue
A6: Cancelled | B6: =SUMIF('Charge SlipBilling'!F:F, "Cancelled",'Charge SlipBilling'!E:E) -> 2420707.9 | D6: Income as of December 31, 2024 | E6: 3621502.7
A7: Processing | B7: =SUMIF('Charge SlipBilling'!F:F, "Processing",'Charge SlipBilling'!E:E) -> 2771974.2 | D7: Income January 2025 - September 15, 2025 | E7: =(sum('Charge SlipBilling'!E96,'Charge SlipBilling'!E98:E141)*60%) -> 1001143.6 | F7: =sum('Charge SlipBilling'!E124:E142) -> 889545.25
B8: =B5-(B6+B7) -> 3897387.7 | D8: TOTAL REVENUE | E8: =SUM(E6:E7) -> 4622646.3
A9: Expenses as of July 1, 2025 | B9: 524686.04 | D9: % Increase | E9: =E7/E6 -> 0.27644425
B10: =B8-B9 -> 3372701.6

Sheet Project Records_v1
A1: Client Name | B1: Client ID Number | D1: Sex | E1: Date Started | F1: Date Ended | G1: STATUS | H1: Project Number | J1: Tag (Client Surname_Project Acronym and/or_Organism) | K1: Project Title | L1: Sending Institution | M1: Funding Category | N1: Funding | O1: Service Requested | P1: Service Details | Q1: Equipment Used | R1: Omics Personnel | S1: Project Design to Implementation | T1: LEGEND:
A2: PGC VISAYAS | B2: CL-2019- | C2: 0 | E2: 43525 | G2: Ongoing | H2: P-2019- | I2: 0 | J2: PGCV | K2: PGC VISAYAS SATELLITE FACILITY | L2: Government | M2: In-House | N2: DOST | S2: No
A3: Rema C. Sibonga | B3: CL-2020- | C3: 10 | D3: F | E3: 43903 | F3: 44196 | G3: Completed | H3: P-2020- | I3: 1 | J3: GSStar | K3: Global Seaweed STAR Project | L3: UP System | M3: External | N3: UK Research and Innovation - Global Challenges Research Fund (UKRI-GCRF) | O3: Equipment Use | P3: Equipment Use - Omics Lab | Q3: MultiSkan Sky, Qubit, Bio-Rad T100, Mupid One, Bio-Rad Gel Doc, Thomas Scientific Q700, Heidolph Unimax 1010, KF Duo Prime, Pipettors | R3: Carmel | S3: No | T3: Black | U3: Ongoing Project
A4: Karen Claire S. Ebreo | B4: CL-2020- | C4: 11 | D4: F | E4: 43903 | F4: 44408 | G4: Completed | H4: P-2020- | I4: 2 | J4: TBI | K4: Taklong Barcoding Initiative | L4: UP System | M4: External | N4: EIDR | O4: Equipment Use | P4: Equipment Use - Omics Lab | Q4: Bio-Rad T100, MS Sky | R4: Carmel | S4: No | T4: Green | U4: Completed Project
A5: Loina Henzel A. Delgado | B5: CL-2020- | C5: 23 | D5: F | L5: UP System | S5: No | T5: Red | U5: Cancelled Project
A6: Angel Queenee D. Dequito | B6: CL-2020- | C6: 13 | D6: F | E6: 43990 | F6: 44316 | G6: Completed | H6: P-2020- | I6: 3 | J6: TGMPPEFET | K6: Transcriptome and Gut Metagenome Profile of Penaeus vannamei Exposed to Fluctuating Environmental Temperatures | L6: UP System | M6: External | N6: DOST-PCAARRD | O6: Equipment Use | P6: Equipment Use - Omics Lab | Q6: MultiSkan Sky, Qubit, Mupid One, Bio-Rad Gel Doc, Sartorius balance, CHC Laminar Flow, Pipettors | R6: Jasmine | S6: No
A7: Kyle R. Castañares | B7: CL-2020- | C7: 12 | D7: M | L7: UP System | P7: Equipment Use - Omics Lab | S7: No
A8: Mary Antonette F. Atilano | B8: CL-2020- | C8: 8 | D8: F | L8: UP System | P8: Equipment Use - Omics Lab | S8: No | T8: Assigned to:
A9: Nadalene Faith N. Cartago | B9: CL-2020- | C9: 14 | D9: F | E9: 44015 | F9: 44347 | G9: Completed | H9: P-2020- | I9: 4 | J9: Cartago | K9: Transcriptional Response of Selected Genes of the Green Mussel (Perna viridis) Exposed to Heat Stress | L9: UP System | M9: External | N9: DOST-ASTHRDP | O9: Equipment Use | P9: Equipment Use - Omics Lab | Q9: Bio-Rad T100, Mupid One, Bio-Rad Gel Doc, Pipettors, Minifuge | R9: Carmel | S9: No | U9: Ma. Carmel F. Javier
A10: Karl Angelo P. Tenizo | B10: CL-2020- | C10: 15 | D10: M | E10: 44034 | F10: present | G10: Ongoing | H10: P-2020- | I10: 5 | J10: Ice-Ice Transcriptomics | K10: Transcriptome and metabolome profiling of seaweeds to elucidate "ice-ice" disease and epiphyte infestation mechanisms | L10: UP System | M10: External | N10: DOST-PCAARRD | O10: Equipment Use | P10: Equipment Use - Omics Lab | Q10: MultiSkan Sky, Qubit, Bio-Rad Gel Doc, Mupid One, Pipettoors, Minifuge | R10: Carmel | S10: No | U10: Jasmine C. Velo
A11: Denise V. Miranda | B11: CL-2020- | C11: 24 | D11: F | L11: UP System | R11: Jasmine | S11: No | U11: Marj Gem B. Bunda-Fajunio
A12: Gabrielle Troy A. Cuevas | B12: CL-2020- | C12: 16 | D12: M | E12: 44034 | F12: 44742 | G12: Completed | H12: P-2020- | I12: 6 | J12: Cuevas | K12: Purification and Characterization of Linamarase from Lakan-1 and Java Variety Cassava (Manihot esculenta Crantz) | L12: UP System | M12: External | N12: UPV In-House Project | O12: Equipment Use | P12: Equipment Use - Omics Lab | Q12: Bio-Rad Mini Protean, Bio-Rad Gel Doc, Pipettors | R12: Carmel | S12: No | U12: Nadelene Faith N. Cartago
A13: Wilson F. Medrocillo | B13: CL-2020- | C13: 17 | D13: M | L13: UP System | P13: Equipment Use - Omics Lab | S13: No | U13: PGCV Omics Lab Team
A14: Leonila F. Endoma | B14: CL-2020- | C14: 18 | D14: M | E14: 44035 | F14: N/A | G14: Cancelled | H14: P-2020- | I14: 7 | J14: Endoma | K14: Instructional videos for Fish 111, Fish 236, Fish 238, Fish 321 | M14: External | P14: Equipment Use | Q14: MultiSkan Sky | R14: Jasmine | S14: No
A15: Dominique P. Mediodia | B15: CL-2020- | C15: 19 | D15: M | E15: 44048 | F15: 44620 | G15: Completed | H15: P-2020- | I15: 8 | J15: Panay Marfish Project | K15: Marine Fisheries Assessment of Panay: Building Local Fisheries Information through Research Capability Enhancement on Higher Education Insitutions | L15: UP System | M15: External | N15: CHED | O15: Equipment Use | P15: Equipment Use - Omics Lab | Q15: Bio-Rad T100, Mupid One, Bio-Rad Gel Doc, Pipettors, Microwave, Balance | R15: Jasmine | S15: No
A16: Ma. Novem Grace Ylayron | B16: CL-2020- | C16: 20 | D16: F | P16: Equipment Use - Omics Lab | S16: No
A17: Carmelo del Castillo | B17: CL-2020- | C17: 21 | D17: M | P17: Equipment Use - Omics Lab | S17: No
A18: Pretty Lee Silva | B18: CL-2020- | C18: 22 | D18: F | E18: 44062 | F18: N/A | G18: Cancelled | H18: P-2020- | I18: 9 | J18: Silva | K18: MS in Chemical Engineering | P18: Operations Observation | Q18: N/A | R18: Marj | S18: No
A19: Leni G. Yap-Dejeto | B19: CL-2021- | C19: 27 | D19: F | E19: 44250 | F19: 44377 | G19: Completed | H19: P-2021- | I19: 10 | J19: Glycogen | K19: c/o UP Visayas Tacloban College | L19: SUC/HEI | M19: External | O19: Laboratory Service | P19: Nucleic Acid Extraction and Quantification | Q19: DNA Extraction through Purelink Genomic DNA Kit; Qubit Fluorometry, MultiSkan Sky Spectrophotometry | R19: Jasmine | S19: No
A20: Dianne Frances Penuela | B20: CL-2021- | C20: 28 | D20: F | E20: 44280 | F20: 44882 | G20: Completed | H20: P-2021- | I20: 11 | J20: DNA Barcoding | K20: DNA barcoding of fishes from Western Visayas, Philippines | L20: UP System | M20: External | N20: CHED | O20: Equipment Use | P20: Equipment Use - Omics Lab | Q20: Bio-Rad T100, Mupid One, Bio-Rad Gel Doc, Heraus Pico 17, Sartorius analytical balance, Pipettors | R20: Carmel | S20: No
A21: Roxanne Cabebe | B21: CL-2021- | C21: 29 | D21: F | S21: No
A22: Albert C. Noblezada | B22: CL-2021- | C22: 30 | D22: M | E22: 44302 | F22: 44681 | G22: Completed | H22: P-2021- | I22: 12 | J22: Noblezada | K22: Population Structure of Green Mussel (Perna viridis) in Panay Island, Philippines using D-loop Sequences | L22: UP System | M22: External | N22: DOST-ASTHRDP Thesis Grant | O22: Equipment Use | P22: Equipment Use - Omics Lab | Q22: Bio-Rad T100, Mupid One, Bio-Rad Gel Doc, Heraus Pico 17, Sartorius analytical balance, Pipettors | R22: Carmel | S22: No
A23: Arlene L . Avillanosa | B23: CL-2021- | C23: 31 | D23: F | E23: 44334 | F23: present | G23: Ongoing | H23: P-2021- | I23: 13 | J23: GeM-PHIL | K23: Genetic Characterization of Macrobrachium populations in the Philippines for broodstock development and seed production | L23: SUC/HEI | M23: External | N23: DOST-PCAARRD | O23: Laboratory Service | P23: Nucleic Acid Extraction, Nucleic Acid Quantification, PCR, PCR Product Purification, Sequencing | Q23: N/A | R23: Omics Lab Team | S23: Yes
A24: Reymart S. Dagaraga | B24: CL-2021- | C24: 32 | D24: M | Q24: N/A | S24: Yes
A25: Jasper D. Pacho | B25: CL-2021- | C25: 33 | D25: M | Q25: N/A | S25: Yes
A26: Kristina Samantha Lacson | B26: CL-2021- | C26: 34 | D26: F | E26: 44382 | F26: 44553 | G26: Completed | H26: P-2021- | I26: 14 | J26: Calamansi Project | K26: Pre-commercialization of Microwave Extracted Pectin from Waste Calamansi Peels | L26: UP System | M26: External | N26: CHED | O26: Retail Sales | P26: Retail Sales - Liquid Nitrogen | Q26: N/A | R26: Nadelene
A27: Concepcion Ponce | B27: CL-2021- | C27: 35 | D27: F | P27: Retail Sales - Liquid Nitrogen | Q27: N/A
A28: Carolyn T. Mejares | B28: CL-2021- | C28: 36 | D28: F | E28: 44435 | F28: N/A | G28: Cancelled | H28: P-2021- | I28: 15 | J28: Mejares | K28: Effect of high temperature treatments on buffalo milk and buffalo bovine milk blends | P28: Equipment Use | Q28: Bio-Rad Mini Protean, Bio-Rad Gel Doc, Pipettors | R28: Jasmine | U28: Bioinfo Lab Team
A29: Rowena E. Cadiz | B29: CL-2022- | C29: 37 | D29: F | E29: 44579 | F29: N/A | G29: Cancelled | H29: P-2022- | I29: 16 | J29: AquaFeed | K29: Development of immunoactive and growth promoting AquaFeed additive from Ulva seaweed | N29: DOST-PCAARRD | P29: Equipment Use | Q29: CFX 96 Real Time PCR System | R29: Jasmine | U29: Julia Regalado
A30: Eric Zeus C. Rizo | B30: CL-2022- | C30: 38 | D30: M | E30: 44622 | F30: present | G30: Completed | H30: P-2022- | I30: 17 | J30: PFZ | K30: Development of a Water Quality Biological Monitoring Protocol using Genetic, Phylogenetic and Functional Diversity on Freshwater Zooplankton Communitites in Inland Waters of Panay Island, Philippines | L30: UP System | M30: External | N30: DOST-PCIEERD | O30: Equipment Use | P30: Equipment Use - Omics Lab | Q30: Qubit 4.0, Bio-Rad T100, Mupid One, Bio-Rad Gel Doc, Heraeus Picoo 17, Heidlph Unimax 1010, Sartorius analytical balance, -20 Freezer | R30: Carmel | U30: Chrstine Florece
A31: Shea Kathleen P. Guinto | B31: CL-2022- | C31: 39 | D31: F | U31: Karl Angelo Tenizo
A32: Rother M. Gaudiel | B32: CL-2022- | C32: 40 | D32: M | E32: 44622 | F32: 44865 | G32: Completed | H32: P-2022- | I32: 18 | J32: R Gaudiel | K32: Fishery and Some Aspects on the Biology and Ecology of the Sergestid Shrimp, Acetes, in Miagao, Iloilo | L32: UP System | M32: External | N32: DOST-ASTHRDP Thesis Grant | O32: Equipment Use | P32: Equipment Use - Omics Lab | Q32: Bio-Rad T100, Mupid One, Bio-Rad Gel Doc, Thermo Scientific Fresco 17 | R32: Nadelene | U32: Albert Noblezada
A33: John Rey F. Rasgo | B33: CL-2022- | C33: 41 | D33: M | E33: 44624 | F33: 44687 | G33: Completed | H33: P-2022- | I33: 19 | J33: JR Rasgo | K33: Genetic Marker Assessment of 12s and 18s of Kappaphycus striatus collected in Palawan | L33: UP System | M33: External | N33: c/o Global Seaweed STAR Project | O33: Equipment Use | P33: Equipment Use - Omics Lab | Q33: Bio-Rad T100, Mupid One, Elma Easy 300H, Thermo Scientific Fresco 17, Operon ULTF | R33: Nadelene
A34: Luke Dranoel D. Atencio | B34: CL-2022- | C34: 42 | D34: M | E34: 44628 | F34: 44986 | G34: Completed | H34: P-2022- | I34: 20 | J34: LD Atencio | K34: ESKAPE Pathogens in Intensive Care Unit from a Tertiary Healthcare Setting | L34: UP System | M34: Internal | N34: N/A | O34: Equipment Use | P34: Equipment Use - Omics Lab | R34: Jasmine
A35: Whelver N. Surnido | B35: CL-2022- | C35: 43 | D35: M | E35: 44634 | F35: 44687 | G35: Completed | H35: P-2022- | I35: 21 | J35: WNSurnido | K35: Dynamics of the Epibacterial Community Structure and Composition of Kappaphycus alvarezii in Response to Thermal-induced Ice-ice Disease | L35: UP System | M35: External | N35: c/o Ice-ice Project | O35: Equipment Use | P35: Equipment Use - Omics Lab | Q35: Qubit 4.0, Bio-Rad T100, Mupid One, Bio-Rad Gel Doc, Heraeus Picoo 17, Heidlph Unimax 1010, Sartorius analytical balance, -20 Freezer | R35: Jasmine
A36: Kingsley John de los Santos | B36: CL-2022- | C36: 44 | D36: M | E36: 44644 | F36: 44712 | G36: Completed | H36: P-2022- | I36: 22 | J36: KDSantos | K36: Assessment of Anthropogenic Marine Debris and Mangrove Forest Health in Iloilo Strait, Western Visayas, Philippines | L36: UP System | M36: External | N36: DOST-ASTHRDP Thesis Grant | O36: Retail Sales | P36: Retail Sales - Liquid Nitrogen | Q36: N/A | R36: Nadelene
A37: Karl C. Abismo | B37: CL-2022- | C37: 45 | D37: M | E37: 44645 | F37: 44727 | G37: Completed | H37: P-2022- | I37: 23 | J37: KCAbismo | K37: Assessment of Antimicrobial Activitiy of Selected Fungi from Tilapia Greenwater Technology Against Vibrio parahaemolyticus in Blood Cockle, Anadara granosa | L37: UP System | M37: External | N37: DOST Thesis Grant | O37: Equipment Use | P37: Equipment Use - Omics Lab | Q37: Bio-Rad T100, Mupid One, Bio-Rad Gel Doc, Incubator, Biosafety Cabinet, Microcentrifuges | R37: Jasmine
A38: Benedict Maralit | B38: CL-2022- | C38: 47 | D38: M | E38: 44680 | F38: 45016 | G38: Completed | H38: P-2022- | I38: 24 | J38: Retrospective Biosurveillance | K38: Sequencing and Analysis of SARS-CoV-2 genomes in swab specimens collected by subnational / DOH-accredited COVID-19 laboratories in the Philippines from March to October 2020 | L38: UP System | M38: Internal | N38: PGC Visayas In-house | O38: Equipment Use | P38: Equipment Use - Omics Lab | Q38: Nucleic Acid Extraction and Quantification, PCR, Library Preparation, NGS | R38: Omics Lab Team
A39: Prof. Philip Alviola | B39: CL-2022- | C39: 48 | D39: M | E39: 44680 | F39: present | G39: Ongoing | H39: P-2022- | I39: 25 | J39: Bats | K39: Molecular detection of Henipa and Coronavirus in Flying Fox (Order Chiroptera: Family Pteropodidae) roost within First Gas Plant Site, Batangas City | L39: UP System | M39: Internal | N39: PGC Visayas In-house | O39: Equipment Use | P39: Equipment Use - Omics Lab | Q39: Nucleic Acid Extraction and Quantification, PCR, Library Preparation, NGS | R39: Omics Lab Team
A40: Persie Persie Mark Sienes | B40: CL-2023- | C40: 70 | D40: M | E40: 44682 | F40: present | G40: Ongoing | H40: P-2022- | I40: 26 | J40: PGCV_Deer WGS | K40: Whole Genome Sequencing of the Philippine spotted deer (Rusa alfredi) | L40: UP System | M40: Internal | N40: PGC Visayas In-house | O40: Laboratory Service | P40: NGS | Q40: Nucleic Acid Extraction and Quantification, PCR, Library Preparation, NGS | R40: Omics Lab Team | S40: Yes
A41: Beverly T. Jaspe | B41: CL-2022- | C41: 51 | D41: F | E41: 44682 | F41: 45229 | G41: Completed | H41: P-2022- | I41: 27 | J41: Pholas | K41: Genomic variations among different (meta) populations of oriental angelwing clam (Pholas orientalis) in the Western Visayas, Philippines: basis for conservation breeding program | L41: SUC/HEI | M41: External | N41: DOST-NRCP NSTEP | O41: Equipment Use | P41: Equipment Use - Omics Lab | Q41: Bio-Rad T100, Mupid One, Multiskan Sky Microplate Reader, Bio-Rad Gel Doc, Biosafety Cabinet, Microcentrifuges | R41: Carmel | S41: Yes
A42: Camille Rose T. Mueda | B42: CL-2022- | C42: 50 | D42: F | E42: 44718 | F42: 44926 | G42: Completed | H42: P-2022- | I42: 028-A | J42: Mueda | K42: Metagenomic Characterization of Oil-degrading Microbial Communities from Slipper-shaped Oyster (Magallana bilineata) in Oil-contaminated Areas along Iloilo Strait, Philippines | L42: UP System | M42: Internal | N42: PGC Visayas In-house | O42: Equipment Use | P42: Equipment Use - Omics Lab | Q42: Bio-Rad T100, Mupid One, Qubit 4.0, Agilent Bioanalyzer, Multiskan Sky Microplate Reader | R42: Carmel
G43: Completed | I43: 028-B | O43: Laboratory Service | P43: Bioinformatics Analysis | Q43: Metagenomics Analysis Pipeline | R43: Bioinfo Team
A44: Kneessa Louie G. Dato-on | B44: CL-2022- | C44: 53 | D44: F | E44: 44725 | F44: present | G44: Ongoing | H44: P-2022- | I44: 29 | J44: Thrausto | K44: Isolation, Characterization and Phylogenetic identification of Thraustochytrids from mangrove habitats around Panay Island, Philippines | L44: UP System | M44: Internal | N44: PGC Visayas In-house | O44: Equipment Use | P44: Equipment Use - Omics Lab | Q44: Bio-Rad T100, Mupid One, Multiskan Sky Microplate Reader, Bio-Rad Gel Doc, Incubator, Biosafety Cabinet, Microcentrifuges | R44: Jasmine
A45: Therese Javellana | B45: CL-2024- | C45: 161 | D45: F | O45: Equipment Use | P45: Equipment Use - Omics Lab | Q45: Bio-Rad T100, Mupid One, Multiskan Sky Microplate Reader, Bio-Rad Gel Doc, Incubator, Biosafety Cabinet, Microcentrifuges
A46: Zeth Rodario Bebit | B46: CL-2022- | C46: 52 | D46: M | E46: 44729 | F46: 44773 | G46: Completed | H46: P-2022- | I46: 30 | J46: Bebit | K46: Marine Fisheries Assessment of Panay: Building Local Fisheries Information through Research Capability Enhancement in HEIs Component 3: Chemical Composition of Marine Fishes – Leverage Research Project (SP20-14) | L46: UP System | M46: External | N46: CHED | O46: Equipment Use | P46: Equipment Use - Omics Lab | Q46: Gel Doc XR+ | R46: Nadelene
A47: Angel Queenee D. Dequito | B47: CL-2020- | C47: 13 | D47: F | E47: 44754 | F47: 44773 | G47: Completed | H47: P-2022- | I47: 31 | J47: TGMPPEFET | K47: Transcriptome and Gut Metagenome Profile of Penaeus vannamei Exposed to Fluctuating Environmental Temperatures | L47: UP System | M47: External | N47: DOST-PCAARRD | O47: Equipment Use | P47: Equipment Use/Bioinformatics Analysis | Q47: Workstation, Export Files to CSV for Client Use | R47: Bioinfo Team
A48: Rhudith Cabulong | B48: CL-2022- | C48: 55 | D48: F | E48: 44763 | F48: 45107 | G48: Completed | H48: P-2022- | I48: 32 | J48: Cabulong, (OM,CM) | K48: Diversity and screening of culturable cellulytic microorganisms from mangrove forests, natural parks, paddy field, and sugar plantation in Panay Island, Philippines | L48: UP System | M48: External | N48: UPV Regular In-House Research (RIR) | O48: Laboratory Service | P48: Equipment Use - Omics Lab and Micro Lab, NGS | Q48: Labconco BSC, ALP autoclave, Binder incubator, Multiskan Sky MIcroplate Reader, Amplicon Sequencing | R48: Jasmine
A49: Isabel Grace Gatpatan | B49: CL-2022- | C49: 49 | D49: F
A50: Rommel J. Gestuveo | B50: CL-2022- | C50: 60 | D50: M | E50: 44835 | F50: present | G50: Ongoing | H50: P-2022- | I50: 33 | J50: DeNoVac | K50: Development of Novel Antiviral Compounds against Arthropod-borne Viruses | L50: UP System | M50: External | N50: DOST-DST JRP | O50: Equipment Use | P50: Equipment Use - Omics Lab | Q50: Bio-rad T100, Bio-Rad CFX96, Mupid One, Bio-Rad Mini-Protean, Bio-Rad Gel Doc XR+, Refrigerated Microcentrifuge, Standard Microcentrifuge, Shaker Incubator, Julabo Water Bath, Sartorius Analytical, Liquid Nitrogen Tank and Generator, Storage Freezer, Ultralow Freezer, Vortex Mixer, Autoclave, Laminar Flow PCR Cabinet | R50: Carmel
A51: Frenche B. Hechanova | B51: CL-2022- | C51: 61 | D51: F
A52: Jade G. Pahila | B52: CL-2022- | C52: 62 | D52: F | E52: 44859 | F52: present | G52: Ongoing | H52: P-2022- | I52: 34 | J52: Microalgae | K52: Production and evaluation of Dried Microalgal Biomass for improved shelf life and product diversification | L52: UP System | M52: External | N52: DOST | O52: Equipment Use | P52: Equipment Use - Omics Lab | Q52: MultiSkan Sky Spectrophotometer, Thermo Scientific Fresco 17 Refrigerated Microcentrifuge,Heraeus Pico 17 Standard Microcentrifuge,Binder BD115 Incubator Cabinet, ESCO Biosafety Cabinet, loop sterilizer, minifuges | R52: Jasmine
A53: Cezarie L. Golingay | B53: CL-2022- | C53: 63 | D53: F
A54: Ella Marie E. Villaruz | B54: CL-2022- | C54: 64 | D54: F
A55: Antoniette Lorain Z. Dimaano | B55: CL-2022- | C55: 65 | D55: F
A56: Arnel Adrian Rara | B56: CL-2023- | C56: 76 | D56: M | P56: Equipment Use - Omics Lab | Q56: Orbital shaker
A57: Pauline Anne Lamela | B57: CL-2022- | C57: 66 | D57: F | E57: 44902 | F57: 45107 | G57: Completed | H57: P-2022- | I57: 35 | J57: Lamela | K57: Isolation, Characterization, And Identification of Plastic-Degrading Bacteria From Bago City Landfill, Negros Occidental, Philippines | L57: UP System | M57: External | O57: Laboratory Service | P57: NAE, PCR, Cappilary Sequencing | Q57: Analytical Balance (Sartorious); Electrophoresis System | R57: Nadelene
A58: Raymond Cabarles | B58: CL-2022- | C58: 67 | D58: M | E58: 44910 | F58: 45069 | G58: Completed | H58: P-2022- | I58: 36 | J58: Cabarles et al | K58: MS Aqua Fish 219 (Advanced Genetics) | L58: UP System | M58: Internal | O58: Laboratory Service | P58: NGS - 16s | Q58: N/A | R58: Jasmine
A59: Emelyn Joy Mameloco | B59: CL-2022- | C59: 68 | D59: F
A60: Edcel T. Resano | B60: CL-2022- | C60: 69 | D60: F
A61: Dr. Zayda Halun | B61: CL-2023- | C61: 71 | D61: F | E61: 44964 | F61: present | G61: Ongoing | H61: P-2023- | I61: 37 | J61: Halun | K61: Amplicon Sequencing of Seaweed | L61: SUC/HEI | M61: External | N61: MSU TCTO | O61: Laboratory Service | P61: NGS - Amplicon Seq | Q61: N/A | R61: Nadelene
A62: PGC Visayas | B62: CL-2019- | C62: 000 | E62: 44993 | F62: 45069 | G62: Completed | H62: P-2023- | I62: 38 | J62: Dugong - Miagao | K62: Molecular identification of Dugong (Batch 1) | L62: UP System | M62: Internal | N62: PGC Visayas In-house | O62: Laboratory Service | R62: Nadelene
A63: Elsie Y. Guibone | B63: CL-2022- | C63: 59 | D63: F | E63: 44999 | F63: 45199 | G63: Completed | H63: P-2023- | I63: 39 | J63: Lernaea | K63: Fish 258 - Marine Biotechnology: Identification of Lernaea using 18s primers | L63: UP System | M63: Internal | N63: PGC Visayas In-house | O63: Equipment Use | P63: Equipment Use - Omics Lab | Q63: Bio-Rad T100, Mupid One, Multiskan Sky Microplate Reader, Bio-Rad Gel Doc, Incubator, Biosafety Cabinet, Microcentrifuges | R63: Carmel
A64: Claire Samantha Juanico | B64: CL-2023- | C64: 77 | D64: F
A65: Claire Samantha Juanico | B65: CL-2023- | C65: 77 | D65: F | E65: 44999 | F65: present | G65: Ongoing | H65: P-2023- | I65: 40 | J65: Fish Gut | K65: Gut Metabarcoding | L65: UP System | M65: Internal | N65: PGC Visayas In-house | O65: Equipment Use | P65: Equipment Use - Omics Lab | Q65: Bio-Rad T100, Mupid One, Multiskan Sky Microplate Reader, Bio-Rad Gel Doc, Incubator, Biosafety Cabinet, Microcentrifuges | R65: Jasmine
A66: Rose Ann Lumapan | B66: CL-2023- | C66: 79 | D66: F | E66: 45007 | F66: 45072 | G66: Completed | H66: P-2023- | I66: 41 | J66: Lumapan | K66: Real-time PCR Detection of Foodborne Pathogens in Oyster from local markets in Iloilo | L66: UP System | M66: Internal | N66: N/A | O66: Equipment Use | P66: Equipment Use - Omics Lab | Q66: qPCR, PCR Cabinet, Minifuge, Micropipettors | R66: Nadelene
A67: Karmelie Jane Monaya | B67: CL-2023- | C67: 80 | D67: F
A68: Beatrice L. Anacita | B68: CL-2023- | C68: 81 | D68: F | E68: 45035 | F68: 45083 | G68: Completed | H68: P-2023- | I68: 42 | J68: Anacita | K68: Bacterial Biofilm Formation and Inhibition Potential of Wild Macrofungi from Miagao, Iloilo | L68: UP System | M68: External | N68: N/A | O68: Equipment Use | P68: Equipment Use - Micro | Q68: Multiskan Sky, Binder Incubator, Biosafety Cabinet, Loop Sterilizer, Autoclave, Micropipettors | R68: Jasmine
A69: Kyla Julienne P. Talaman | B69: CL-2023- | C69: 82 | D69: F | E69: 45035 | F69: 45083 | G69: Completed | H69: P-2023- | I69: 43 | J69: Talaman | K69: Prebiotic potential of Beta-glucan extracted from macrofungu found in Miagao, Iloilo | L69: UP System | M69: External | N69: N/A | O69: Equipment Use | P69: Equipment Use - Micro | Q69: Multiskan Sky, Binder Incubator, Biosafety Cabinet, Loop Sterilizer, Autoclave, Micropipettors | R69: Jasmine
A70: Trisha Marie Santos | B70: CL-2023- | C70: 83 | D70: F | E70: 45036 | F70: 45083 | G70: Completed | H70: P-2023- | I70: 44 | J70: Santos | K70: Antimicrobial Resistance Profigel of P aeroginosa Environmental Isolates from Iloilo River, Iloilo City | L70: UP System | M70: External | N70: N/A | O70: Equipment Use | P70: Equipment Use - Micro | Q70: Multiskan Sky, Binder Incubator, Biosafety Cabinet, Loop Sterilizer, Autoclave, Micropipettors | R70: Jasmine
A71: Trisha Catalya | B71: CL-2023- | C71: 84 | D71: F | E71: 45051 | F71: 45079 | G71: Completed | H71: P-2023- | I71: 45 | J71: Catalya | K71: Detection of E. coli and Salmonella using Culture-Independent Methods in Spiked Oyster Ostreidaei | L71: UP System | M71: Internal | N71: N/A | O71: Equipment Use | P71: Equipment Use - Omics Lab | Q71: qPCR, PCR Cabinet, Minifuge, Micropipettors | R71: Nadelene
A72: Josie Mar G. Cabalo | B72: CL-2023- | C72: 85 | D72: F | E72: 45051 | F72: 45079 | G72: Completed | H72: P-2023- | I72: 46 | J72: Cabalo | K72: Detection of Vibrio parahaemolyticus and Vibrio cholerae in Oyster using Quantitative Real-Time Polymerase Chain Reaction (qPCR) | L72: UP System | M72: Internal | O72: Equipment Use | P72: Equipment Use - Omics Lab | Q72: qPCR, PCR Cabinet, Minifuge, Micropipettors | R72: Nadelene
A73: Carlo S. Gregorio | B73: CL-2023- | C73: 86 | D73: M | E73: 45062 | F73: 45107 | G73: Completed | H73: P-2023- | I73: 47 | J73: LN - Gregorio, Sibulan | K73: Characterization Of Picophytoplankton Abundance And Distribution In Relation To Varying Environmental Conditions In The Bay Zone Of The Batan Bay Estuary | L73: UP System | M73: External | N73: DOST-ASTHRDP | O73: Retail Sales | P73: Retail Sales - Liquid Nitrogen | Q73: N/A | R73: Nadelene
A74: Elize Margareth C. Sibulan | B74: CL-2023- | C74: 87 | D74: F | K74: Picophytoplankton Community Structure and Responses to Physicochemical Variations in the Back-Barrier Zone of Batan Bay Estuary | L74: UP System | M74: External | P74: Retail Sales - Liquid Nitrogen
A75: Ella Marie Kristine Baldove | B75: CL-2023- | C75: 91 | D75: F | E75: 45082 | F75: 45229 | G75: Completed | H75: P-2023- | I75: 48 | J75: Feedmix | K75: Molecular identification of microalgae | L75: Private Local | M75: Internal | N75: PGC Visayas In-house | O75: Laboratory Service | P75: NAE, PCR, Capillary Sequencing | Q75: N/A | R75: Carmel
A76: Abigail F. Padua | B76: CL-2023- | C76: 88 | D76: F | E76: 45083 | F76: 45107 | G76: Completed | H76: P-2023- | I76: 49 | J76: LN - Padua | K76: The effect of fermented silage on sperm quality of mixed-breed anglo nubian goats in Romblon | L76: UP System | M76: External | N76: N/A | O76: Retail Sales | P76: Retail Sales - Liquid Nitrogen | Q76: N/A | R76: Marj
A77: Rachel A. Casio | B77: CL-2023- | C77: 89 | D77: F | E77: 45083 | F77: 45229 | G77: Completed | H77: P-2023- | I77: 50 | K77: Molecular identification of Warty Pig and Hawk Eagle | L77: UP System | M77: Internal | N77: PGC Visayas In-house | O77: Laboratory Service | P77: NAE, PCR, NGS - Amplicon Seq | Q77: N/A | R77: Nadelene
A78: Jojie P. Gereza | B78: CL-2023- | C78: 90 | D78: F | P78: NAE, PCR, NGS - Amplicon Seq
A79: Ma Jowina Galarion | B79: CL-2023- | C79: 92 | D79: F | E79: 45091 | F79: 45199 | G79: Completed | H79: P-2023- | I79: 51 | J79: Dengue Seq | K79: Assessing the feasibility of implementing field deployable sequencing applied to dengue virus surveillance in the Philippines | L79: International | M79: External | N79: Medical Research Council - University of Glasgow Centre for Virus Research | O79: Equipment Use | P79: Equipment Use - Omics Lab | Q79: Bench space, Micropipettors, Biosafety Cabinet | R79: Carmel
A80: Mark Calabon | B80: CL-2023- | C80: 96 | D80: M | E80: 45119 | F80: present | G80: Ongoing | H80: P-2023- | I80: 52 | J80: AQFP (Calabon-Fungi) | K80: Unraveling the Hidden Diversity of Aquatic Fungi from Panay Island, Philippines Project | L80: UP System | M80: External | N80: DOST | O80: Laboratory Service | P80: Equipment Use, NAE, PCR, NGS - Amplicon Seq | R80: Jasmine
A81: James Nim | B81: CL-2023- | C81: 97 | D81: M
A82: Jan Felnesh Exe Bagacay | B82: CL-2023- | C82: 115 | D82: F | E82: 45209
A83: Sheryll Mesa | B83: CL-2023- | C83: 98 | D83: F | E83: 45125 | F83: 45229 | G83: Completed | H83: P-2023- | I83: 53 | J83: BFAR Sperm Whale | K83: Molecular identification of Kogiid whale stranded in Sicogon Island, Carles, Iloilo | L83: Government | M83: Internal | N83: PGC Visayas In-house | O83: Laboratory Service | P83: NAE, PCR, NGS - Amplicon Seq | Q83: N/A | R83: Nadelene
A84: Krshna Mahakaola A. Dueñas | B84: CL-2023- | C84: 100 | D84: F | E84: 45140 | F84: 45149 | G84: Completed | H84: P-2023- | I84: 54 | J84: LN - Dueñas | K84: Effects of Crown-of-Thorns (Acanthaster planci) Starfish as a Growth Enhacer in White Mice (Mus musculus) | L84: SUC/HEI | M84: External | N84: N/A | O84: Retail Sales | P84: Retail Sales - Liquid Nitrogen | Q84: N/A | R84: Marj
A85: Franco MIguel N. Nodado | B85: CL-2023- | C85: 101 | D85: M | E85: 45154 | F85: 45301 | G85: Completed | H85: P-2023- | I85: 55 | J85: V. cholerae (WVSU) | K85: Inhibitory Activity of Vitex negundo (Lagundi) Leaf Extract Against Biofilm Formation and Quorom Sensing of Vibrio cholerae | L85: SUC/HEI | M85: External | N85: N/A | O85: Laboratory Service | P85: NAE, PCR, qPCR | Q85: N/A | R85: Jasmine
A86: Danielle L. Elevado | B86: CL-2023- | C86: 102 | D86: F
A87: Yoo Ki Bastol | B87: CL-2023- | C87: 103 | D87: F
A88: Zeb Jose Joshua C. Cabalfin | B88: CL-2023- | C88: 104 | D88: M
A89: Maio Vendell V. Sabidong | B89: CL-2023- | C89: 105 | D89: M
A90: Jemma Dawn C. Leonardo | B90: CL-2023- | C90: 106 | D90: F
A91: Leopoldo T. Bacquial II | B91: CL-2023- | C91: 107 | D91: M
A92: Kathleen Mae V. Donoso | B92: CL-2023- | C92: 108 | D92: F
A93: Nove Kris B. Herida | B93: CL-2023- | C93: 109 | D93: F
A94: Angel Mae T. Malones | B94: CL-2023- | C94: 110 | D94: F
A95: Adrienne Marrie S. Bugayon-Janagap | B95: CL-2023- | C95: 111 | D95: F
A96: Stephen G. Sabinay | B96: CL-2022- | C96: 46 | D96: M
A97: Joseph Faisan | B97: CL-2023- | C97: 112 | D97: M | E97: 45167 | F97: 45189 | G97: Completed | H97: P-2023- | I97: 56 | J97: SEAFDEC (Eel) | K97: Fish Species ID | L97: International | M97: External | N97: N/A | O97: Laboratory Service | P97: NAE, PCR, NGS | Q97: N/A | R97: Carmel
A98: Nadine Belas | B98: CL-2023- | C98: 113 | D98: F | E98: 45180 | F98: present | G98: Completed | H98: P-2023- | I98: 57 | J98: Kapis | K98: The Complete Mitogenome of Placuna placenta and its Phylogenetic Implications | L98: UP System | M98: Internal | N98: N/A | O98: Equipment Use | P98: Equipment Use | Q98: N/A | R98: Marj
A99: Maureen Emily V. Niño | B99: CL-2023- | C99: 114 | D99: F | E99: 45190 | F99: present | G99: Ongoing | H99: P-2023- | I99: 58 | J99: KIOST | K99: Diversity assessment of freshwater zooplankton and macroinvertebrates towards identification of centers of biodiversity conservation in the Jalaur River Basin, Iloilo, Philippines | L99: UP System | M99: External | N99: OVPAA Balik PhD | O99: Equipment Use | P99: Equipment Use, CS | Q99: N/A | R99: Carmel
A100: Eric Zeus C. Rizo | B100: CL-2022- | C100: 38 | D100: M
...

Sheet STATS Summary
A1: As of July 31, 2024 | C1: Funding
C2: Internal | D2: External | E2: Equipment Use | F2: Laboratory Service | G2: Retail Sales | H2: UP System | I2: SUCs/HEIs | J2: Gov't Agencies | K2: Private Local | L2: International
A3: Ongoing | B3: =COUNTIF('Project Records_v1'!G2:G1042,"ongoing") -> 33
A4: Completed | B4: =countif('Project Records_v1'!G2:G1042, "completed") -> 70
A5: Cancelled | B5: =COUNTIF('Project Records_v1'!G2:G1042,"cancelled") -> 5
A6: Total | B6: =sum(B3:B5) -> 108 | C6: =countif('Project Records_v1'!M:M,"Internal") -> 32 | D6: =countif('Project Records_v1'!M:M,"External") -> 69 | E6: =countif('Project Records_v1'!O:O, "equipment use") -> 51 | F6: =countif('Project Records_v1'!O:O,"Laboratory Service") -> 45 | G6: =countif('Project Records_v1'!O:O,"retail sales") -> 7 | H6: =countif('Project Records_v1'!L:L,"UP System") -> 76 | I6: =countif('Project Records_v1'!L:L,"SUC/HEI") -> 21 | J6: =countif('Project Records_v1'!L:L,"Government") -> 6 | K6: =countif('Project Records_v1'!L:L,"Private local") -> 1 | L6: =countif('Project Records_v1'!L:L,"International") -> 3
F8: As of July 31, 2024
B9: 2020 | C9: 2021 | D9: 2022 | E9: 2023 | F9: 2024 | G9: Overall Total
A10: CLIENTS
A11: Completed | B11: 20 | C11: 8 | D11: 24 | E11: 41 | F11: 10 | G11: 103
A12: Ongoing | B12: 2 | C12: 3 | D12: 9 | E12: 16 | F12: 13 | G12: 43
A13: Cancelled | B13: 2 | C13: 1 | D13: 1 | E13: 1 | F13: 0 | G13: 5
A14: Total Clients | B14: 24 | C14: 12 | D14: 34 | E14: 58 | F14: 23 | G14: 151
A16: PROJECTS
A17: Completed | B17: =countif('Project Records_v1'!G3:G18, "completed") -> 6 | C17: =countif('Project Records_v1'!G19:G28, "completed") -> 4 | D17: =countif('Project Records_v1'!G29:G60, "completed") -> 16 | E17: =countif('Project Records_v1'!G61:G106, "completed") -> 21 | F17: =countif('Project Records_v1'!G107:G151, "completed") -> 22 | G17: =sum(B17:F17) -> 69
A18: Ongoing | B18: =countif('Project Records_v1'!G2:G18, "Ongoing") -> 2 | C18: =countif('Project Records_v1'!G19:G28,"ongoing") -> 1 | D18: =countif('Project Records_v1'!G29:G60,"ongoing") -> 5 | E18: =countif('Project Records_v1'!G61:G106,"ongoing") -> 5 | F18: =countif('Project Records_v1'!G107:G151,"ongoing") -> 10 | G18: =sum(B18:F18) -> 23
A19: Cancelled | B19: =countif('Project Records_v1'!G5:G20, "cancelled") -> 2 | C19: =countif('Project Records_v1'!G19:G28, "cancelled") -> 1 | D19: =countif('Project Records_v1'!G29:G60, "cancelled") -> 1 | E19: =countif('Project Records_v1'!G61:G106, "cancelled") -> 1 | F19: =countif('Project Records_v1'!G107:G151, "cancelled") -> 0 | G19: =sum(B19:F19) -> 5
A20: Total Projects | B20: =sum(B17:B19) -> 10 | C20: =sum(C17:C19) -> 6 | D20: =sum(D17:D19) -> 22 | E20: =sum(E17:E19) -> 27 | F20: =sum(F17:F19) -> 32 | G20: =sum(G17:G19) -> 97
A22: TRAINING REQUESTS
A23: Completed | B23: 1 | C23: 3 | D23: 4 | E23: 6 | F23: 1 | G23: =sum(B23:F23) -> 15

Sheet DASHBOARD
A1: Year | B1: CLIENTS | C1: PROJECTS | E1: Year | F1: PGC Visayas Funded | G1: External | I1: Year | J1: Laboratory Service | K1: Equipment Use | L1: Retail Sales | N1: Year | O1: UP System | P1: SUC/HEI | Q1: Gov't Agencies | R1: Private Local | S1: International
A2: 2019 | B2: =countif('Client ID Records_v2'!A:A, "2019") -> 1 | C2: 1 | E2: 2019 | F2: =COUNTIFS('Project Records_v2'!A:A,"2019",'Project Records_v2'!K:K,"In-House") -> 1 | G2: =COUNTIFS('Project Records_v2'!A:A,"2019",'Project Records_v2'!K:K,"External") -> 0 | I2: 2019 | J2: =COUNTIFS('Project Records_v2'!A:A,"2019",'Project Records_v2'!M:M,"Laboratory Services") -> 0 | K2: =COUNTIFS('Project Records_v2'!A:A,"2019",'Project Records_v2'!M:M,"Equipment Use") -> 0 | L2: =COUNTIFS('Project Records_v2'!A:A,"2019",'Project Records_v2'!M:M,"Retail Sales") -> 0 | N2: 2019 | O2: =COUNTIFS('Project Records_v2'!A:A,"2019",'Project Records_v2'!J:J,"UP System") -> 0 | P2: =COUNTIFS('Project Records_v2'!A:A,"2019",'Project Records_v2'!J:J,"SUC/HEI") -> 0 | Q2: =COUNTIFS('Project Records_v2'!A:A,"2019",'Project Records_v2'!J:J,"Government") -> 0 | R2: =COUNTIFS('Project Records_v2'!A:A,"2019",'Project Records_v2'!J:J,"Private/Local") -> 0 | S2: =COUNTIFS('Project Records_v2'!A:A,"2019",'Project Records_v2'!J:J,"International") -> 0
A3: 2020 | B3: 24 | C3: 9 | E3: 2020 | F3: =COUNTIFS('Project Records_v2'!A:A,"2020",'Project Records_v2'!K:K,"In-House") -> 0 | G3: =COUNTIFS('Project Records_v2'!A:A,"2020",'Project Records_v2'!K:K,"External") -> 9 | I3: 2020 | J3: =COUNTIFS('Project Records_v2'!A:A,"2020",'Project Records_v2'!M:M,"Laboratory Services") -> 0 | K3: =COUNTIFS('Project Records_v2'!A:A,"2020",'Project Records_v2'!M:M,"Equipment Use") -> 9 | L3: =COUNTIFS('Project Records_v2'!A:A,"2020",'Project Records_v2'!M:M,"Retail Sales") -> 0 | N3: 2020 | O3: =COUNTIFS('Project Records_v2'!A:A,"2020",'Project Records_v2'!J:J,"UP System") -> 9 | P3: =COUNTIFS('Project Records_v2'!A:A,"2020",'Project Records_v2'!J:J,"SUC/HEI") -> 0 | Q3: =COUNTIFS('Project Records_v2'!A:A,"2020",'Project Records_v2'!J:J,"Government") -> 0 | R3: =COUNTIFS('Project Records_v2'!A:A,"2020",'Project Records_v2'!J:J,"Private/Local") -> 0 | S3: =COUNTIFS('Project Records_v2'!A:A,"2020",'Project Records_v2'!J:J,"International") -> 0
A4: 2021 | B4: 12 | C4: 6 | E4: 2021 | F4: =COUNTIFS('Project Records_v2'!A:A,"2021",'Project Records_v2'!K:K,"In-House") -> 0 | G4: =COUNTIFS('Project Records_v2'!A:A,"2021",'Project Records_v2'!K:K,"External") -> 5 | I4: 2021 | J4: =COUNTIFS('Project Records_v2'!A:A,"2021",'Project Records_v2'!M:M,"Laboratory Services") -> 2 | K4: =COUNTIFS('Project Records_v2'!A:A,"2021",'Project Records_v2'!M:M,"Equipment Use") -> 2 | L4: =COUNTIFS('Project Records_v2'!A:A,"2021",'Project Records_v2'!M:M,"Retail Sales") -> 1 | N4: 2021 | O4: =COUNTIFS('Project Records_v2'!A:A,"2021",'Project Records_v2'!J:J,"UP System") -> 3 | P4: =COUNTIFS('Project Records_v2'!A:A,"2021",'Project Records_v2'!J:J,"SUC/HEI") -> 3 | Q4: =COUNTIFS('Project Records_v2'!A:A,"2021",'Project Records_v2'!J:J,"Government") -> 0 | R4: =COUNTIFS('Project Records_v2'!A:A,"2021",'Project Records_v2'!J:J,"Private/Local") -> 0 | S4: =COUNTIFS('Project Records_v2'!A:A,"2021",'Project Records_v2'!J:J,"International") -> 0
A5: 2022 | B5: 34 | C5: 21 | E5: 2022 | F5: =COUNTIFS('Project Records_v2'!A:A,"2022",'Project Records_v2'!K:K,"In-House") -> 5 | G5: =COUNTIFS('Project Records_v2'!A:A,"2022",'Project Records_v2'!K:K,"External") -> 16 | I5: 2022 | J5: =COUNTIFS('Project Records_v2'!A:A,"2022",'Project Records_v2'!M:M,"Laboratory Services") -> 5 | K5: =COUNTIFS('Project Records_v2'!A:A,"2022",'Project Records_v2'!M:M,"Equipment Use") -> 15 | L5: =COUNTIFS('Project Records_v2'!A:A,"2022",'Project Records_v2'!M:M,"Retail Sales") -> 1 | N5: 2022 | O5: =COUNTIFS('Project Records_v2'!A:A,"2022",'Project Records_v2'!J:J,"UP System") -> 18 | P5: =COUNTIFS('Project Records_v2'!A:A,"2022",'Project Records_v2'!J:J,"SUC/HEI") -> 3 | Q5: =COUNTIFS('Project Records_v2'!A:A,"2022",'Project Records_v2'!J:J,"Government") -> 0 | R5: =COUNTIFS('Project Records_v2'!A:A,"2022",'Project Records_v2'!J:J,"Private/Local") -> 0 | S5: =COUNTIFS('Project Records_v2'!A:A,"2022",'Project Records_v2'!J:J,"International") -> 0
